Workbook

Sheet Ledger
A1: DIPSEVA LEDGER • Issue=भाड्याने दिले • Return=परत आले • Payment=पैसे जमा
A2: Date तारीख | B2: Customer ग्राहक | C2: Type प्रकार | D2: Item ID कोड | E2: Item Name वस्तू | F2: Qty नग | G2: Rate भाडे | H2: Bill ₹ बिल | I2: Paid ₹ जमा | J2: Pay Mode पेमेंट | K2: Note नोंद
A3: 46204 | B3: Yogesh Caterers | C3: Issue | D3: CTRNG | E3: =IF($D3="","",IFERROR(XLOOKUP($D3,Items!$A:$A,Items!$B:$B),"ERR")) | F3: 1 | G3: 850 | H3: =IF($C3="Issue",IFERROR($F3*$G3,0),0) | I3: 600 | J3: Cash
A4: 46204 | B4: Samarth Sound | C4: Issue | D4: GD | E4: =IF($D4="","",IFERROR(XLOOKUP($D4,Items!$A:$A,Items!$B:$B),"ERR")) | F4: 10 | G4: 15 | H4: =IF($C4="Issue",IFERROR($F4*$G4,0),0) | I4: 150 | J4: Cash
A5: 46204 | B5: Samarth Sound | C5: Issue | D5: AAH | E5: =IF($D5="","",IFERROR(XLOOKUP($D5,Items!$A:$A,Items!$B:$B),"ERR")) | F5: 1 | G5: 800 | H5: =IF($C5="Issue",IFERROR($F5*$G5,0),0) | I5: 800 | J5: Cash
A6: 46204 | B6: Tulja Bhavani Mandap | C6: Issue | D6: CH | E6: =IF($D6="","",IFERROR(XLOOKUP($D6,Items!$A:$A,Items!$B:$B),"ERR")) | F6: 20 | G6: 4 | H6: =IF($C6="Issue",IFERROR($F6*$G6,0),0)
A7: 46204 | B7: Tulja Bhavani Mandap | C7: Issue | D7: CH | E7: =IF($D7="","",IFERROR(XLOOKUP($D7,Items!$A:$A,Items!$B:$B),"ERR")) | F7: 70 | G7: 4 | H7: =IF($C7="Issue",IFERROR($F7*$G7,0),0)
A8: 46204 | B8: CASH | C8: Issue | D8: TBL | E8: =IF($D8="","",IFERROR(XLOOKUP($D8,Items!$A:$A,Items!$B:$B),"ERR")) | F8: 39 | G8: 20 | H8: =IF($C8="Issue",IFERROR($F8*$G8,0),0) | I8: 1000 | J8: Cash | K8: OLD 1000 FIX->780 Avinash gaikwad
A9: 46204 | B9: CASH | C9: Issue | D9: DSH | E9: =IF($D9="","",IFERROR(XLOOKUP($D9,Items!$A:$A,Items!$B:$B),"ERR")) | F9: 200 | G9: 2 | H9: =IF($C9="Issue",IFERROR($F9*$G9,0),0) | I9: 540 | J9: Cash | K9: OLD 540 FIX->400 Avinash gaikwad
A10: 46206 | B10: CASH | C10: Issue | D10: CTRNG | E10: =IF($D10="","",IFERROR(XLOOKUP($D10,Items!$A:$A,Items!$B:$B),"ERR")) | F10: 1 | G10: 50 | H10: =IF($C10="Issue",IFERROR($F10*$G10,0),0) | K10: Vijay jadhav
A11: 46206 | B11: Sunil Garandwal | C11: Issue | D11: HLC | E11: =IF($D11="","",IFERROR(XLOOKUP($D11,Items!$A:$A,Items!$B:$B),"ERR")) | F11: 1 | G11: 300 | H11: =IF($C11="Issue",IFERROR($F11*$G11,0),0) | I11: 300 | J11: Cash
A12: 46207 | B12: Abhiman Kharat | C12: Issue | D12: CTRNG | E12: =IF($D12="","",IFERROR(XLOOKUP($D12,Items!$A:$A,Items!$B:$B),"ERR")) | F12: 1 | G12: 330 | H12: =IF($C12="Issue",IFERROR($F12*$G12,0),0) | I12: 100 | J12: Cash
A13: 46206 | B13: Ganesh Mandap T | C13: Issue | D13: CTRNG | E13: =IF($D13="","",IFERROR(XLOOKUP($D13,Items!$A:$A,Items!$B:$B),"ERR")) | F13: 1 | G13: 450 | H13: =IF($C13="Issue",IFERROR($F13*$G13,0),0)
A14: 46206 | B14: Ganesh Mandap T | C14: Issue | D14: HLC | E14: =IF($D14="","",IFERROR(XLOOKUP($D14,Items!$A:$A,Items!$B:$B),"ERR")) | F14: 1 | G14: 300 | H14: =IF($C14="Issue",IFERROR($F14*$G14,0),0)
A15: 46206 | B15: Atul Salve | C15: Payment | E15: =IF($D15="","",IFERROR(XLOOKUP($D15,Items!$A:$A,Items!$B:$B),"ERR")) | G15: =IF($D15="","",IFERROR(XLOOKUP($D15,Items!$A:$A,Items!$D:$D),0)) | H15: =IF($C15="Issue",IFERROR($F15*$G15,0),0) | I15: 1000 | K15: Advance
A16: 46207 | B16: Vishva Mandap | C16: Issue | D16: SMI | E16: =IF($D16="","",IFERROR(XLOOKUP($D16,Items!$A:$A,Items!$B:$B),"ERR")) | F16: 1 | G16: 300 | H16: =IF($C16="Issue",IFERROR($F16*$G16,0),0) | I16: 300 | J16: Cash
A17: 46207 | B17: Vishva Mandap | C17: Issue | D17: CHCVR | E17: =IF($D17="","",IFERROR(XLOOKUP($D17,Items!$A:$A,Items!$B:$B),"ERR")) | F17: 10 | G17: 10 | H17: =IF($C17="Issue",IFERROR($F17*$G17,0),0) | I17: 100 | J17: Cash
A18: 46207 | B18: Vishva Mandap | C18: Return | D18: CHCVR | E18: =IF($D18="","",IFERROR(XLOOKUP($D18,Items!$A:$A,Items!$B:$B),"ERR")) | F18: 1 | G18: =IF($D18="","",IFERROR(XLOOKUP($D18,Items!$A:$A,Items!$D:$D),0)) | H18: =IF($C18="Issue",IFERROR($F18*$G18,0),0) | K18: old Return
A19: 46208 | B19: Ayush Mandap | C19: Issue | D19: PLN | E19: =IF($D19="","",IFERROR(XLOOKUP($D19,Items!$A:$A,Items!$B:$B),"ERR")) | F19: 1 | G19: 500 | H19: =IF($C19="Issue",IFERROR($F19*$G19,0),0)
A20: 46208 | B20: Ayush Mandap | C20: Issue | D20: MSF | E20: =IF($D20="","",IFERROR(XLOOKUP($D20,Items!$A:$A,Items!$B:$B),"ERR")) | F20: 1 | G20: 700 | H20: =IF($C20="Issue",IFERROR($F20*$G20,0),0) | I20: 700 | J20: Cash
A21: 46208 | B21: Ayush Mandap | C21: Issue | D21: TBL | E21: =IF($D21="","",IFERROR(XLOOKUP($D21,Items!$A:$A,Items!$B:$B),"ERR")) | F21: 15 | G21: 20 | H21: =IF($C21="Issue",IFERROR($F21*$G21,0),0) | I21: 300 | J21: Cash
A22: 46208 | B22: Ayush Mandap | C22: Return | D22: TBL | E22: =IF($D22="","",IFERROR(XLOOKUP($D22,Items!$A:$A,Items!$B:$B),"ERR")) | F22: 1 | G22: =IF($D22="","",IFERROR(XLOOKUP($D22,Items!$A:$A,Items!$D:$D),0)) | H22: =IF($C22="Issue",IFERROR($F22*$G22,0),0) | K22: old Return
A23: 46208 | B23: Ayush Mandap | C23: Issue | D23: SHF | E23: =IF($D23="","",IFERROR(XLOOKUP($D23,Items!$A:$A,Items!$B:$B),"ERR")) | F23: 5 | G23: 50 | H23: =IF($C23="Issue",IFERROR($F23*$G23,0),0) | I23: 250 | J23: Cash
A24: 46208 | B24: Ayush Mandap | C24: Return | D24: SHF | E24: =IF($D24="","",IFERROR(XLOOKUP($D24,Items!$A:$A,Items!$B:$B),"ERR")) | F24: 1 | G24: =IF($D24="","",IFERROR(XLOOKUP($D24,Items!$A:$A,Items!$D:$D),0)) | H24: =IF($C24="Issue",IFERROR($F24*$G24,0),0) | K24: old Return
A25: 46208 | B25: Ayush Mandap | C25: Issue | D25: PLN | E25: =IF($D25="","",IFERROR(XLOOKUP($D25,Items!$A:$A,Items!$B:$B),"ERR")) | F25: 1 | G25: 500 | H25: =IF($C25="Issue",IFERROR($F25*$G25,0),0) | I25: 500 | J25: Cash
A26: 46208 | B26: Yogesh Caterers | C26: Issue | D26: CTRNG | E26: =IF($D26="","",IFERROR(XLOOKUP($D26,Items!$A:$A,Items!$B:$B),"ERR")) | F26: 1 | G26: 900 | H26: =IF($C26="Issue",IFERROR($F26*$G26,0),0)
A27: 46207 | B27: CASH | C27: Issue | D27: FN | E27: =IF($D27="","",IFERROR(XLOOKUP($D27,Items!$A:$A,Items!$B:$B),"ERR")) | F27: 4 | G27: 150 | H27: =IF($C27="Issue",IFERROR($F27*$G27,0),0) | I27: 600 | J27: Cash | K27: Ajay Hiwrale
A28: 46204 | B28: CASH | C28: Issue | D28: GD SET | E28: =IF($D28="","",IFERROR(XLOOKUP($D28,Items!$A:$A,Items!$B:$B),"ERR")) | F28: 10 | G28: 100 | H28: =IF($C28="Issue",IFERROR($F28*$G28,0),0) | I28: 1000 | J28: Cash
A29: 46204 | B29: CASH | C29: Issue | D29: RTBL | E29: =IF($D29="","",IFERROR(XLOOKUP($D29,Items!$A:$A,Items!$B:$B),"ERR")) | F29: 1 | G29: 200 | H29: =IF($C29="Issue",IFERROR($F29*$G29,0),0) | I29: 200 | J29: Cash
A30: 46204 | B30: CASH | C30: Issue | D30: PRD | E30: =IF($D30="","",IFERROR(XLOOKUP($D30,Items!$A:$A,Items!$B:$B),"ERR")) | F30: 1 | G30: 100 | H30: =IF($C30="Issue",IFERROR($F30*$G30,0),0) | I30: 100 | J30: Cash
A31: 46207 | B31: CASH | C31: Issue | D31: DRM | E31: =IF($D31="","",IFERROR(XLOOKUP($D31,Items!$A:$A,Items!$B:$B),"ERR")) | F31: 1 | G31: 20 | H31: =IF($C31="Issue",IFERROR($F31*$G31,0),0) | I31: 120 | J31: Cash | K31: OLD 120 FIX->20 Pritam patil
A32: 46208 | B32: CASH | C32: Issue | D32: CH | E32: =IF($D32="","",IFERROR(XLOOKUP($D32,Items!$A:$A,Items!$B:$B),"ERR")) | F32: 5 | G32: 10 | H32: =IF($C32="Issue",IFERROR($F32*$G32,0),0) | I32: 50 | J32: Cash
A33: 46208 | B33: CASH | C33: Return | D33: CH | E33: =IF($D33="","",IFERROR(XLOOKUP($D33,Items!$A:$A,Items!$B:$B),"ERR")) | F33: 1 | G33: =IF($D33="","",IFERROR(XLOOKUP($D33,Items!$A:$A,Items!$D:$D),0)) | H33: =IF($C33="Issue",IFERROR($F33*$G33,0),0) | K33: old Return
A34: 46208 | B34: CASH | C34: Issue | D34: DSH | E34: =IF($D34="","",IFERROR(XLOOKUP($D34,Items!$A:$A,Items!$B:$B),"ERR")) | F34: 50 | G34: 4 | H34: =IF($C34="Issue",IFERROR($F34*$G34,0),0) | I34: 250 | J34: Cash | K34: OLD 250 FIX->200 Prem Pandit
A35: 46208 | B35: CASH | C35: Return | D35: DSH | E35: =IF($D35="","",IFERROR(XLOOKUP($D35,Items!$A:$A,Items!$B:$B),"ERR")) | F35: 1 | G35: =IF($D35="","",IFERROR(XLOOKUP($D35,Items!$A:$A,Items!$D:$D),0)) | H35: =IF($C35="Issue",IFERROR($F35*$G35,0),0) | K35: old Return
A36: 46209 | B36: CASH | C36: Issue | D36: MT | E36: =IF($D36="","",IFERROR(XLOOKUP($D36,Items!$A:$A,Items!$B:$B),"ERR")) | F36: 2 | G36: 50 | H36: =IF($C36="Issue",IFERROR($F36*$G36,0),0) | I36: 100 | J36: Cash | K36: Vijay Dabhade
A37: 46209 | B37: CASH | C37: Return | D37: MT | E37: =IF($D37="","",IFERROR(XLOOKUP($D37,Items!$A:$A,Items!$B:$B),"ERR")) | F37: 1 | G37: =IF($D37="","",IFERROR(XLOOKUP($D37,Items!$A:$A,Items!$D:$D),0)) | H37: =IF($C37="Issue",IFERROR($F37*$G37,0),0) | K37: old Return
A38: 46208 | B38: CASH | C38: Issue | D38: ASN | E38: =IF($D38="","",IFERROR(XLOOKUP($D38,Items!$A:$A,Items!$B:$B),"ERR")) | F38: 8 | G38: 20 | H38: =IF($C38="Issue",IFERROR($F38*$G38,0),0) | I38: 160 | J38: Cash
A39: 46208 | B39: CASH | C39: Return | D39: ASN | E39: =IF($D39="","",IFERROR(XLOOKUP($D39,Items!$A:$A,Items!$B:$B),"ERR")) | F39: 1 | G39: =IF($D39="","",IFERROR(XLOOKUP($D39,Items!$A:$A,Items!$D:$D),0)) | H39: =IF($C39="Issue",IFERROR($F39*$G39,0),0) | K39: old Return
A40: 46209 | B40: CASH | C40: Issue | D40: CTRNG | E40: =IF($D40="","",IFERROR(XLOOKUP($D40,Items!$A:$A,Items!$B:$B),"ERR")) | F40: 1 | G40: 100 | H40: =IF($C40="Issue",IFERROR($F40*$G40,0),0) | I40: 100 | J40: Cash
A41: 46210 | B41: CASH | C41: Issue | D41: THRMS | E41: =IF($D41="","",IFERROR(XLOOKUP($D41,Items!$A:$A,Items!$B:$B),"ERR")) | F41: 1 | G41: 50 | H41: =IF($C41="Issue",IFERROR($F41*$G41,0),0) | K41: Bhagwat Pawar
A42: 46211 | B42: CASH | C42: Issue | D42: CH | E42: =IF($D42="","",IFERROR(XLOOKUP($D42,Items!$A:$A,Items!$B:$B),"ERR")) | F42: 37 | G42: 10 | H42: =IF($C42="Issue",IFERROR($F42*$G42,0),0) | I42: 370 | J42: Cash
A43: 46211 | B43: CASH | C43: Issue | D43: TBL | E43: =IF($D43="","",IFERROR(XLOOKUP($D43,Items!$A:$A,Items!$B:$B),"ERR")) | F43: 9 | G43: 20 | H43: =IF($C43="Issue",IFERROR($F43*$G43,0),0) | I43: 180 | J43: Cash
A44: 46211 | B44: CASH | C44: Issue | D44: FRL | E44: =IF($D44="","",IFERROR(XLOOKUP($D44,Items!$A:$A,Items!$B:$B),"ERR")) | F44: 5 | G44: 30 | H44: =IF($C44="Issue",IFERROR($F44*$G44,0),0) | I44: 150 | J44: Cash
A45: 46212 | B45: CASH | C45: Issue | D45: CTRNG | E45: =IF($D45="","",IFERROR(XLOOKUP($D45,Items!$A:$A,Items!$B:$B),"ERR")) | F45: 1 | G45: 275 | H45: =IF($C45="Issue",IFERROR($F45*$G45,0),0) | I45: 275 | J45: Cash
A46: 46212 | B46: CASH | C46: Issue | D46: CH | E46: =IF($D46="","",IFERROR(XLOOKUP($D46,Items!$A:$A,Items!$B:$B),"ERR")) | F46: 4 | G46: 10 | H46: =IF($C46="Issue",IFERROR($F46*$G46,0),0) | I46: 40 | J46: Cash
A47: 46212 | B47: CASH | C47: Issue | D47: ASN | E47: =IF($D47="","",IFERROR(XLOOKUP($D47,Items!$A:$A,Items!$B:$B),"ERR")) | F47: 8 | G47: 10 | H47: =IF($C47="Issue",IFERROR($F47*$G47,0),0) | I47: 80 | J47: Cash
A48: 46213 | B48: CASH | C48: Issue | D48: AB | E48: =IF($D48="","",IFERROR(XLOOKUP($D48,Items!$A:$A,Items!$B:$B),"ERR")) | F48: 1 | G48: 500 | H48: =IF($C48="Issue",IFERROR($F48*$G48,0),0)
A49: 46213 | B49: CASH | C49: Issue | D49: CTRNG | E49: =IF($D49="","",IFERROR(XLOOKUP($D49,Items!$A:$A,Items!$B:$B),"ERR")) | F49: 1 | G49: 100 | H49: =IF($C49="Issue",IFERROR($F49*$G49,0),0) | K49: Prem Jangale
A50: 46213 | B50: CASH | C50: Issue | D50: CTRNG | E50: =IF($D50="","",IFERROR(XLOOKUP($D50,Items!$A:$A,Items!$B:$B),"ERR")) | F50: 1 | G50: 100 | H50: =IF($C50="Issue",IFERROR($F50*$G50,0),0)
A51: 46213 | B51: CASH | C51: Issue | D51: SMI | E51: =IF($D51="","",IFERROR(XLOOKUP($D51,Items!$A:$A,Items!$B:$B),"ERR")) | F51: 1 | G51: 300 | H51: =IF($C51="Issue",IFERROR($F51*$G51,0),0) | K51: Indriya Jewellers
A52: 46208 | B52: Shri Decorators | C52: Issue | D52: SF | E52: =IF($D52="","",IFERROR(XLOOKUP($D52,Items!$A:$A,Items!$B:$B),"ERR")) | F52: 2 | G52: 150 | H52: =IF($C52="Issue",IFERROR($F52*$G52,0),0) | I52: 300 | J52: Cash
A53: 46208 | B53: Shri Decorators | C53: Return | D53: SF | E53: =IF($D53="","",IFERROR(XLOOKUP($D53,Items!$A:$A,Items!$B:$B),"ERR")) | F53: 1 | G53: =IF($D53="","",IFERROR(XLOOKUP($D53,Items!$A:$A,Items!$D:$D),0)) | H53: =IF($C53="Issue",IFERROR($F53*$G53,0),0) | K53: old Return
A54: 46209 | B54: Nagve Patil Caterers | C54: Issue | D54: CTRNG | E54: =IF($D54="","",IFERROR(XLOOKUP($D54,Items!$A:$A,Items!$B:$B),"ERR")) | F54: 1 | G54: 50 | H54: =IF($C54="Issue",IFERROR($F54*$G54,0),0) | I54: 50 | J54: Cash
A55: 46210 | B55: Dip Mandap | C55: Issue | D55: SF | E55: =IF($D55="","",IFERROR(XLOOKUP($D55,Items!$A:$A,Items!$B:$B),"ERR")) | F55: 1 | G55: 150 | H55: =IF($C55="Issue",IFERROR($F55*$G55,0),0) | I55: 150 | J55: Cash
A56: 46210 | B56: Dip Mandap | C56: Issue | D56: CTRNG | E56: =IF($D56="","",IFERROR(XLOOKUP($D56,Items!$A:$A,Items!$B:$B),"ERR")) | F56: 3 | G56: 50 | H56: =IF($C56="Issue",IFERROR($F56*$G56,0),0) | I56: 150 | J56: Cash | K56: Sofa Cover
A57: 46210 | B57: Dip Mandap | C57: Return | D57: CTRNG | E57: =IF($D57="","",IFERROR(XLOOKUP($D57,Items!$A:$A,Items!$B:$B),"ERR")) | F57: 1 | G57: =IF($D57="","",IFERROR(XLOOKUP($D57,Items!$A:$A,Items!$D:$D),0)) | H57: =IF($C57="Issue",IFERROR($F57*$G57,0),0) | K57: old Return
A58: 46210 | B58: Dip Mandap | C58: Issue | D58: THRMS | E58: =IF($D58="","",IFERROR(XLOOKUP($D58,Items!$A:$A,Items!$B:$B),"ERR")) | F58: 1 | G58: 50 | H58: =IF($C58="Issue",IFERROR($F58*$G58,0),0) | I58: 50 | J58: Cash
A59: 46210 | B59: Mahalakshmi Mandap | C59: Issue | D59: CH | E59: =IF($D59="","",IFERROR(XLOOKUP($D59,Items!$A:$A,Items!$B:$B),"ERR")) | F59: 30 | G59: 4 | H59: =IF($C59="Issue",IFERROR($F59*$G59,0),0) | I59: 120 | J59: Cash
A60: 46210 | B60: Mahalakshmi Mandap | C60: Return | D60: CH | E60: =IF($D60="","",IFERROR(XLOOKUP($D60,Items!$A:$A,Items!$B:$B),"ERR")) | F60: 1 | G60: =IF($D60="","",IFERROR(XLOOKUP($D60,Items!$A:$A,Items!$D:$D),0)) | H60: =IF($C60="Issue",IFERROR($F60*$G60,0),0) | K60: old Return
A61: 46210 | B61: Mahalakshmi Mandap | C61: Issue | D61: TBL | E61: =IF($D61="","",IFERROR(XLOOKUP($D61,Items!$A:$A,Items!$B:$B),"ERR")) | F61: 1 | G61: 20 | H61: =IF($C61="Issue",IFERROR($F61*$G61,0),0) | I61: 20 | J61: Cash
A62: 46210 | B62: Rajdhani Mandap | C62: Issue | D62: GD SET | E62: =IF($D62="","",IFERROR(XLOOKUP($D62,Items!$A:$A,Items!$B:$B),"ERR")) | F62: 1 | G62: 6000 | H62: =IF($C62="Issue",IFERROR($F62*$G62,0),0) | I62: 4000 | J62: Cash
A63: 46210 | B63: Sunil Garandwal | C63: Issue | D63: GD | E63: =IF($D63="","",IFERROR(XLOOKUP($D63,Items!$A:$A,Items!$B:$B),"ERR")) | F63: 20 | G63: 15 | H63: =IF($C63="Issue",IFERROR($F63*$G63,0),0) | I63: 300 | J63: Cash
A64: 46210 | B64: Sunil Garandwal | C64: Return | D64: GD | E64: =IF($D64="","",IFERROR(XLOOKUP($D64,Items!$A:$A,Items!$B:$B),"ERR")) | F64: 1 | G64: =IF($D64="","",IFERROR(XLOOKUP($D64,Items!$A:$A,Items!$D:$D),0)) | H64: =IF($C64="Issue",IFERROR($F64*$G64,0),0) | K64: old Return
A65: 46210 | B65: Sunil Garandwal | C65: Issue | D65: CH | E65: =IF($D65="","",IFERROR(XLOOKUP($D65,Items!$A:$A,Items!$B:$B),"ERR")) | F65: 20 | G65: 4 | H65: =IF($C65="Issue",IFERROR($F65*$G65,0),0) | I65: 80 | J65: Cash
A66: 46210 | B66: Sunil Garandwal | C66: Return | D66: CH | E66: =IF($D66="","",IFERROR(XLOOKUP($D66,Items!$A:$A,Items!$B:$B),"ERR")) | F66: 1 | G66: =IF($D66="","",IFERROR(XLOOKUP($D66,Items!$A:$A,Items!$D:$D),0)) | H66: =IF($C66="Issue",IFERROR($F66*$G66,0),0) | K66: old Return
A67: 46211 | B67: Pruthviraj Mandap | C67: Issue | D67: CTRNG | E67: =IF($D67="","",IFERROR(XLOOKUP($D67,Items!$A:$A,Items!$B:$B),"ERR")) | F67: 1 | G67: 600 | H67: =IF($C67="Issue",IFERROR($F67*$G67,0),0) | I67: 600 | J67: Cash
E68: =IF($D68="","",IFERROR(XLOOKUP($D68,Items!$A:$A,Items!$B:$B),"ERR")) | G68: =IF($D68="","",IFERROR(XLOOKUP($D68,Items!$A:$A,Items!$D:$D),0)) | H68: =IF($C68="Issue",IFERROR($F68*$G68,0),0)
E69: =IF($D69="","",IFERROR(XLOOKUP($D69,Items!$A:$A,Items!$B:$B),"ERR")) | G69: =IF($D69="","",IFERROR(XLOOKUP($D69,Items!$A:$A,Items!$D:$D),0)) | H69: =IF($C69="Issue",IFERROR($F69*$G69,0),0)
E70: =IF($D70="","",IFERROR(XLOOKUP($D70,Items!$A:$A,Items!$B:$B),"ERR")) | G70: =IF($D70="","",IFERROR(XLOOKUP($D70,Items!$A:$A,Items!$D:$D),0)) | H70: =IF($C70="Issue",IFERROR($F70*$G70,0),0)
E71: =IF($D71="","",IFERROR(XLOOKUP($D71,Items!$A:$A,Items!$B:$B),"ERR")) | G71: =IF($D71="","",IFERROR(XLOOKUP($D71,Items!$A:$A,Items!$D:$D),0)) | H71: =IF($C71="Issue",IFERROR($F71*$G71,0),0)
E72: =IF($D72="","",IFERROR(XLOOKUP($D72,Items!$A:$A,Items!$B:$B),"ERR")) | G72: =IF($D72="","",IFERROR(XLOOKUP($D72,Items!$A:$A,Items!$D:$D),0)) | H72: =IF($C72="Issue",IFERROR($F72*$G72,0),0)
E73: =IF($D73="","",IFERROR(XLOOKUP($D73,Items!$A:$A,Items!$B:$B),"ERR")) | G73: =IF($D73="","",IFERROR(XLOOKUP($D73,Items!$A:$A,Items!$D:$D),0)) | H73: =IF($C73="Issue",IFERROR($F73*$G73,0),0)
E74: =IF($D74="","",IFERROR(XLOOKUP($D74,Items!$A:$A,Items!$B:$B),"ERR")) | G74: =IF($D74="","",IFERROR(XLOOKUP($D74,Items!$A:$A,Items!$D:$D),0)) | H74: =IF($C74="Issue",IFERROR($F74*$G74,0),0)
E75: =IF($D75="","",IFERROR(XLOOKUP($D75,Items!$A:$A,Items!$B:$B),"ERR")) | G75: =IF($D75="","",IFERROR(XLOOKUP($D75,Items!$A:$A,Items!$D:$D),0)) | H75: =IF($C75="Issue",IFERROR($F75*$G75,0),0)
E76: =IF($D76="","",IFERROR(XLOOKUP($D76,Items!$A:$A,Items!$B:$B),"ERR")) | G76: =IF($D76="","",IFERROR(XLOOKUP($D76,Items!$A:$A,Items!$D:$D),0)) | H76: =IF($C76="Issue",IFERROR($F76*$G76,0),0)
E77: =IF($D77="","",IFERROR(XLOOKUP($D77,Items!$A:$A,Items!$B:$B),"ERR")) | G77: =IF($D77="","",IFERROR(XLOOKUP($D77,Items!$A:$A,Items!$D:$D),0)) | H77: =IF($C77="Issue",IFERROR($F77*$G77,0),0)
E78: =IF($D78="","",IFERROR(XLOOKUP($D78,Items!$A:$A,Items!$B:$B),"ERR")) | G78: =IF($D78="","",IFERROR(XLOOKUP($D78,Items!$A:$A,Items!$D:$D),0)) | H78: =IF($C78="Issue",IFERROR($F78*$G78,0),0)
E79: =IF($D79="","",IFERROR(XLOOKUP($D79,Items!$A:$A,Items!$B:$B),"ERR")) | G79: =IF($D79="","",IFERROR(XLOOKUP($D79,Items!$A:$A,Items!$D:$D),0)) | H79: =IF($C79="Issue",IFERROR($F79*$G79,0),0)
... E1002: =IF($D1002="","",IFERROR(XLOOKUP($D1002,Items!$A:$A,Items!$B:$B),"ERR")) | G1002: =IF($D1002="","",IFERROR(XLOOKUP($D1002,Items!$A:$A,Items!$D:$D),0)) | H1002: =IF($C1002="Issue",IFERROR($F1002*$G1002,0),0)

Sheet Items
A1: ITEMS • वस्तू यादी • भाडे येथूनच Ledger मध्ये auto येईल
A2: Item ID कोड | B2: Item Name वस्तू (EN) | C2: Item Marathi वस्तू (मराठी) | D2: Rate ₹ भाडे | E2: Opening Stock सुरुवातीचा माल | F2: Min Stock किमान | G2: Note
A3: OP BAL | B3: Opening Balance | C3: ओपनिंग | D3: 0
A4: CTRNG | B4: CTRNG | C4: केटरिंग | D4: 0
A5: JC | B5: Jumbo Cooler | C5: जंबो कुलर | D5: 500
A6: CH | B6: Chair | C6: खुर्ची | D6: 4 | E6: 600 | F6: 100
A7: RTBL | B7: Round Table | C7: गोल टेबल | D7: 125
A8: FN | B8: Fan | C8: पंखा | D8: 100
A9: GD | B9: Gadi | C9: गादी | D9: 15
A10: DRM | B10: Drum | C10: ड्रम | D10: 20
A11: TBL | B11: Table | C11: टेबल | D11: 20
A12: AB | B12: Ahuja Speaker | C12: अहुजा स्पीकर | D12: 500
A13: SMI | B13: Samai | C13: समई | D13: 300
A14: WBS | B14: Wash Basin | C14: वॉश बेसिन | D14: 200
A15: BS | B15: Bedsheet | C15: चादर | D15: 5
A16: PLN | B16: Palna | C16: पाळणा | D16: 500
A17: Sm Culr | B17: Small Cooler | C17: छोटा कुलर | D17: 200
A18: FRL | B18: Freel | C18: फ्रिल | D18: 30
... A40: SHF | B40: Shafing Dish | C40: शेफिंग डिश | D40: 50
A41: CSH | B41: CASH | D41: 0
A42: CHD | B42: Chadar | C42: चादर | D42: 10
A43: MT | B43: Matt | C43: मॅट | D43: 30
A44: HW | B44: Hawan Kund | C44: हवन कुंड | D44: 100
A45: DSH | B45: Dish | C45: डिश | D45: 1
A46: PD | B46: Podium | C46: पोडियम | D46: 300
A47: STFRM | B47: Stage Frame | C47: स्टेज फ्रेम | D47: 100
A48: BFR | B48: Buffer | C48: बफर | D48: 100
A49: GDR | B49: Grinder | C49: ग्राइंडर | D49: 300
A50: BK FRL | B50: Black Freel | C50: काळा फ्रिल | D50: 30
A51: THRMS | B51: Thermos | C51: थर्मास | D51: 50
A52: PIPE | B52: PIPE | C52: पाईप | D52: 10
A53: RECPT | B53: RECPT | D53: 0
A54: GD SET | B54: Gadi Set | C54: गादी सेट | D54: 30
A55: Table CVR | B55: Table Cover | C55: टेबल कव्हर | D55: 0
A56: STRN | B56: Satranji | C56: सतरंजी | D56: 50
A57: DIAS | B57: Podium | C57: पोडियम | D57: 300

Sheet Customers
A1: CUSTOMERS • ग्राहक यादी • नाव एकदाच लिहा
A2: Customer ग्राहक | B2: Contact Person व्यक्ती | C2: Phone फोन | D2: Type मंडप/केटरर्स | E2: Address / Marathi Name पत्ता | F2: Opening Due ₹ जुनी बाकी
A3: Ayush Mandap | B3: Ajay Kulkarni | D3: Mandap | F3: 0
A4: Ganesh Mandap T | B4: Shyam Thakur | D4: Mandap | E4: विष्णु ठाकूर | F4: 0
A5: Yogesh Caterers | B5: Anand Bansode | D5: Caterers | F5: 0
A6: Tulja Bhavani Mandap | B6: Sanju Khoje | D6: Mandap | E6: तुळजा भवानी मंडप | F6: 0
A7: Abhiman Kharat | B7: Abhiman Kharat | D7: Caterers | F7: 0
A8: G S Event | B8: Guddu Shinde | D8: Mandap | E8: गुड्डू शिंदे | F8: 0
A9: Jay Hari Mandap | B9: Krushna Panchal | D9: Mandap | E9: पांचाळ महाराज | F9: 0
A10: Maitri Mandap | B10: Sanket Yeole | D10: Mandap | E10: संकेत येवले | F10: 0
A11: Pruthviraj Mandap | B11: Kishor Bhalerao | D11: Mandap | E11: पृथ्वीराज मंडप | F11: 0
A12: Ankit bajaj | B12: Ankit bajaj | D12: Mandap | F12: 0
A13: Saileela Caterers | B13: Sandeep Sontakke | D13: Caterers | E13: संदीप सोनटक्के | F13: 0
A14: Sant Shiromani Mandap | B14: Babasaheb Dabhade | D14: Mandap | E14: संत शिरोमणी मंडप | F14: 0
A15: Ajay Mandap | B15: Ajay Kharat | D15: Mandap | E15: अजय खरात | F15: 0
A16: Sai Pooja Caterers | B16: Sunil Nayar | D16: Caterers | E16: सुनील नायर | F16: 0
A17: Pathare Mandap | B17: Sachin Pathare | D17: Mandap | E17: पठारे मंडप | F17: 0
A18: Golden Mandap | B18: Altaf Patel | D18: Mandap | E18: गोल्डन मंडप | F18: 0
A19: Hotel Ecotel | B19: Kshirsagar | D19: Mandap | F19: 0
A20: Nilesh Chaudahary | B20: Nilesh Chaudahary | D20: Mandap | F20: 0
A21: Renuka Mandap | B21: Rohidas Igve | D21: Mandap | F21: 0
A22: Gautam Kirtikar | B22: Gautam Kirtikar | D22: Mandap | F22: 0
A23: Pawan Dhakne | B23: Pawan Dhakne | D23: Caterers | F23: 0
A24: Sai Shraddha Caterers | B24: Kishor Shinde | D24: Caterers | E24: किशोर शिंदे | F24: 0
A25: B R Mandap | B25: PArvez Shaikh | D25: Mandap | E25: बि आर मंडप | F25: 0
A26: Abdul Rikshaw | B26: Abdul Rikshaw | D26: Mandap | F26: 0
A27: Matoshree lawns | B27: Sachin Wagh | D27: Mandap | F27: 0
A28: Dipak Nikam | B28: Dipak Nikam | D28: Mandap | F28: 0
A29: Balaji Mandap G | B29: Giriraj Uplenchwar | D29: Mandap | E29: बालाजी मंडप | F29: 0
A30: Kishor Mandap | B30: Kishor Chaudhari | D30: Mandap | F30: 0
A31: Mahadev Umrikar | B31: Mahadev Umrikar | D31: Caterers | F31: 0
A32: Balaji Mandap K | B32: Khandre Mama | D32: Mandap | F32: 0
A33: Dashrath Caterers | B33: Babasaheb Borade | D33: Caterers | F33: 0
A34: Dip Mandap | B34: Bhagwat Pawar | D34: Mandap | F34: 0
A35: Dipak Nawale | B35: Dipak Nawale | D35: Mandap | F35: 0
A36: Ganesh Mandap K | B36: Ganesh Kale | D36: Mandap | F36: 0
A37: Kshirsagar Mandap R | B37: Raju Kshirsagar | D37: Mandap | F37: 0
A38: Kshirsagar Mandap S | B38: Shyam Kshirsagar | D38: Mandap | F38: 0
A39: Mahalakshmi Mandap | B39: Abasaheb Tawar | D39: Mandap | F39: 0
A40: Mauli Mandap | B40: Shravan Vaidya | D40: Mandap | F40: 0
A41: Sachin Mandap | B41: Jaydave Gande | D41: Mandap | F41: 0
... A78: Samarth Sound | B78: Ganesh Karangale | D78: Mandap | F78: 0
A79: Atul Salve | B79: Atul Salve | D79: Mandap | E79: अतुल साळवे | F79: 0
A80: CASH | B80: Cash Customer | D80: Mandap | F80: 0
A81: Shri Decorators | B81: Pramod Pawar | D81: Mandap | F81: 0
A82: Rajdhani Mandap | B82: Dipak Bagul | D82: Mandap | F82: 0

Sheet Dashboard
A1: DIPSEVA • डॅशबोर्ड • आजची स्थिती एका नजरेत
A2: सर्व आकडे Ledger मधून auto — येथे टाइप करू नका. फक्त H2 तारीख बदला. | G2: Today / आज: | H2: 46218
A3: Total Billed • एकूण बिल | B3: Total Received • जमा | C3: Pending • येणे बाकी | E3: Today Collection • आजची जमा | F3: Today Billed • आजचे बिल | G3: Due Customers • थकबाकीदार | H3: Issue rows
A4: =SUM(Ledger!$H$3:$H$1002) | B4: =SUM(Ledger!$I$3:$I$1002) | C4: =B4-C4 | E4: =SUMIFS(Ledger!$I$3:$I$1002,Ledger!$A$3:$A$1002,$H$2) | F4: =SUMIFS(Ledger!$H$3:$H$1002,Ledger!$A$3:$A$1002,$H$2) | G4: =SUMPRODUCT((Khata!$E$3:$E$202>0)*(Khata!$A$3:$A$202<>"")) | H4: =COUNTIF(Ledger!$C$3:$C$1002,"Issue")
A6: TOP PENDING CUSTOMERS • जास्त बाकी असलेले ग्राहक
A7: # | B7: Customer / ग्राहक | C7: Billed | D7: Received | E7: Pending | F7: Given | G7: Returned | H7: Outside
A8: =1 | B8: =IFERROR(INDEX(Khata!$A:$A,MATCH(LARGE(Khata!$E$3:$E$202,1),Khata!$E$3:$E$202,0)),"") | C8: =IF($B8="","",SUMIFS(Ledger!$H$3:$H$1002,Ledger!$B$3:$B$1002,$B8)+XLOOKUP($B8,Customers!$A:$A,Customers!$F:$F,0)) | D8: =IF($B8="","",SUMIFS(Ledger!$I$3:$I$1002,Ledger!$B$3:$B$1002,$B8)) | E8: =IF($B8="","",$C8-$D8) | F8: =IF($B8="","",SUMIFS(Ledger!$F$3:$F$1002,Ledger!$B$3:$B$1002,$B8,Ledger!$C$3:$C$1002,"Issue")) | G8: =IF($B8="","",SUMIFS(Ledger!$F$3:$F$1002,Ledger!$B$3:$B$1002,$B8,Ledger!$C$3:$C$1002,"Return")) | H8: =IF($B8="","",$F8-$G8)
A9: =2 | B9: =IFERROR(INDEX(Khata!$A:$A,MATCH(LARGE(Khata!$E$3:$E$202,2),Khata!$E$3:$E$202,0)),"") | C9: =IF($B9="","",SUMIFS(Ledger!$H$3:$H$1002,Ledger!$B$3:$B$1002,$B9)+XLOOKUP($B9,Customers!$A:$A,Customers!$F:$F,0)) | D9: =IF($B9="","",SUMIFS(Ledger!$I$3:$I$1002,Ledger!$B$3:$B$1002,$B9)) | E9: =IF($B9="","",$C9-$D9) | F9: =IF($B9="","",SUMIFS(Ledger!$F$3:$F$1002,Ledger!$B$3:$B$1002,$B9,Ledger!$C$3:$C$1002,"Issue")) | G9: =IF($B9="","",SUMIFS(Ledger!$F$3:$F$1002,Ledger!$B$3:$B$1002,$B9,Ledger!$C$3:$C$1002,"Return")) | H9: =IF($B9="","",$F9-$G9)
A10: =3 | B10: =IFERROR(INDEX(Khata!$A:$A,MATCH(LARGE(Khata!$E$3:$E$202,3),Khata!$E$3:$E$202,0)),"") | C10: =IF($B10="","",SUMIFS(Ledger!$H$3:$H$1002,Ledger!$B$3:$B$1002,$B10)+XLOOKUP($B10,Customers!$A:$A,Customers!$F:$F,0)) | D10: =IF($B10="","",SUMIFS(Ledger!$I$3:$I$1002,Ledger!$B$3:$B$1002,$B10)) | E10: =IF($B10="","",$C10-$D10) | F10: =IF($B10="","",SUMIFS(Ledger!$F$3:$F$1002,Ledger!$B$3:$B$1002,$B10,Ledger!$C$3:$C$1002,"Issue")) | G10: =IF($B10="","",SUMIFS(Ledger!$F$3:$F$1002,Ledger!$B$3:$B$1002,$B10,Ledger!$C$3:$C$1002,"Return")) | H10: =IF($B10="","",$F10-$G10)
A11: =4 | B11: =IFERROR(INDEX(Khata!$A:$A,MATCH(LARGE(Khata!$E$3:$E$202,4),Khata!$E$3:$E$202,0)),"") | C11: =IF($B11="","",SUMIFS(Ledger!$H$3:$H$1002,Ledger!$B$3:$B$1002,$B11)+XLOOKUP($B11,Customers!$A:$A,Customers!$F:$F,0)) | D11: =IF($B11="","",SUMIFS(Ledger!$I$3:$I$1002,Ledger!$B$3:$B$1002,$B11)) | E11: =IF($B11="","",$C11-$D11) | F11: =IF($B11="","",SUMIFS(Ledger!$F$3:$F$1002,Ledger!$B$3:$B$1002,$B11,Ledger!$C$3:$C$1002,"Issue")) | G11: =IF($B11="","",SUMIFS(Ledger!$F$3:$F$1002,Ledger!$B$3:$B$1002,$B11,Ledger!$C$3:$C$1002,"Return")) | H11: =IF($B11="","",$F11-$G11)
A12: =5 | B12: =IFERROR(INDEX(Khata!$A:$A,MATCH(LARGE(Khata!$E$3:$E$202,5),Khata!$E$3:$E$202,0)),"") | C12: =IF($B12="","",SUMIFS(Ledger!$H$3:$H$1002,Ledger!$B$3:$B$1002,$B12)+XLOOKUP($B12,Customers!$A:$A,Customers!$F:$F,0)) | D12: =IF($B12="","",SUMIFS(Ledger!$I$3:$I$1002,Ledger!$B$3:$B$1002,$B12)) | E12: =IF($B12="","",$C12-$D12) | F12: =IF($B12="","",SUMIFS(Ledger!$F$3:$F$1002,Ledger!$B$3:$B$1002,$B12,Ledger!$C$3:$C$1002,"Issue")) | G12: =IF($B12="","",SUMIFS(Ledger!$F$3:$F$1002,Ledger!$B$3:$B$1002,$B12,Ledger!$C$3:$C$1002,"Return")) | H12: =IF($B12="","",$F12-$G12)
A13: =6 | B13: =IFERROR(INDEX(Khata!$A:$A,MATCH(LARGE(Khata!$E$3:$E$202,6),Khata!$E$3:$E$202,0)),"") | C13: =IF($B13="","",SUMIFS(Ledger!$H$3:$H$1002,Ledger!$B$3:$B$1002,$B13)+XLOOKUP($B13,Customers!$A:$A,Customers!$F:$F,0)) | D13: =IF($B13="","",SUMIFS(Ledger!$I$3:$I$1002,Ledger!$B$3:$B$1002,$B13)) | E13: =IF($B13="","",$C13-$D13) | F13: =IF($B13="","",SUMIFS(Ledger!$F$3:$F$1002,Ledger!$B$3:$B$1002,$B13,Ledger!$C$3:$C$1002,"Issue")) | G13: =IF($B13="","",SUMIFS(Ledger!$F$3:$F$1002,Ledger!$B$3:$B$1002,$B13,Ledger!$C$3:$C$1002,"Return")) | H13: =IF($B13="","",$F13-$G13)
A14: =7 | B14: =IFERROR(INDEX(Khata!$A:$A,MATCH(LARGE(Khata!$E$3:$E$202,7),Khata!$E$3:$E$202,0)),"") | C14: =IF($B14="","",SUMIFS(Ledger!$H$3:$H$1002,Ledger!$B$3:$B$1002,$B14)+XLOOKUP($B14,Customers!$A:$A,Customers!$F:$F,0)) | D14: =IF($B14="","",SUMIFS(Ledger!$I$3:$I$1002,Ledger!$B$3:$B$1002,$B14)) | E14: =IF($B14="","",$C14-$D14) | F14: =IF($B14="","",SUMIFS(Ledger!$F$3:$F$1002,Ledger!$B$3:$B$1002,$B14,Ledger!$C$3:$C$1002,"Issue")) | G14: =IF($B14="","",SUMIFS(Ledger!$F$3:$F$1002,Ledger!$B$3:$B$1002,$B14,Ledger!$C$3:$C$1002,"Return")) | H14: =IF($B14="","",$F14-$G14)
A15: =8 | B15: =IFERROR(INDEX(Khata!$A:$A,MATCH(LARGE(Khata!$E$3:$E$202,8),Khata!$E$3:$E$202,0)),"") | C15: =IF($B15="","",SUMIFS(Ledger!$H$3:$H$1002,Ledger!$B$3:$B$1002,$B15)+XLOOKUP($B15,Customers!$A:$A,Customers!$F:$F,0)) | D15: =IF($B15="","",SUMIFS(Ledger!$I$3:$I$1002,Ledger!$B$3:$B$1002,$B15)) | E15: =IF($B15="","",$C15-$D15) | F15: =IF($B15="","",SUMIFS(Ledger!$F$3:$F$1002,Ledger!$B$3:$B$1002,$B15,Ledger!$C$3:$C$1002,"Issue")) | G15: =IF($B15="","",SUMIFS(Ledger!$F$3:$F$1002,Ledger!$B$3:$B$1002,$B15,Ledger!$C$3:$C$1002,"Return")) | H15: =IF($B15="","",$F15-$G15)
A16: =9 | B16: =IFERROR(INDEX(Khata!$A:$A,MATCH(LARGE(Khata!$E$3:$E$202,9),Khata!$E$3:$E$202,0)),"") | C16: =IF($B16="","",SUMIFS(Ledger!$H$3:$H$1002,Ledger!$B$3:$B$1002,$B16)+XLOOKUP($B16,Customers!$A:$A,Customers!$F:$F,0)) | D16: =IF($B16="","",SUMIFS(Ledger!$I$3:$I$1002,Ledger!$B$3:$B$1002,$B16)) | E16: =IF($B16="","",$C16-$D16) | F16: =IF($B16="","",SUMIFS(Ledger!$F$3:$F$1002,Ledger!$B$3:$B$1002,$B16,Ledger!$C$3:$C$1002,"Issue")) | G16: =IF($B16="","",SUMIFS(Ledger!$F$3:$F$1002,Ledger!$B$3:$B$1002,$B16,Ledger!$C$3:$C$1002,"Return")) | H16: =IF($B16="","",$F16-$G16)
A17: =10 | B17: =IFERROR(INDEX(Khata!$A:$A,MATCH(LARGE(Khata!$E$3:$E$202,10),Khata!$E$3:$E$202,0)),"") | C17: =IF($B17="","",SUMIFS(Ledger!$H$3:$H$1002,Ledger!$B$3:$B$1002,$B17)+XLOOKUP($B17,Customers!$A:$A,Customers!$F:$F,0)) | D17: =IF($B17="","",SUMIFS(Ledger!$I$3:$I$1002,Ledger!$B$3:$B$1002,$B17)) | E17: =IF($B17="","",$C17-$D17) | F17: =IF($B17="","",SUMIFS(Ledger!$F$3:$F$1002,Ledger!$B$3:$B$1002,$B17,Ledger!$C$3:$C$1002,"Issue")) | G17: =IF($B17="","",SUMIFS(Ledger!$F$3:$F$1002,Ledger!$B$3:$B$1002,$B17,Ledger!$C$3:$C$1002,"Return")) | H17: =IF($B17="","",$F17-$G17)
A19: LOW STOCK • कमी माल
A20: Item ID | B20: Item | C20: Opening | D20: Given | E20: Returned | F20: In Hand | G20: Min | H20: Status
A21: =IFERROR(INDEX(Stock!$A:$A,1+2),"") | B21: =IF($A21="","",XLOOKUP($A21,Items!$A:$A,Items!$B:$B)) | C21: =IF($A21="","",XLOOKUP($A21,Stock!$A:$A,Stock!$B:$B)) | D21: =IF($A21="","",XLOOKUP($A21,Stock!$A:$A,Stock!$C:$C)) | E21: =IF($A21="","",XLOOKUP($A21,Stock!$A:$A,Stock!$D:$D)) | F21: =IF($A21="","",XLOOKUP($A21,Stock!$A:$A,Stock!$E:$E)) | G21: =IF($A21="","",XLOOKUP($A21,Stock!$A:$A,Stock!$F:$F)) | H21: =IF($A21="","",XLOOKUP($A21,Stock!$A:$A,Stock!$H:$H))
A22: =IFERROR(INDEX(Stock!$A:$A,2+2),"") | B22: =IF($A22="","",XLOOKUP($A22,Items!$A:$A,Items!$B:$B)) | C22: =IF($A22="","",XLOOKUP($A22,Stock!$A:$A,Stock!$B:$B)) | D22: =IF($A22="","",XLOOKUP($A22,Stock!$A:$A,Stock!$C:$C)) | E22: =IF($A22="","",XLOOKUP($A22,Stock!$A:$A,Stock!$D:$D)) | F22: =IF($A22="","",XLOOKUP($A22,Stock!$A:$A,Stock!$E:$E)) | G22: =IF($A22="","",XLOOKUP($A22,Stock!$A:$A,Stock!$F:$F)) | H22: =IF($A22="","",XLOOKUP($A22,Stock!$A:$A,Stock!$H:$H))
A23: =IFERROR(INDEX(Stock!$A:$A,3+2),"") | B23: =IF($A23="","",XLOOKUP($A23,Items!$A:$A,Items!$B:$B)) | C23: =IF($A23="","",XLOOKUP($A23,Stock!$A:$A,Stock!$B:$B)) | D23: =IF($A23="","",XLOOKUP($A23,Stock!$A:$A,Stock!$C:$C)) | E23: =IF($A23="","",XLOOKUP($A23,Stock!$A:$A,Stock!$D:$D)) | F23: =IF($A23="","",XLOOKUP($A23,Stock!$A:$A,Stock!$E:$E)) | G23: =IF($A23="","",XLOOKUP($A23,Stock!$A:$A,Stock!$F:$F)) | H23: =IF($A23="","",XLOOKUP($A23,Stock!$A:$A,Stock!$H:$H))
A24: =IFERROR(INDEX(Stock!$A:$A,4+2),"") | B24: =IF($A24="","",XLOOKUP($A24,Items!$A:$A,Items!$B:$B)) | C24: =IF($A24="","",XLOOKUP($A24,Stock!$A:$A,Stock!$B:$B)) | D24: =IF($A24="","",XLOOKUP($A24,Stock!$A:$A,Stock!$C:$C)) | E24: =IF($A24="","",XLOOKUP($A24,Stock!$A:$A,Stock!$D:$D)) | F24: =IF($A24="","",XLOOKUP($A24,Stock!$A:$A,Stock!$E:$E)) | G24: =IF($A24="","",XLOOKUP($A24,Stock!$A:$A,Stock!$F:$F)) | H24: =IF($A24="","",XLOOKUP($A24,Stock!$A:$A,Stock!$H:$H))
A25: =IFERROR(INDEX(Stock!$A:$A,5+2),"") | B25: =IF($A25="","",XLOOKUP($A25,Items!$A:$A,Items!$B:$B)) | C25: =IF($A25="","",XLOOKUP($A25,Stock!$A:$A,Stock!$B:$B)) | D25: =IF($A25="","",XLOOKUP($A25,Stock!$A:$A,Stock!$C:$C)) | E25: =IF($A25="","",XLOOKUP($A25,Stock!$A:$A,Stock!$D:$D)) | F25: =IF($A25="","",XLOOKUP($A25,Stock!$A:$A,Stock!$E:$E)) | G25: =IF($A25="","",XLOOKUP($A25,Stock!$A:$A,Stock!$F:$F)) | H25: =IF($A25="","",XLOOKUP($A25,Stock!$A:$A,Stock!$H:$H))
A26: =IFERROR(INDEX(Stock!$A:$A,6+2),"") | B26: =IF($A26="","",XLOOKUP($A26,Items!$A:$A,Items!$B:$B)) | C26: =IF($A26="","",XLOOKUP($A26,Stock!$A:$A,Stock!$B:$B)) | D26: =IF($A26="","",XLOOKUP($A26,Stock!$A:$A,Stock!$C:$C)) | E26: =IF($A26="","",XLOOKUP($A26,Stock!$A:$A,Stock!$D:$D)) | F26: =IF($A26="","",XLOOKUP($A26,Stock!$A:$A,Stock!$E:$E)) | G26: =IF($A26="","",XLOOKUP($A26,Stock!$A:$A,Stock!$F:$F)) | H26: =IF($A26="","",XLOOKUP($A26,Stock!$A:$A,Stock!$H:$H))
A27: =IFERROR(INDEX(Stock!$A:$A,7+2),"") | B27: =IF($A27="","",XLOOKUP($A27,Items!$A:$A,Items!$B:$B)) | C27: =IF($A27="","",XLOOKUP($A27,Stock!$A:$A,Stock!$B:$B)) | D27: =IF($A27="","",XLOOKUP($A27,Stock!$A:$A,Stock!$C:$C)) | E27: =IF($A27="","",XLOOKUP($A27,Stock!$A:$A,Stock!$D:$D)) | F27: =IF($A27="","",XLOOKUP($A27,Stock!$A:$A,Stock!$E:$E)) | G27: =IF($A27="","",XLOOKUP($A27,Stock!$A:$A,Stock!$F:$F)) | H27: =IF($A27="","",XLOOKUP($A27,Stock!$A:$A,Stock!$H:$H))
A28: =IFERROR(INDEX(Stock!$A:$A,8+2),"") | B28: =IF($A28="","",XLOOKUP($A28,Items!$A:$A,Items!$B:$B)) | C28: =IF($A28="","",XLOOKUP($A28,Stock!$A:$A,Stock!$B:$B)) | D28: =IF($A28="","",XLOOKUP($A28,Stock!$A:$A,Stock!$C:$C)) | E28: =IF($A28="","",XLOOKUP($A28,Stock!$A:$A,Stock!$D:$D)) | F28: =IF($A28="","",XLOOKUP($A28,Stock!$A:$A,Stock!$E:$E)) | G28: =IF($A28="","",XLOOKUP($A28,Stock!$A:$A,Stock!$F:$F)) | H28: =IF($A28="","",XLOOKUP($A28,Stock!$A:$A,Stock!$H:$H))
A30: LAST 10 DAYS • रोजची जमा
A31: Date | B31: Billed | C31: Received | E31: Customer | F31: Billed | G31: Received
A32: =$H$2-9+0 | B32: =SUMIFS(Ledger!$H$3:$H$1002,Ledger!$A$3:$A$1002,$A32) | C32: =SUMIFS(Ledger!$I$3:$I$1002,Ledger!$A$3:$A$1002,$A32) | E32: =IFERROR(INDEX(Khata!$A:$A,0+3),"") | F32: =IF($E32="","",SUMIFS(Ledger!$H$3:$H$1002,Ledger!$B$3:$B$1002,$E32)) | G32: =IF($E32="","",SUMIFS(Ledger!$I$3:$I$1002,Ledger!$B$3:$B$1002,$E32))
A33: =$H$2-9+1 | B33: =SUMIFS(Ledger!$H$3:$H$1002,Ledger!$A$3:$A$1002,$A33) | C33: =SUMIFS(Ledger!$I$3:$I$1002,Ledger!$A$3:$A$1002,$A33) | E33: =IFERROR(INDEX(Khata!$A:$A,1+3),"") | F33: =IF($E33="","",SUMIFS(Ledger!$H$3:$H$1002,Ledger!$B$3:$B$1002,$E33)) | G33: =IF($E33="","",SUMIFS(Ledger!$I$3:$I$1002,Ledger!$B$3:$B$1002,$E33))
A34: =$H$2-9+2 | B34: =SUMIFS(Ledger!$H$3:$H$1002,Ledger!$A$3:$A$1002,$A34) | C34: =SUMIFS(Ledger!$I$3:$I$1002,Ledger!$A$3:$A$1002,$A34) | E34: =IFERROR(INDEX(Khata!$A:$A,2+3),"") | F34: =IF($E34="","",SUMIFS(Ledger!$H$3:$H$1002,Ledger!$B$3:$B$1002,$E34)) | G34: =IF($E34="","",SUMIFS(Ledger!$I$3:$I$1002,Ledger!$B$3:$B$1002,$E34))
A35: =$H$2-9+3 | B35: =SUMIFS(Ledger!$H$3:$H$1002,Ledger!$A$3:$A$1002,$A35) | C35: =SUMIFS(Ledger!$I$3:$I$1002,Ledger!$A$3:$A$1002,$A35) | E35: =IFERROR(INDEX(Khata!$A:$A,3+3),"") | F35: =IF($E35="","",SUMIFS(Ledger!$H$3:$H$1002,Ledger!$B$3:$B$1002,$E35)) | G35: =IF($E35="","",SUMIFS(Ledger!$I$3:$I$1002,Ledger!$B$3:$B$1002,$E35))
A36: =$H$2-9+4 | B36: =SUMIFS(Ledger!$H$3:$H$1002,Ledger!$A$3:$A$1002,$A36) | C36: =SUMIFS(Ledger!$I$3:$I$1002,Ledger!$A$3:$A$1002,$A36) | E36: =IFERROR(INDEX(Khata!$A:$A,4+3),"") | F36: =IF($E36="","",SUMIFS(Ledger!$H$3:$H$1002,Ledger!$B$3:$B$1002,$E36)) | G36: =IF($E36="","",SUMIFS(Ledger!$I$3:$I$1002,Ledger!$B$3:$B$1002,$E36))
A37: =$H$2-9+5 | B37: =SUMIFS(Ledger!$H$3:$H$1002,Ledger!$A$3:$A$1002,$A37) | C37: =SUMIFS(Ledger!$I$3:$I$1002,Ledger!$A$3:$A$1002,$A37) | E37: =IFERROR(INDEX(Khata!$A:$A,5+3),"") | F37: =IF($E37="","",SUMIFS(Ledger!$H$3:$H$1002,Ledger!$B$3:$B$1002,$E37)) | G37: =IF($E37="","",SUMIFS(Ledger!$I$3:$I$1002,Ledger!$B$3:$B$1002,$E37))
A38: =$H$2-9+6 | B38: =SUMIFS(Ledger!$H$3:$H$1002,Ledger!$A$3:$A$1002,$A38) | C38: =SUMIFS(Ledger!$I$3:$I$1002,Ledger!$A$3:$A$1002,$A38) | E38: =IFERROR(INDEX(Khata!$A:$A,6+3),"") | F38: =IF($E38="","",SUMIFS(Ledger!$H$3:$H$1002,Ledger!$B$3:$B$1002,$E38)) | G38: =IF($E38="","",SUMIFS(Ledger!$I$3:$I$1002,Ledger!$B$3:$B$1002,$E38))
A39: =$H$2-9+7 | B39: =SUMIFS(Ledger!$H$3:$H$1002,Ledger!$A$3:$A$1002,$A39) | C39: =SUMIFS(Ledger!$I$3:$I$1002,Ledger!$A$3:$A$1002,$A39) | E39: =IFERROR(INDEX(Khata!$A:$A,7+3),"") | F39: =IF($E39="","",SUMIFS(Ledger!$H$3:$H$1002,Ledger!$B$3:$B$1002,$E39)) | G39: =IF($E39="","",SUMIFS(Ledger!$I$3:$I$1002,Ledger!$B$3:$B$1002,$E39))
A40: =$H$2-9+8 | B40: =SUMIFS(Ledger!$H$3:$H$1002,Ledger!$A$3:$A$1002,$A40) | C40: =SUMIFS(Ledger!$I$3:$I$1002,Ledger!$A$3:$A$1002,$A40) | E40: =IFERROR(INDEX(Khata!$A:$A,8+3),"") | F40: =IF($E40="","",SUMIFS(Ledger!$H$3:$H$1002,Ledger!$B$3:$B$1002,$E40)) | G40: =IF($E40="","",SUMIFS(Ledger!$I$3:$I$1002,Ledger!$B$3:$B$1002,$E40))
A41: =$H$2-9+9 | B41: =SUMIFS(Ledger!$H$3:$H$1002,Ledger!$A$3:$A$1002,$A41) | C41: =SUMIFS(Ledger!$I$3:$I$1002,Ledger!$A$3:$A$1002,$A41) | E41: =IFERROR(INDEX(Khata!$A:$A,9+3),"") | F41: =IF($E41="","",SUMIFS(Ledger!$H$3:$H$1002,Ledger!$B$3:$B$1002,$E41)) | G41: =IF($E41="","",SUMIFS(Ledger!$I$3:$I$1002,Ledger!$B$3:$B$1002,$E41))

Sheet Khata
A1: KHATA • ग्राहक खाते • बेरीज (Yogesh: 850+900 बिल, 600 जमा = 1150 बाकी)
A2: Customer ग्राहक | B2: Billed ₹ एकूण बिल | C2: Received ₹ एकूण जमा | D2: Opening Due जुनी बाकी | E2: Pending ₹ येणे बाकी | F2: Given Qty दिलेले | G2: Outside Qty बाहेर
A3: =IF(Customers!A3="","",Customers!A3) | B3: =IF($A3="","",SUMIFS(Ledger!$H$3:$H$1002,Ledger!$B$3:$B$1002,$A3)) | C3: =IF($A3="","",SUMIFS(Ledger!$I$3:$I$1002,Ledger!$B$3:$B$1002,$A3)) | D3: =IF($A3="","",IFERROR(XLOOKUP($A3,Customers!$A:$A,Customers!$F:$F),0)) | E3: =IF($A3="","",$B3+$D3-$C3) | F3: =IF($A3="","",SUMIFS(Ledger!$F$3:$F$1002,Ledger!$B$3:$B$1002,$A3,Ledger!$C$3:$C$1002,"Issue")) | G3: =IF($A3="","",SUMIFS(Ledger!$F$3:$F$1002,Ledger!$B$3:$B$1002,$A3,Ledger!$C$3:$C$1002,"Issue")-SUMIFS(Ledger!$F$3:$F$1002,Ledger!$B$3:$B$1002,$A3,Ledger!$C$3:$C$1002,"Return"))
A4: =IF(Customers!A4="","",Customers!A4) | B4: =IF($A4="","",SUMIFS(Ledger!$H$3:$H$1002,Ledger!$B$3:$B$1002,$A4)) | C4: =IF($A4="","",SUMIFS(Ledger!$I$3:$I$1002,Ledger!$B$3:$B$1002,$A4)) | D4: =IF($A4="","",IFERROR(XLOOKUP($A4,Customers!$A:$A,Customers!$F:$F),0)) | E4: =IF($A4="","",$B4+$D4-$C4) | F4: =IF($A4="","",SUMIFS(Ledger!$F$3:$F$1002,Ledger!$B$3:$B$1002,$A4,Ledger!$C$3:$C$1002,"Issue")) | G4: =IF($A4="","",SUMIFS(Ledger!$F$3:$F$1002,Ledger!$B$3:$B$1002,$A4,Ledger!$C$3:$C$1002,"Issue")-SUMIFS(Ledger!$F$3:$F$1002,Ledger!$B$3:$B$1002,$A4,Ledger!$C$3:$C$1002,"Return"))
A5: =IF(Customers!A5="","",Customers!A5) | B5: =IF($A5="","",SUMIFS(Ledger!$H$3:$H$1002,Ledger!$B$3:$B$1002,$A5)) | C5: =IF($A5="","",SUMIFS(Ledger!$I$3:$I$1002,Ledger!$B$3:$B$1002,$A5)) | D5: =IF($A5="","",IFERROR(XLOOKUP($A5,Customers!$A:$A,Customers!$F:$F),0)) | E5: =IF($A5="","",$B5+$D5-$C5) | F5: =IF($A5="","",SUMIFS(Ledger!$F$3:$F$1002,Ledger!$B$3:$B$1002,$A5,Ledger!$C$3:$C$1002,"Issue")) | G5: =IF($A5="","",SUMIFS(Ledger!$F$3:$F$1002,Ledger!$B$3:$B$1002,$A5,Ledger!$C$3:$C$1002,"Issue")-SUMIFS(Ledger!$F$3:$F$1002,Ledger!$B$3:$B$1002,$A5,Ledger!$C$3:$C$1002,"Return"))
A6: =IF(Customers!A6="","",Customers!A6) | B6: =IF($A6="","",SUMIFS(Ledger!$H$3:$H$1002,Ledger!$B$3:$B$1002,$A6)) | C6: =IF($A6="","",SUMIFS(Ledger!$I$3:$I$1002,Ledger!$B$3:$B$1002,$A6)) | D6: =IF($A6="","",IFERROR(XLOOKUP($A6,Customers!$A:$A,Customers!$F:$F),0)) | E6: =IF($A6="","",$B6+$D6-$C6) | F6: =IF($A6="","",SUMIFS(Ledger!$F$3:$F$1002,Ledger!$B$3:$B$1002,$A6,Ledger!$C$3:$C$1002,"Issue")) | G6: =IF($A6="","",SUMIFS(Ledger!$F$3:$F$1002,Ledger!$B$3:$B$1002,$A6,Ledger!$C$3:$C$1002,"Issue")-SUMIFS(Ledger!$F$3:$F$1002,Ledger!$B$3:$B$1002,$A6,Ledger!$C$3:$C$1002,"Return"))
A7: =IF(Customers!A7="","",Customers!A7) | B7: =IF($A7="","",SUMIFS(Ledger!$H$3:$H$1002,Ledger!$B$3:$B$1002,$A7)) | C7: =IF($A7="","",SUMIFS(Ledger!$I$3:$I$1002,Ledger!$B$3:$B$1002,$A7)) | D7: =IF($A7="","",IFERROR(XLOOKUP($A7,Customers!$A:$A,Customers!$F:$F),0)) | E7: =IF($A7="","",$B7+$D7-$C7) | F7: =IF($A7="","",SUMIFS(Ledger!$F$3:$F$1002,Ledger!$B$3:$B$1002,$A7,Ledger!$C$3:$C$1002,"Issue")) | G7: =IF($A7="","",SUMIFS(Ledger!$F$3:$F$1002,Ledger!$B$3:$B$1002,$A7,Ledger!$C$3:$C$1002,"Issue")-SUMIFS(Ledger!$F$3:$F$1002,Ledger!$B$3:$B$1002,$A7,Ledger!$C$3:$C$1002,"Return"))
A8: =IF(Customers!A8="","",Customers!A8) | B8: =IF($A8="","",SUMIFS(Ledger!$H$3:$H$1002,Ledger!$B$3:$B$1002,$A8)) | C8: =IF($A8="","",SUMIFS(Ledger!$I$3:$I$1002,Ledger!$B$3:$B$1002,$A8)) | D8: =IF($A8="","",IFERROR(XLOOKUP($A8,Customers!$A:$A,Customers!$F:$F),0)) | E8: =IF($A8="","",$B8+$D8-$C8) | F8: =IF($A8="","",SUMIFS(Ledger!$F$3:$F$1002,Ledger!$B$3:$B$1002,$A8,Ledger!$C$3:$C$1002,"Issue")) | G8: =IF($A8="","",SUMIFS(Ledger!$F$3:$F$1002,Ledger!$B$3:$B$1002,$A8,Ledger!$C$3:$C$1002,"Issue")-SUMIFS(Ledger!$F$3:$F$1002,Ledger!$B$3:$B$1002,$A8,Ledger!$C$3:$C$1002,"Return"))
A9: =IF(Customers!A9="","",Customers!A9) | B9: =IF($A9="","",SUMIFS(Ledger!$H$3:$H$1002,Ledger!$B$3:$B$1002,$A9)) | C9: =IF($A9="","",SUMIFS(Ledger!$I$3:$I$1002,Ledger!$B$3:$B$1002,$A9)) | D9: =IF($A9="","",IFERROR(XLOOKUP($A9,Customers!$A:$A,Customers!$F:$F),0)) | E9: =IF($A9="","",$B9+$D9-$C9) | F9: =IF($A9="","",SUMIFS(Ledger!$F$3:$F$1002,Ledger!$B$3:$B$1002,$A9,Ledger!$C$3:$C$1002,"Issue")) | G9: =IF($A9="","",SUMIFS(Ledger!$F$3:$F$1002,Ledger!$B$3:$B$1002,$A9,Ledger!$C$3:$C$1002,"Issue")-SUMIFS(Ledger!$F$3:$F$1002,Ledger!$B$3:$B$1002,$A9,Ledger!$C$3:$C$1002,"Return"))
A10: =IF(Customers!A10="","",Customers!A10) | B10: =IF($A10="","",SUMIFS(Ledger!$H$3:$H$1002,Ledger!$B$3:$B$1002,$A10)) | C10: =IF($A10="","",SUMIFS(Ledger!$I$3:$I$1002,Ledger!$B$3:$B$1002,$A10)) | D10: =IF($A10="","",IFERROR(XLOOKUP($A10,Customers!$A:$A,Customers!$F:$F),0)) | E10: =IF($A10="","",$B10+$D10-$C10) | F10: =IF($A10="","",SUMIFS(Ledger!$F$3:$F$1002,Ledger!$B$3:$B$1002,$A10,Ledger!$C$3:$C$1002,"Issue")) | G10: =IF($A10="","",SUMIFS(Ledger!$F$3:$F$1002,Ledger!$B$3:$B$1002,$A10,Ledger!$C$3:$C$1002,"Issue")-SUMIFS(Ledger!$F$3:$F$1002,Ledger!$B$3:$B$1002,$A10,Ledger!$C$3:$C$1002,"Return"))
A11: =IF(Customers!A11="","",Customers!A11) | B11: =IF($A11="","",SUMIFS(Ledger!$H$3:$H$1002,Ledger!$B$3:$B$1002,$A11)) | C11: =IF($A11="","",SUMIFS(Ledger!$I$3:$I$1002,Ledger!$B$3:$B$1002,$A11)) | D11: =IF($A11="","",IFERROR(XLOOKUP($A11,Customers!$A:$A,Customers!$F:$F),0)) | E11: =IF($A11="","",$B11+$D11-$C11) | F11: =IF($A11="","",SUMIFS(Ledger!$F$3:$F$1002,Ledger!$B$3:$B$1002,$A11,Ledger!$C$3:$C$1002,"Issue")) | G11: =IF($A11="","",SUMIFS(Ledger!$F$3:$F$1002,Ledger!$B$3:$B$1002,$A11,Ledger!$C$3:$C$1002,"Issue")-SUMIFS(Ledger!$F$3:$F$1002,Ledger!$B$3:$B$1002,$A11,Ledger!$C$3:$C$1002,"Return"))
A12: =IF(Customers!A12="","",Customers!A12) | B12: =IF($A12="","",SUMIFS(Ledger!$H$3:$H$1002,Ledger!$B$3:$B$1002,$A12)) | C12: =IF($A12="","",SUMIFS(Ledger!$I$3:$I$1002,Ledger!$B$3:$B$1002,$A12)) | D12: =IF($A12="","",IFERROR(XLOOKUP($A12,Customers!$A:$A,Customers!$F:$F),0)) | E12: =IF($A12="","",$B12+$D12-$C12) | F12: =IF($A12="","",SUMIFS(Ledger!$F$3:$F$1002,Ledger!$B$3:$B$1002,$A12,Ledger!$C$3:$C$1002,"Issue")) | G12: =IF($A12="","",SUMIFS(Ledger!$F$3:$F$1002,Ledger!$B$3:$B$1002,$A12,Ledger!$C$3:$C$1002,"Issue")-SUMIFS(Ledger!$F$3:$F$1002,Ledger!$B$3:$B$1002,$A12,Ledger!$C$3:$C$1002,"Return"))
A13: =IF(Customers!A13="","",Customers!A13) | B13: =IF($A13="","",SUMIFS(Ledger!$H$3:$H$1002,Ledger!$B$3:$B$1002,$A13)) | C13: =IF($A13="","",SUMIFS(Ledger!$I$3:$I$1002,Ledger!$B$3:$B$1002,$A13)) | D13: =IF($A13="","",IFERROR(XLOOKUP($A13,Customers!$A:$A,Customers!$F:$F),0)) | E13: =IF($A13="","",$B13+$D13-$C13) | F13: =IF($A13="","",SUMIFS(Ledger!$F$3:$F$1002,Ledger!$B$3:$B$1002,$A13,Ledger!$C$3:$C$1002,"Issue")) | G13: =IF($A13="","",SUMIFS(Ledger!$F$3:$F$1002,Ledger!$B$3:$B$1002,$A13,Ledger!$C$3:$C$1002,"Issue")-SUMIFS(Ledger!$F$3:$F$1002,Ledger!$B$3:$B$1002,$A13,Ledger!$C$3:$C$1002,"Return"))
A14: =IF(Customers!A14="","",Customers!A14) | B14: =IF($A14="","",SUMIFS(Ledger!$H$3:$H$1002,Ledger!$B$3:$B$1002,$A14)) | C14: =IF($A14="","",SUMIFS(Ledger!$I$3:$I$1002,Ledger!$B$3:$B$1002,$A14)) | D14: =IF($A14="","",IFERROR(XLOOKUP($A14,Customers!$A:$A,Customers!$F:$F),0)) | E14: =IF($A14="","",$B14+$D14-$C14) | F14: =IF($A14="","",SUMIFS(Ledger!$F$3:$F$1002,Ledger!$B$3:$B$1002,$A14,Ledger!$C$3:$C$1002,"Issue")) | G14: =IF($A14="","",SUMIFS(Ledger!$F$3:$F$1002,Ledger!$B$3:$B$1002,$A14,Ledger!$C$3:$C$1002,"Issue")-SUMIFS(Ledger!$F$3:$F$1002,Ledger!$B$3:$B$1002,$A14,Ledger!$C$3:$C$1002,"Return"))
... A202: =IF(Customers!A202="","",Customers!A202) | B202: =IF($A202="","",SUMIFS(Ledger!$H$3:$H$1002,Ledger!$B$3:$B$1002,$A202)) | C202: =IF($A202="","",SUMIFS(Ledger!$I$3:$I$1002,Ledger!$B$3:$B$1002,$A202)) | D202: =IF($A202="","",IFERROR(XLOOKUP($A202,Customers!$A:$A,Customers!$F:$F),0)) | E202: =IF($A202="","",$B202+$D202-$C202) | F202: =IF($A202="","",SUMIFS(Ledger!$F$3:$F$1002,Ledger!$B$3:$B$1002,$A202,Ledger!$C$3:$C$1002,"Issue")) | G202: =IF($A202="","",SUMIFS(Ledger!$F$3:$F$1002,Ledger!$B$3:$B$1002,$A202,Ledger!$C$3:$C$1002,"Issue")-SUMIFS(Ledger!$F$3:$F$1002,Ledger!$B$3:$B$1002,$A202,Ledger!$C$3:$C$1002,"Return"))

Sheet Stock
A1: STOCK • माल हिशोब • In Hand = Opening + Return - Given
A2: Item ID | B2: Opening | C2: Given दिले | D2: Returned परत | E2: In Hand हातात | F2: Min किमान | G2: Revenue ₹ कमाई | H2: Status
A3: =IF(Items!A3="","",Items!A3) | B3: =IF($A3="","",IFERROR(XLOOKUP($A3,Items!$A:$A,Items!$E:$E),0)) | C3: =IF($A3="","",SUMIFS(Ledger!$F$3:$F$1002,Ledger!$D$3:$D$1002,$A3,Ledger!$C$3:$C$1002,"Issue")) | D3: =IF($A3="","",SUMIFS(Ledger!$F$3:$F$1002,Ledger!$D$3:$D$1002,$A3,Ledger!$C$3:$C$1002,"Return")) | E3: =IF($A3="","",$B3+$D3-$C3) | F3: =IF($A3="","",IFERROR(XLOOKUP($A3,Items!$A:$A,Items!$F:$F),0)) | G3: =IF($A3="","",SUMIFS(Ledger!$H$3:$H$1002,Ledger!$D$3:$D$1002,$A3)) | H3: =IF($A3="","",IF($E3<$F3,"LOW",IF($E3=0,"EMPTY","OK")))
A4: =IF(Items!A4="","",Items!A4) | B4: =IF($A4="","",IFERROR(XLOOKUP($A4,Items!$A:$A,Items!$E:$E),0)) | C4: =IF($A4="","",SUMIFS(Ledger!$F$3:$F$1002,Ledger!$D$3:$D$1002,$A4,Ledger!$C$3:$C$1002,"Issue")) | D4: =IF($A4="","",SUMIFS(Ledger!$F$3:$F$1002,Ledger!$D$3:$D$1002,$A4,Ledger!$C$3:$C$1002,"Return")) | E4: =IF($A4="","",$B4+$D4-$C4) | F4: =IF($A4="","",IFERROR(XLOOKUP($A4,Items!$A:$A,Items!$F:$F),0)) | G4: =IF($A4="","",SUMIFS(Ledger!$H$3:$H$1002,Ledger!$D$3:$D$1002,$A4)) | H4: =IF($A4="","",IF($E4<$F4,"LOW",IF($E4=0,"EMPTY","OK")))
A5: =IF(Items!A5="","",Items!A5) | B5: =IF($A5="","",IFERROR(XLOOKUP($A5,Items!$A:$A,Items!$E:$E),0)) | C5: =IF($A5="","",SUMIFS(Ledger!$F$3:$F$1002,Ledger!$D$3:$D$1002,$A5,Ledger!$C$3:$C$1002,"Issue")) | D5: =IF($A5="","",SUMIFS(Ledger!$F$3:$F$1002,Ledger!$D$3:$D$1002,$A5,Ledger!$C$3:$C$1002,"Return")) | E5: =IF($A5="","",$B5+$D5-$C5) | F5: =IF($A5="","",IFERROR(XLOOKUP($A5,Items!$A:$A,Items!$F:$F),0)) | G5: =IF($A5="","",SUMIFS(Ledger!$H$3:$H$1002,Ledger!$D$3:$D$1002,$A5)) | H5: =IF($A5="","",IF($E5<$F5,"LOW",IF($E5=0,"EMPTY","OK")))
A6: =IF(Items!A6="","",Items!A6) | B6: =IF($A6="","",IFERROR(XLOOKUP($A6,Items!$A:$A,Items!$E:$E),0)) | C6: =IF($A6="","",SUMIFS(Ledger!$F$3:$F$1002,Ledger!$D$3:$D$1002,$A6,Ledger!$C$3:$C$1002,"Issue")) | D6: =IF($A6="","",SUMIFS(Ledger!$F$3:$F$1002,Ledger!$D$3:$D$1002,$A6,Ledger!$C$3:$C$1002,"Return")) | E6: =IF($A6="","",$B6+$D6-$C6) | F6: =IF($A6="","",IFERROR(XLOOKUP($A6,Items!$A:$A,Items!$F:$F),0)) | G6: =IF($A6="","",SUMIFS(Ledger!$H$3:$H$1002,Ledger!$D$3:$D$1002,$A6)) | H6: =IF($A6="","",IF($E6<$F6,"LOW",IF($E6=0,"EMPTY","OK")))
A7: =IF(Items!A7="","",Items!A7) | B7: =IF($A7="","",IFERROR(XLOOKUP($A7,Items!$A:$A,Items!$E:$E),0)) | C7: =IF($A7="","",SUMIFS(Ledger!$F$3:$F$1002,Ledger!$D$3:$D$1002,$A7,Ledger!$C$3:$C$1002,"Issue")) | D7: =IF($A7="","",SUMIFS(Ledger!$F$3:$F$1002,Ledger!$D$3:$D$1002,$A7,Ledger!$C$3:$C$1002,"Return")) | E7: =IF($A7="","",$B7+$D7-$C7) | F7: =IF($A7="","",IFERROR(XLOOKUP($A7,Items!$A:$A,Items!$F:$F),0)) | G7: =IF($A7="","",SUMIFS(Ledger!$H$3:$H$1002,Ledger!$D$3:$D$1002,$A7)) | H7: =IF($A7="","",IF($E7<$F7,"LOW",IF($E7=0,"EMPTY","OK")))
A8: =IF(Items!A8="","",Items!A8) | B8: =IF($A8="","",IFERROR(XLOOKUP($A8,Items!$A:$A,Items!$E:$E),0)) | C8: =IF($A8="","",SUMIFS(Ledger!$F$3:$F$1002,Ledger!$D$3:$D$1002,$A8,Ledger!$C$3:$C$1002,"Issue")) | D8: =IF($A8="","",SUMIFS(Ledger!$F$3:$F$1002,Ledger!$D$3:$D$1002,$A8,Ledger!$C$3:$C$1002,"Return")) | E8: =IF($A8="","",$B8+$D8-$C8) | F8: =IF($A8="","",IFERROR(XLOOKUP($A8,Items!$A:$A,Items!$F:$F),0)) | G8: =IF($A8="","",SUMIFS(Ledger!$H$3:$H$1002,Ledger!$D$3:$D$1002,$A8)) | H8: =IF($A8="","",IF($E8<$F8,"LOW",IF($E8=0,"EMPTY","OK")))
A9: =IF(Items!A9="","",Items!A9) | B9: =IF($A9="","",IFERROR(XLOOKUP($A9,Items!$A:$A,Items!$E:$E),0)) | C9: =IF($A9="","",SUMIFS(Ledger!$F$3:$F$1002,Ledger!$D$3:$D$1002,$A9,Ledger!$C$3:$C$1002,"Issue")) | D9: =IF($A9="","",SUMIFS(Ledger!$F$3:$F$1002,Ledger!$D$3:$D$1002,$A9,Ledger!$C$3:$C$1002,"Return")) | E9: =IF($A9="","",$B9+$D9-$C9) | F9: =IF($A9="","",IFERROR(XLOOKUP($A9,Items!$A:$A,Items!$F:$F),0)) | G9: =IF($A9="","",SUMIFS(Ledger!$H$3:$H$1002,Ledger!$D$3:$D$1002,$A9)) | H9: =IF($A9="","",IF($E9<$F9,"LOW",IF($E9=0,"EMPTY","OK")))
A10: =IF(Items!A10="","",Items!A10) | B10: =IF($A10="","",IFERROR(XLOOKUP($A10,Items!$A:$A,Items!$E:$E),0)) | C10: =IF($A10="","",SUMIFS(Ledger!$F$3:$F$1002,Ledger!$D$3:$D$1002,$A10,Ledger!$C$3:$C$1002,"Issue")) | D10: =IF($A10="","",SUMIFS(Ledger!$F$3:$F$1002,Ledger!$D$3:$D$1002,$A10,Ledger!$C$3:$C$1002,"Return")) | E10: =IF($A10="","",$B10+$D10-$C10) | F10: =IF($A10="","",IFERROR(XLOOKUP($A10,Items!$A:$A,Items!$F:$F),0)) | G10: =IF($A10="","",SUMIFS(Ledger!$H$3:$H$1002,Ledger!$D$3:$D$1002,$A10)) | H10: =IF($A10="","",IF($E10<$F10,"LOW",IF($E10=0,"EMPTY","OK")))
A11: =IF(Items!A11="","",Items!A11) | B11: =IF($A11="","",IFERROR(XLOOKUP($A11,Items!$A:$A,Items!$E:$E),0)) | C11: =IF($A11="","",SUMIFS(Ledger!$F$3:$F$1002,Ledger!$D$3:$D$1002,$A11,Ledger!$C$3:$C$1002,"Issue")) | D11: =IF($A11="","",SUMIFS(Ledger!$F$3:$F$1002,Ledger!$D$3:$D$1002,$A11,Ledger!$C$3:$C$1002,"Return")) | E11: =IF($A11="","",$B11+$D11-$C11) | F11: =IF($A11="","",IFERROR(XLOOKUP($A11,Items!$A:$A,Items!$F:$F),0)) | G11: =IF($A11="","",SUMIFS(Ledger!$H$3:$H$1002,Ledger!$D$3:$D$1002,$A11)) | H11: =IF($A11="","",IF($E11<$F11,"LOW",IF($E11=0,"EMPTY","OK")))
A12: =IF(Items!A12="","",Items!A12) | B12: =IF($A12="","",IFERROR(XLOOKUP($A12,Items!$A:$A,Items!$E:$E),0)) | C12: =IF($A12="","",SUMIFS(Ledger!$F$3:$F$1002,Ledger!$D$3:$D$1002,$A12,Ledger!$C$3:$C$1002,"Issue")) | D12: =IF($A12="","",SUMIFS(Ledger!$F$3:$F$1002,Ledger!$D$3:$D$1002,$A12,Ledger!$C$3:$C$1002,"Return")) | E12: =IF($A12="","",$B12+$D12-$C12) | F12: =IF($A12="","",IFERROR(XLOOKUP($A12,Items!$A:$A,Items!$F:$F),0)) | G12: =IF($A12="","",SUMIFS(Ledger!$H$3:$H$1002,Ledger!$D$3:$D$1002,$A12)) | H12: =IF($A12="","",IF($E12<$F12,"LOW",IF($E12=0,"EMPTY","OK")))
A13: =IF(Items!A13="","",Items!A13) | B13: =IF($A13="","",IFERROR(XLOOKUP($A13,Items!$A:$A,Items!$E:$E),0)) | C13: =IF($A13="","",SUMIFS(Ledger!$F$3:$F$1002,Ledger!$D$3:$D$1002,$A13,Ledger!$C$3:$C$1002,"Issue")) | D13: =IF($A13="","",SUMIFS(Ledger!$F$3:$F$1002,Ledger!$D$3:$D$1002,$A13,Ledger!$C$3:$C$1002,"Return")) | E13: =IF($A13="","",$B13+$D13-$C13) | F13: =IF($A13="","",IFERROR(XLOOKUP($A13,Items!$A:$A,Items!$F:$F),0)) | G13: =IF($A13="","",SUMIFS(Ledger!$H$3:$H$1002,Ledger!$D$3:$D$1002,$A13)) | H13: =IF($A13="","",IF($E13<$F13,"LOW",IF($E13=0,"EMPTY","OK")))
A14: =IF(Items!A14="","",Items!A14) | B14: =IF($A14="","",IFERROR(XLOOKUP($A14,Items!$A:$A,Items!$E:$E),0)) | C14: =IF($A14="","",SUMIFS(Ledger!$F$3:$F$1002,Ledger!$D$3:$D$1002,$A14,Ledger!$C$3:$C$1002,"Issue")) | D14: =IF($A14="","",SUMIFS(Ledger!$F$3:$F$1002,Ledger!$D$3:$D$1002,$A14,Ledger!$C$3:$C$1002,"Return")) | E14: =IF($A14="","",$B14+$D14-$C14) | F14: =IF($A14="","",IFERROR(XLOOKUP($A14,Items!$A:$A,Items!$F:$F),0)) | G14: =IF($A14="","",SUMIFS(Ledger!$H$3:$H$1002,Ledger!$D$3:$D$1002,$A14)) | H14: =IF($A14="","",IF($E14<$F14,"LOW",IF($E14=0,"EMPTY","OK")))
... A202: =IF(Items!A202="","",Items!A202) | B202: =IF($A202="","",IFERROR(XLOOKUP($A202,Items!$A:$A,Items!$E:$E),0)) | C202: =IF($A202="","",SUMIFS(Ledger!$F$3:$F$1002,Ledger!$D$3:$D$1002,$A202,Ledger!$C$3:$C$1002,"Issue")) | D202: =IF($A202="","",SUMIFS(Ledger!$F$3:$F$1002,Ledger!$D$3:$D$1002,$A202,Ledger!$C$3:$C$1002,"Return")) | E202: =IF($A202="","",$B202+$D202-$C202) | F202: =IF($A202="","",IFERROR(XLOOKUP($A202,Items!$A:$A,Items!$F:$F),0)) | G202: =IF($A202="","",SUMIFS(Ledger!$H$3:$H$1002,Ledger!$D$3:$D$1002,$A202)) | H202: =IF($A202="","",IF($E202<$F202,"LOW",IF($E202=0,"EMPTY","OK")))

Sheet Statement
A1: STATEMENT • ग्राहक बिल • वर ग्राहक निवडा
A2: Select Customer: | B2: Yogesh Caterers | F2: =SUMIFS(Ledger!$H:$H,Ledger!$B:$B,$B$2)+IFERROR(XLOOKUP($B$2,Customers!$A:$A,Customers!$F:$F),0) | G2: =SUMIFS(Ledger!$I:$I,Ledger!$B:$B,$B$2) | H2: =$F$2-$G$2
F3: Total Bill | G3: Received | H3: Pending
A4: WhatsApp: | B4: ="Namaskar "&$B$2&", DipSeva hisob: Bill Rs"&TEXT($F$2,"#,##0")&", Jama Rs"&TEXT($G$2,"#,##0")&", Baki Rs"&TEXT($H$2,"#,##0")&" - Dhanyavad"
A5: Date | B5: Type | C5: Item ID | D5: Item | E5: Qty | F5: Bill | G5: Paid | H5: Note
A6: =IFERROR(INDEX(Ledger!$A:$A,AGGREGATE(15,6,ROW(Ledger!$B$3:$B$1002)/(Ledger!$B$3:$B$1002=$B$2),1)),"") | B6: =IF($A6="","",INDEX(Ledger!$C:$C,AGGREGATE(15,6,ROW(Ledger!$B$3:$B$1002)/(Ledger!$B$3:$B$1002=$B$2),1))) | C6: =IF($A6="","",INDEX(Ledger!$D:$D,AGGREGATE(15,6,ROW(Ledger!$B$3:$B$1002)/(Ledger!$B$3:$B$1002=$B$2),1))) | D6: =IF($A6="","",INDEX(Ledger!$E:$E,AGGREGATE(15,6,ROW(Ledger!$B$3:$B$1002)/(Ledger!$B$3:$B$1002=$B$2),1))) | E6: =IF($A6="","",INDEX(Ledger!$F:$F,AGGREGATE(15,6,ROW(Ledger!$B$3:$B$1002)/(Ledger!$B$3:$B$1002=$B$2),1))) | F6: =IF($A6="","",INDEX(Ledger!$H:$H,AGGREGATE(15,6,ROW(Ledger!$B$3:$B$1002)/(Ledger!$B$3:$B$1002=$B$2),1))) | G6: =IF($A6="","",INDEX(Ledger!$I:$I,AGGREGATE(15,6,ROW(Ledger!$B$3:$B$1002)/(Ledger!$B$3:$B$1002=$B$2),1))) | H6: =IF($A6="","",INDEX(Ledger!$K:$K,AGGREGATE(15,6,ROW(Ledger!$B$3:$B$1002)/(Ledger!$B$3:$B$1002=$B$2),1)))
A7: =IFERROR(INDEX(Ledger!$A:$A,AGGREGATE(15,6,ROW(Ledger!$B$3:$B$1002)/(Ledger!$B$3:$B$1002=$B$2),2)),"") | B7: =IF($A7="","",INDEX(Ledger!$C:$C,AGGREGATE(15,6,ROW(Ledger!$B$3:$B$1002)/(Ledger!$B$3:$B$1002=$B$2),2))) | C7: =IF($A7="","",INDEX(Ledger!$D:$D,AGGREGATE(15,6,ROW(Ledger!$B$3:$B$1002)/(Ledger!$B$3:$B$1002=$B$2),2))) | D7: =IF($A7="","",INDEX(Ledger!$E:$E,AGGREGATE(15,6,ROW(Ledger!$B$3:$B$1002)/(Ledger!$B$3:$B$1002=$B$2),2))) | E7: =IF($A7="","",INDEX(Ledger!$F:$F,AGGREGATE(15,6,ROW(Ledger!$B$3:$B$1002)/(Ledger!$B$3:$B$1002=$B$2),2))) | F7: =IF($A7="","",INDEX(Ledger!$H:$H,AGGREGATE(15,6,ROW(Ledger!$B$3:$B$1002)/(Ledger!$B$3:$B$1002=$B$2),2))) | G7: =IF($A7="","",INDEX(Ledger!$I:$I,AGGREGATE(15,6,ROW(Ledger!$B$3:$B$1002)/(Ledger!$B$3:$B$1002=$B$2),2))) | H7: =IF($A7="","",INDEX(Ledger!$K:$K,AGGREGATE(15,6,ROW(Ledger!$B$3:$B$1002)/(Ledger!$B$3:$B$1002=$B$2),2)))
A8: =IFERROR(INDEX(Ledger!$A:$A,AGGREGATE(15,6,ROW(Ledger!$B$3:$B$1002)/(Ledger!$B$3:$B$1002=$B$2),3)),"") | B8: =IF($A8="","",INDEX(Ledger!$C:$C,AGGREGATE(15,6,ROW(Ledger!$B$3:$B$1002)/(Ledger!$B$3:$B$1002=$B$2),3))) | C8: =IF($A8="","",INDEX(Ledger!$D:$D,AGGREGATE(15,6,ROW(Ledger!$B$3:$B$1002)/(Ledger!$B$3:$B$1002=$B$2),3))) | D8: =IF($A8="","",INDEX(Ledger!$E:$E,AGGREGATE(15,6,ROW(Ledger!$B$3:$B$1002)/(Ledger!$B$3:$B$1002=$B$2),3))) | E8: =IF($A8="","",INDEX(Ledger!$F:$F,AGGREGATE(15,6,ROW(Ledger!$B$3:$B$1002)/(Ledger!$B$3:$B$1002=$B$2),3))) | F8: =IF($A8="","",INDEX(Ledger!$H:$H,AGGREGATE(15,6,ROW(Ledger!$B$3:$B$1002)/(Ledger!$B$3:$B$1002=$B$2),3))) | G8: =IF($A8="","",INDEX(Ledger!$I:$I,AGGREGATE(15,6,ROW(Ledger!$B$3:$B$1002)/(Ledger!$B$3:$B$1002=$B$2),3))) | H8: =IF($A8="","",INDEX(Ledger!$K:$K,AGGREGATE(15,6,ROW(Ledger!$B$3:$B$1002)/(Ledger!$B$3:$B$1002=$B$2),3)))
A9: =IFERROR(INDEX(Ledger!$A:$A,AGGREGATE(15,6,ROW(Ledger!$B$3:$B$1002)/(Ledger!$B$3:$B$1002=$B$2),4)),"") | B9: =IF($A9="","",INDEX(Ledger!$C:$C,AGGREGATE(15,6,ROW(Ledger!$B$3:$B$1002)/(Ledger!$B$3:$B$1002=$B$2),4))) | C9: =IF($A9="","",INDEX(Ledger!$D:$D,AGGREGATE(15,6,ROW(Ledger!$B$3:$B$1002)/(Ledger!$B$3:$B$1002=$B$2),4))) | D9: =IF($A9="","",INDEX(Ledger!$E:$E,AGGREGATE(15,6,ROW(Ledger!$B$3:$B$1002)/(Ledger!$B$3:$B$1002=$B$2),4))) | E9: =IF($A9="","",INDEX(Ledger!$F:$F,AGGREGATE(15,6,ROW(Ledger!$B$3:$B$1002)/(Ledger!$B$3:$B$1002=$B$2),4))) | F9: =IF($A9="","",INDEX(Ledger!$H:$H,AGGREGATE(15,6,ROW(Ledger!$B$3:$B$1002)/(Ledger!$B$3:$B$1002=$B$2),4))) | G9: =IF($A9="","",INDEX(Ledger!$I:$I,AGGREGATE(15,6,ROW(Ledger!$B$3:$B$1002)/(Ledger!$B$3:$B$1002=$B$2),4))) | H9: =IF($A9="","",INDEX(Ledger!$K:$K,AGGREGATE(15,6,ROW(Ledger!$B$3:$B$1002)/(Ledger!$B$3:$B$1002=$B$2),4)))
A10: =IFERROR(INDEX(Ledger!$A:$A,AGGREGATE(15,6,ROW(Ledger!$B$3:$B$1002)/(Ledger!$B$3:$B$1002=$B$2),5)),"") | B10: =IF($A10="","",INDEX(Ledger!$C:$C,AGGREGATE(15,6,ROW(Ledger!$B$3:$B$1002)/(Ledger!$B$3:$B$1002=$B$2),5))) | C10: =IF($A10="","",INDEX(Ledger!$D:$D,AGGREGATE(15,6,ROW(Ledger!$B$3:$B$1002)/(Ledger!$B$3:$B$1002=$B$2),5))) | D10: =IF($A10="","",INDEX(Ledger!$E:$E,AGGREGATE(15,6,ROW(Ledger!$B$3:$B$1002)/(Ledger!$B$3:$B$1002=$B$2),5))) | E10: =IF($A10="","",INDEX(Ledger!$F:$F,AGGREGATE(15,6,ROW(Ledger!$B$3:$B$1002)/(Ledger!$B$3:$B$1002=$B$2),5))) | F10: =IF($A10="","",INDEX(Ledger!$H:$H,AGGREGATE(15,6,ROW(Ledger!$B$3:$B$1002)/(Ledger!$B$3:$B$1002=$B$2),5))) | G10: =IF($A10="","",INDEX(Ledger!$I:$I,AGGREGATE(15,6,ROW(Ledger!$B$3:$B$1002)/(Ledger!$B$3:$B$1002=$B$2),5))) | H10: =IF($A10="","",INDEX(Ledger!$K:$K,AGGREGATE(15,6,ROW(Ledger!$B$3:$B$1002)/(Ledger!$B$3:$B$1002=$B$2),5)))
A11: =IFERROR(INDEX(Ledger!$A:$A,AGGREGATE(15,6,ROW(Ledger!$B$3:$B$1002)/(Ledger!$B$3:$B$1002=$B$2),6)),"") | B11: =IF($A11="","",INDEX(Ledger!$C:$C,AGGREGATE(15,6,ROW(Ledger!$B$3:$B$1002)/(Ledger!$B$3:$B$1002=$B$2),6))) | C11: =IF($A11="","",INDEX(Ledger!$D:$D,AGGREGATE(15,6,ROW(Ledger!$B$3:$B$1002)/(Ledger!$B$3:$B$1002=$B$2),6))) | D11: =IF($A11="","",INDEX(Ledger!$E:$E,AGGREGATE(15,6,ROW(Ledger!$B$3:$B$1002)/(Ledger!$B$3:$B$1002=$B$2),6))) | E11: =IF($A11="","",INDEX(Ledger!$F:$F,AGGREGATE(15,6,ROW(Ledger!$B$3:$B$1002)/(Ledger!$B$3:$B$1002=$B$2),6))) | F11: =IF($A11="","",INDEX(Ledger!$H:$H,AGGREGATE(15,6,ROW(Ledger!$B$3:$B$1002)/(Ledger!$B$3:$B$1002=$B$2),6))) | G11: =IF($A11="","",INDEX(Ledger!$I:$I,AGGREGATE(15,6,ROW(Ledger!$B$3:$B$1002)/(Ledger!$B$3:$B$1002=$B$2),6))) | H11: =IF($A11="","",INDEX(Ledger!$K:$K,AGGREGATE(15,6,ROW(Ledger!$B$3:$B$1002)/(Ledger!$B$3:$B$1002=$B$2),6)))
A12: =IFERROR(INDEX(Ledger!$A:$A,AGGREGATE(15,6,ROW(Ledger!$B$3:$B$1002)/(Ledger!$B$3:$B$1002=$B$2),7)),"") | B12: =IF($A12="","",INDEX(Ledger!$C:$C,AGGREGATE(15,6,ROW(Ledger!$B$3:$B$1002)/(Ledger!$B$3:$B$1002=$B$2),7))) | C12: =IF($A12="","",INDEX(Ledger!$D:$D,AGGREGATE(15,6,ROW(Ledger!$B$3:$B$1002)/(Ledger!$B$3:$B$1002=$B$2),7))) | D12: =IF($A12="","",INDEX(Ledger!$E:$E,AGGREGATE(15,6,ROW(Ledger!$B$3:$B$1002)/(Ledger!$B$3:$B$1002=$B$2),7))) | E12: =IF($A12="","",INDEX(Ledger!$F:$F,AGGREGATE(15,6,ROW(Ledger!$B$3:$B$1002)/(Ledger!$B$3:$B$1002=$B$2),7))) | F12: =IF($A12="","",INDEX(Ledger!$H:$H,AGGREGATE(15,6,ROW(Ledger!$B$3:$B$1002)/(Ledger!$B$3:$B$1002=$B$2),7))) | G12: =IF($A12="","",INDEX(Ledger!$I:$I,AGGREGATE(15,6,ROW(Ledger!$B$3:$B$1002)/(Ledger!$B$3:$B$1002=$B$2),7))) | H12: =IF($A12="","",INDEX(Ledger!$K:$K,AGGREGATE(15,6,ROW(Ledger!$B$3:$B$1002)/(Ledger!$B$3:$B$1002=$B$2),7)))
A13: =IFERROR(INDEX(Ledger!$A:$A,AGGREGATE(15,6,ROW(Ledger!$B$3:$B$1002)/(Ledger!$B$3:$B$1002=$B$2),8)),"") | B13: =IF($A13="","",INDEX(Ledger!$C:$C,AGGREGATE(15,6,ROW(Ledger!$B$3:$B$1002)/(Ledger!$B$3:$B$1002=$B$2),8))) | C13: =IF($A13="","",INDEX(Ledger!$D:$D,AGGREGATE(15,6,ROW(Ledger!$B$3:$B$1002)/(Ledger!$B$3:$B$1002=$B$2),8))) | D13: =IF($A13="","",INDEX(Ledger!$E:$E,AGGREGATE(15,6,ROW(Ledger!$B$3:$B$1002)/(Ledger!$B$3:$B$1002=$B$2),8))) | E13: =IF($A13="","",INDEX(Ledger!$F:$F,AGGREGATE(15,6,ROW(Ledger!$B$3:$B$1002)/(Ledger!$B$3:$B$1002=$B$2),8))) | F13: =IF($A13="","",INDEX(Ledger!$H:$H,AGGREGATE(15,6,ROW(Ledger!$B$3:$B$1002)/(Ledger!$B$3:$B$1002=$B$2),8))) | G13: =IF($A13="","",INDEX(Ledger!$I:$I,AGGREGATE(15,6,ROW(Ledger!$B$3:$B$1002)/(Ledger!$B$3:$B$1002=$B$2),8))) | H13: =IF($A13="","",INDEX(Ledger!$K:$K,AGGREGATE(15,6,ROW(Ledger!$B$3:$B$1002)/(Ledger!$B$3:$B$1002=$B$2),8)))
A14: =IFERROR(INDEX(Ledger!$A:$A,AGGREGATE(15,6,ROW(Ledger!$B$3:$B$1002)/(Ledger!$B$3:$B$1002=$B$2),9)),"") | B14: =IF($A14="","",INDEX(Ledger!$C:$C,AGGREGATE(15,6,ROW(Ledger!$B$3:$B$1002)/(Ledger!$B$3:$B$1002=$B$2),9))) | C14: =IF($A14="","",INDEX(Ledger!$D:$D,AGGREGATE(15,6,ROW(Ledger!$B$3:$B$1002)/(Ledger!$B$3:$B$1002=$B$2),9))) | D14: =IF($A14="","",INDEX(Ledger!$E:$E,AGGREGATE(15,6,ROW(Ledger!$B$3:$B$1002)/(Ledger!$B$3:$B$1002=$B$2),9))) | E14: =IF($A14="","",INDEX(Ledger!$F:$F,AGGREGATE(15,6,ROW(Ledger!$B$3:$B$1002)/(Ledger!$B$3:$B$1002=$B$2),9))) | F14: =IF($A14="","",INDEX(Ledger!$H:$H,AGGREGATE(15,6,ROW(Ledger!$B$3:$B$1002)/(Ledger!$B$3:$B$1002=$B$2),9))) | G14: =IF($A14="","",INDEX(Ledger!$I:$I,AGGREGATE(15,6,ROW(Ledger!$B$3:$B$1002)/(Ledger!$B$3:$B$1002=$B$2),9))) | H14: =IF($A14="","",INDEX(Ledger!$K:$K,AGGREGATE(15,6,ROW(Ledger!$B$3:$B$1002)/(Ledger!$B$3:$B$1002=$B$2),9)))
A15: =IFERROR(INDEX(Ledger!$A:$A,AGGREGATE(15,6,ROW(Ledger!$B$3:$B$1002)/(Ledger!$B$3:$B$1002=$B$2),10)),"") | B15: =IF($A15="","",INDEX(Ledger!$C:$C,AGGREGATE(15,6,ROW(Ledger!$B$3:$B$1002)/(Ledger!$B$3:$B$1002=$B$2),10))) | C15: =IF($A15="","",INDEX(Ledger!$D:$D,AGGREGATE(15,6,ROW(Ledger!$B$3:$B$1002)/(Ledger!$B$3:$B$1002=$B$2),10))) | D15: =IF($A15="","",INDEX(Ledger!$E:$E,AGGREGATE(15,6,ROW(Ledger!$B$3:$B$1002)/(Ledger!$B$3:$B$1002=$B$2),10))) | E15: =IF($A15="","",INDEX(Ledger!$F:$F,AGGREGATE(15,6,ROW(Ledger!$B$3:$B$1002)/(Ledger!$B$3:$B$1002=$B$2),10))) | F15: =IF($A15="","",INDEX(Ledger!$H:$H,AGGREGATE(15,6,ROW(Ledger!$B$3:$B$1002)/(Ledger!$B$3:$B$1002=$B$2),10))) | G15: =IF($A15="","",INDEX(Ledger!$I:$I,AGGREGATE(15,6,ROW(Ledger!$B$3:$B$1002)/(Ledger!$B$3:$B$1002=$B$2),10))) | H15: =IF($A15="","",INDEX(Ledger!$K:$K,AGGREGATE(15,6,ROW(Ledger!$B$3:$B$1002)/(Ledger!$B$3:$B$1002=$B$2),10)))
A16: =IFERROR(INDEX(Ledger!$A:$A,AGGREGATE(15,6,ROW(Ledger!$B$3:$B$1002)/(Ledger!$B$3:$B$1002=$B$2),11)),"") | B16: =IF($A16="","",INDEX(Ledger!$C:$C,AGGREGATE(15,6,ROW(Ledger!$B$3:$B$1002)/(Ledger!$B$3:$B$1002=$B$2),11))) | C16: =IF($A16="","",INDEX(Ledger!$D:$D,AGGREGATE(15,6,ROW(Ledger!$B$3:$B$1002)/(Ledger!$B$3:$B$1002=$B$2),11))) | D16: =IF($A16="","",INDEX(Ledger!$E:$E,AGGREGATE(15,6,ROW(Ledger!$B$3:$B$1002)/(Ledger!$B$3:$B$1002=$B$2),11))) | E16: =IF($A16="","",INDEX(Ledger!$F:$F,AGGREGATE(15,6,ROW(Ledger!$B$3:$B$1002)/(Ledger!$B$3:$B$1002=$B$2),11))) | F16: =IF($A16="","",INDEX(Ledger!$H:$H,AGGREGATE(15,6,ROW(Ledger!$B$3:$B$1002)/(Ledger!$B$3:$B$1002=$B$2),11))) | G16: =IF($A16="","",INDEX(Ledger!$I:$I,AGGREGATE(15,6,ROW(Ledger!$B$3:$B$1002)/(Ledger!$B$3:$B$1002=$B$2),11))) | H16: =IF($A16="","",INDEX(Ledger!$K:$K,AGGREGATE(15,6,ROW(Ledger!$B$3:$B$1002)/(Ledger!$B$3:$B$1002=$B$2),11)))
A17: =IFERROR(INDEX(Ledger!$A:$A,AGGREGATE(15,6,ROW(Ledger!$B$3:$B$1002)/(Ledger!$B$3:$B$1002=$B$2),12)),"") | B17: =IF($A17="","",INDEX(Ledger!$C:$C,AGGREGATE(15,6,ROW(Ledger!$B$3:$B$1002)/(Ledger!$B$3:$B$1002=$B$2),12))) | C17: =IF($A17="","",INDEX(Ledger!$D:$D,AGGREGATE(15,6,ROW(Ledger!$B$3:$B$1002)/(Ledger!$B$3:$B$1002=$B$2),12))) | D17: =IF($A17="","",INDEX(Ledger!$E:$E,AGGREGATE(15,6,ROW(Ledger!$B$3:$B$1002)/(Ledger!$B$3:$B$1002=$B$2),12))) | E17: =IF($A17="","",INDEX(Ledger!$F:$F,AGGREGATE(15,6,ROW(Ledger!$B$3:$B$1002)/(Ledger!$B$3:$B$1002=$B$2),12))) | F17: =IF($A17="","",INDEX(Ledger!$H:$H,AGGREGATE(15,6,ROW(Ledger!$B$3:$B$1002)/(Ledger!$B$3:$B$1002=$B$2),12))) | G17: =IF($A17="","",INDEX(Ledger!$I:$I,AGGREGATE(15,6,ROW(Ledger!$B$3:$B$1002)/(Ledger!$B$3:$B$1002=$B$2),12))) | H17: =IF($A17="","",INDEX(Ledger!$K:$K,AGGREGATE(15,6,ROW(Ledger!$B$3:$B$1002)/(Ledger!$B$3:$B$1002=$B$2),12)))
A18: =IFERROR(INDEX(Ledger!$A:$A,AGGREGATE(15,6,ROW(Ledger!$B$3:$B$1002)/(Ledger!$B$3:$B$1002=$B$2),13)),"") | B18: =IF($A18="","",INDEX(Ledger!$C:$C,AGGREGATE(15,6,ROW(Ledger!$B$3:$B$1002)/(Ledger!$B$3:$B$1002=$B$2),13))) | C18: =IF($A18="","",INDEX(Ledger!$D:$D,AGGREGATE(15,6,ROW(Ledger!$B$3:$B$1002)/(Ledger!$B$3:$B$1002=$B$2),13))) | D18: =IF($A18="","",INDEX(Ledger!$E:$E,AGGREGATE(15,6,ROW(Ledger!$B$3:$B$1002)/(Ledger!$B$3:$B$1002=$B$2),13))) | E18: =IF($A18="","",INDEX(Ledger!$F:$F,AGGREGATE(15,6,ROW(Ledger!$B$3:$B$1002)/(Ledger!$B$3:$B$1002=$B$2),13))) | F18: =IF($A18="","",INDEX(Ledger!$H:$H,AGGREGATE(15,6,ROW(Ledger!$B$3:$B$1002)/(Ledger!$B$3:$B$1002=$B$2),13))) | G18: =IF($A18="","",INDEX(Ledger!$I:$I,AGGREGATE(15,6,ROW(Ledger!$B$3:$B$1002)/(Ledger!$B$3:$B$1002=$B$2),13))) | H18: =IF($A18="","",INDEX(Ledger!$K:$K,AGGREGATE(15,6,ROW(Ledger!$B$3:$B$1002)/(Ledger!$B$3:$B$1002=$B$2),13)))
A19: =IFERROR(INDEX(Ledger!$A:$A,AGGREGATE(15,6,ROW(Ledger!$B$3:$B$1002)/(Ledger!$B$3:$B$1002=$B$2),14)),"") | B19: =IF($A19="","",INDEX(Ledger!$C:$C,AGGREGATE(15,6,ROW(Ledger!$B$3:$B$1002)/(Ledger!$B$3:$B$1002=$B$2),14))) | C19: =IF($A19="","",INDEX(Ledger!$D:$D,AGGREGATE(15,6,ROW(Ledger!$B$3:$B$1002)/(Ledger!$B$3:$B$1002=$B$2),14))) | D19: =IF($A19="","",INDEX(Ledger!$E:$E,AGGREGATE(15,6,ROW(Ledger!$B$3:$B$1002)/(Ledger!$B$3:$B$1002=$B$2),14))) | E19: =IF($A19="","",INDEX(Ledger!$F:$F,AGGREGATE(15,6,ROW(Ledger!$B$3:$B$1002)/(Ledger!$B$3:$B$1002=$B$2),14))) | F19: =IF($A19="","",INDEX(Ledger!$H:$H,AGGREGATE(15,6,ROW(Ledger!$B$3:$B$1002)/(Ledger!$B$3:$B$1002=$B$2),14))) | G19: =IF($A19="","",INDEX(Ledger!$I:$I,AGGREGATE(15,6,ROW(Ledger!$B$3:$B$1002)/(Ledger!$B$3:$B$1002=$B$2),14))) | H19: =IF($A19="","",INDEX(Ledger!$K:$K,AGGREGATE(15,6,ROW(Ledger!$B$3:$B$1002)/(Ledger!$B$3:$B$1002=$B$2),14)))
A20: =IFERROR(INDEX(Ledger!$A:$A,AGGREGATE(15,6,ROW(Ledger!$B$3:$B$1002)/(Ledger!$B$3:$B$1002=$B$2),15)),"") | B20: =IF($A20="","",INDEX(Ledger!$C:$C,AGGREGATE(15,6,ROW(Ledger!$B$3:$B$1002)/(Ledger!$B$3:$B$1002=$B$2),15))) | C20: =IF($A20="","",INDEX(Ledger!$D:$D,AGGREGATE(15,6,ROW(Ledger!$B$3:$B$1002)/(Ledger!$B$3:$B$1002=$B$2),15))) | D20: =IF($A20="","",INDEX(Ledger!$E:$E,AGGREGATE(15,6,ROW(Ledger!$B$3:$B$1002)/(Ledger!$B$3:$B$1002=$B$2),15))) | E20: =IF($A20="","",INDEX(Ledger!$F:$F,AGGREGATE(15,6,ROW(Ledger!$B$3:$B$1002)/(Ledger!$B$3:$B$1002=$B$2),15))) | F20: =IF($A20="","",INDEX(Ledger!$H:$H,AGGREGATE(15,6,ROW(Ledger!$B$3:$B$1002)/(Ledger!$B$3:$B$1002=$B$2),15))) | G20: =IF($A20="","",INDEX(Ledger!$I:$I,AGGREGATE(15,6,ROW(Ledger!$B$3:$B$1002)/(Ledger!$B$3:$B$1002=$B$2),15))) | H20: =IF($A20="","",INDEX(Ledger!$K:$K,AGGREGATE(15,6,ROW(Ledger!$B$3:$B$1002)/(Ledger!$B$3:$B$1002=$B$2),15)))
A21: =IFERROR(INDEX(Ledger!$A:$A,AGGREGATE(15,6,ROW(Ledger!$B$3:$B$1002)/(Ledger!$B$3:$B$1002=$B$2),16)),"") | B21: =IF($A21="","",INDEX(Ledger!$C:$C,AGGREGATE(15,6,ROW(Ledger!$B$3:$B$1002)/(Ledger!$B$3:$B$1002=$B$2),16))) | C21: =IF($A21="","",INDEX(Ledger!$D:$D,AGGREGATE(15,6,ROW(Ledger!$B$3:$B$1002)/(Ledger!$B$3:$B$1002=$B$2),16))) | D21: =IF($A21="","",INDEX(Ledger!$E:$E,AGGREGATE(15,6,ROW(Ledger!$B$3:$B$1002)/(Ledger!$B$3:$B$1002=$B$2),16))) | E21: =IF($A21="","",INDEX(Ledger!$F:$F,AGGREGATE(15,6,ROW(Ledger!$B$3:$B$1002)/(Ledger!$B$3:$B$1002=$B$2),16))) | F21: =IF($A21="","",INDEX(Ledger!$H:$H,AGGREGATE(15,6,ROW(Ledger!$B$3:$B$1002)/(Ledger!$B$3:$B$1002=$B$2),16))) | G21: =IF($A21="","",INDEX(Ledger!$I:$I,AGGREGATE(15,6,ROW(Ledger!$B$3:$B$1002)/(Ledger!$B$3:$B$1002=$B$2),16))) | H21: =IF($A21="","",INDEX(Ledger!$K:$K,AGGREGATE(15,6,ROW(Ledger!$B$3:$B$1002)/(Ledger!$B$3:$B$1002=$B$2),16)))
A22: =IFERROR(INDEX(Ledger!$A:$A,AGGREGATE(15,6,ROW(Ledger!$B$3:$B$1002)/(Ledger!$B$3:$B$1002=$B$2),17)),"") | B22: =IF($A22="","",INDEX(Ledger!$C:$C,AGGREGATE(15,6,ROW(Ledger!$B$3:$B$1002)/(Ledger!$B$3:$B$1002=$B$2),17))) | C22: =IF($A22="","",INDEX(Ledger!$D:$D,AGGREGATE(15,6,ROW(Ledger!$B$3:$B$1002)/(Ledger!$B$3:$B$1002=$B$2),17))) | D22: =IF($A22="","",INDEX(Ledger!$E:$E,AGGREGATE(15,6,ROW(Ledger!$B$3:$B$1002)/(Ledger!$B$3:$B$1002=$B$2),17))) | E22: =IF($A22="","",INDEX(Ledger!$F:$F,AGGREGATE(15,6,ROW(Ledger!$B$3:$B$1002)/(Ledger!$B$3:$B$1002=$B$2),17))) | F22: =IF($A22="","",INDEX(Ledger!$H:$H,AGGREGATE(15,6,ROW(Ledger!$B$3:$B$1002)/(Ledger!$B$3:$B$1002=$B$2),17))) | G22: =IF($A22="","",INDEX(Ledger!$I:$I,AGGREGATE(15,6,ROW(Ledger!$B$3:$B$1002)/(Ledger!$B$3:$B$1002=$B$2),17))) | H22: =IF($A22="","",INDEX(Ledger!$K:$K,AGGREGATE(15,6,ROW(Ledger!$B$3:$B$1002)/(Ledger!$B$3:$B$1002=$B$2),17)))
A23: =IFERROR(INDEX(Ledger!$A:$A,AGGREGATE(15,6,ROW(Ledger!$B$3:$B$1002)/(Ledger!$B$3:$B$1002=$B$2),18)),"") | B23: =IF($A23="","",INDEX(Ledger!$C:$C,AGGREGATE(15,6,ROW(Ledger!$B$3:$B$1002)/(Ledger!$B$3:$B$1002=$B$2),18))) | C23: =IF($A23="","",INDEX(Ledger!$D:$D,AGGREGATE(15,6,ROW(Ledger!$B$3:$B$1002)/(Ledger!$B$3:$B$1002=$B$2),18))) | D23: =IF($A23="","",INDEX(Ledger!$E:$E,AGGREGATE(15,6,ROW(Ledger!$B$3:$B$1002)/(Ledger!$B$3:$B$1002=$B$2),18))) | E23: =IF($A23="","",INDEX(Ledger!$F:$F,AGGREGATE(15,6,ROW(Ledger!$B$3:$B$1002)/(Ledger!$B$3:$B$1002=$B$2),18))) | F23: =IF($A23="","",INDEX(Ledger!$H:$H,AGGREGATE(15,6,ROW(Ledger!$B$3:$B$1002)/(Ledger!$B$3:$B$1002=$B$2),18))) | G23: =IF($A23="","",INDEX(Ledger!$I:$I,AGGREGATE(15,6,ROW(Ledger!$B$3:$B$1002)/(Ledger!$B$3:$B$1002=$B$2),18))) | H23: =IF($A23="","",INDEX(Ledger!$K:$K,AGGREGATE(15,6,ROW(Ledger!$B$3:$B$1002)/(Ledger!$B$3:$B$1002=$B$2),18)))
A24: =IFERROR(INDEX(Ledger!$A:$A,AGGREGATE(15,6,ROW(Ledger!$B$3:$B$1002)/(Ledger!$B$3:$B$1002=$B$2),19)),"") | B24: =IF($A24="","",INDEX(Ledger!$C:$C,AGGREGATE(15,6,ROW(Ledger!$B$3:$B$1002)/(Ledger!$B$3:$B$1002=$B$2),19))) | C24: =IF($A24="","",INDEX(Ledger!$D:$D,AGGREGATE(15,6,ROW(Ledger!$B$3:$B$1002)/(Ledger!$B$3:$B$1002=$B$2),19))) | D24: =IF($A24="","",INDEX(Ledger!$E:$E,AGGREGATE(15,6,ROW(Ledger!$B$3:$B$1002)/(Ledger!$B$3:$B$1002=$B$2),19))) | E24: =IF($A24="","",INDEX(Ledger!$F:$F,AGGREGATE(15,6,ROW(Ledger!$B$3:$B$1002)/(Ledger!$B$3:$B$1002=$B$2),19))) | F24: =IF($A24="","",INDEX(Ledger!$H:$H,AGGREGATE(15,6,ROW(Ledger!$B$3:$B$1002)/(Ledger!$B$3:$B$1002=$B$2),19))) | G24: =IF($A24="","",INDEX(Ledger!$I:$I,AGGREGATE(15,6,ROW(Ledger!$B$3:$B$1002)/(Ledger!$B$3:$B$1002=$B$2),19))) | H24: =IF($A24="","",INDEX(Ledger!$K:$K,AGGREGATE(15,6,ROW(Ledger!$B$3:$B$1002)/(Ledger!$B$3:$B$1002=$B$2),19)))
A25: =IFERROR(INDEX(Ledger!$A:$A,AGGREGATE(15,6,ROW(Ledger!$B$3:$B$1002)/(Ledger!$B$3:$B$1002=$B$2),20)),"") | B25: =IF($A25="","",INDEX(Ledger!$C:$C,AGGREGATE(15,6,ROW(Ledger!$B$3:$B$1002)/(Ledger!$B$3:$B$1002=$B$2),20))) | C25: =IF($A25="","",INDEX(Ledger!$D:$D,AGGREGATE(15,6,ROW(Ledger!$B$3:$B$1002)/(Ledger!$B$3:$B$1002=$B$2),20))) | D25: =IF($A25="","",INDEX(Ledger!$E:$E,AGGREGATE(15,6,ROW(Ledger!$B$3:$B$1002)/(Ledger!$B$3:$B$1002=$B$2),20))) | E25: =IF($A25="","",INDEX(Ledger!$F:$F,AGGREGATE(15,6,ROW(Ledger!$B$3:$B$1002)/(Ledger!$B$3:$B$1002=$B$2),20))) | F25: =IF($A25="","",INDEX(Ledger!$H:$H,AGGREGATE(15,6,ROW(Ledger!$B$3:$B$1002)/(Ledger!$B$3:$B$1002=$B$2),20))) | G25: =IF($A25="","",INDEX(Ledger!$I:$I,AGGREGATE(15,6,ROW(Ledger!$B$3:$B$1002)/(Ledger!$B$3:$B$1002=$B$2),20))) | H25: =IF($A25="","",INDEX(Ledger!$K:$K,AGGREGATE(15,6,ROW(Ledger!$B$3:$B$1002)/(Ledger!$B$3:$B$1002=$B$2),20)))
A26: =IFERROR(INDEX(Ledger!$A:$A,AGGREGATE(15,6,ROW(Ledger!$B$3:$B$1002)/(Ledger!$B$3:$B$1002=$B$2),21)),"") | B26: =IF($A26="","",INDEX(Ledger!$C:$C,AGGREGATE(15,6,ROW(Ledger!$B$3:$B$1002)/(Ledger!$B$3:$B$1002=$B$2),21))) | C26: =IF($A26="","",INDEX(Ledger!$D:$D,AGGREGATE(15,6,ROW(Ledger!$B$3:$B$1002)/(Ledger!$B$3:$B$1002=$B$2),21))) | D26: =IF($A26="","",INDEX(Ledger!$E:$E,AGGREGATE(15,6,ROW(Ledger!$B$3:$B$1002)/(Ledger!$B$3:$B$1002=$B$2),21))) | E26: =IF($A26="","",INDEX(Ledger!$F:$F,AGGREGATE(15,6,ROW(Ledger!$B$3:$B$1002)/(Ledger!$B$3:$B$1002=$B$2),21))) | F26: =IF($A26="","",INDEX(Ledger!$H:$H,AGGREGATE(15,6,ROW(Ledger!$B$3:$B$1002)/(Ledger!$B$3:$B$1002=$B$2),21))) | G26: =IF($A26="","",INDEX(Ledger!$I:$I,AGGREGATE(15,6,ROW(Ledger!$B$3:$B$1002)/(Ledger!$B$3:$B$1002=$B$2),21))) | H26: =IF($A26="","",INDEX(Ledger!$K:$K,AGGREGATE(15,6,ROW(Ledger!$B$3:$B$1002)/(Ledger!$B$3:$B$1002=$B$2),21)))
A27: =IFERROR(INDEX(Ledger!$A:$A,AGGREGATE(15,6,ROW(Ledger!$B$3:$B$1002)/(Ledger!$B$3:$B$1002=$B$2),22)),"") | B27: =IF($A27="","",INDEX(Ledger!$C:$C,AGGREGATE(15,6,ROW(Ledger!$B$3:$B$1002)/(Ledger!$B$3:$B$1002=$B$2),22))) | C27: =IF($A27="","",INDEX(Ledger!$D:$D,AGGREGATE(15,6,ROW(Ledger!$B$3:$B$1002)/(Ledger!$B$3:$B$1002=$B$2),22))) | D27: =IF($A27="","",INDEX(Ledger!$E:$E,AGGREGATE(15,6,ROW(Ledger!$B$3:$B$1002)/(Ledger!$B$3:$B$1002=$B$2),22))) | E27: =IF($A27="","",INDEX(Ledger!$F:$F,AGGREGATE(15,6,ROW(Ledger!$B$3:$B$1002)/(Ledger!$B$3:$B$1002=$B$2),22))) | F27: =IF($A27="","",INDEX(Ledger!$H:$H,AGGREGATE(15,6,ROW(Ledger!$B$3:$B$1002)/(Ledger!$B$3:$B$1002=$B$2),22))) | G27: =IF($A27="","",INDEX(Ledger!$I:$I,AGGREGATE(15,6,ROW(Ledger!$B$3:$B$1002)/(Ledger!$B$3:$B$1002=$B$2),22))) | H27: =IF($A27="","",INDEX(Ledger!$K:$K,AGGREGATE(15,6,ROW(Ledger!$B$3:$B$1002)/(Ledger!$B$3:$B$1002=$B$2),22)))
A28: =IFERROR(INDEX(Ledger!$A:$A,AGGREGATE(15,6,ROW(Ledger!$B$3:$B$1002)/(Ledger!$B$3:$B$1002=$B$2),23)),"") | B28: =IF($A28="","",INDEX(Ledger!$C:$C,AGGREGATE(15,6,ROW(Ledger!$B$3:$B$1002)/(Ledger!$B$3:$B$1002=$B$2),23))) | C28: =IF($A28="","",INDEX(Ledger!$D:$D,AGGREGATE(15,6,ROW(Ledger!$B$3:$B$1002)/(Ledger!$B$3:$B$1002=$B$2),23))) | D28: =IF($A28="","",INDEX(Ledger!$E:$E,AGGREGATE(15,6,ROW(Ledger!$B$3:$B$1002)/(Ledger!$B$3:$B$1002=$B$2),23))) | E28: =IF($A28="","",INDEX(Ledger!$F:$F,AGGREGATE(15,6,ROW(Ledger!$B$3:$B$1002)/(Ledger!$B$3:$B$1002=$B$2),23))) | F28: =IF($A28="","",INDEX(Ledger!$H:$H,AGGREGATE(15,6,ROW(Ledger!$B$3:$B$1002)/(Ledger!$B$3:$B$1002=$B$2),23))) | G28: =IF($A28="","",INDEX(Ledger!$I:$I,AGGREGATE(15,6,ROW(Ledger!$B$3:$B$1002)/(Ledger!$B$3:$B$1002=$B$2),23))) | H28: =IF($A28="","",INDEX(Ledger!$K:$K,AGGREGATE(15,6,ROW(Ledger!$B$3:$B$1002)/(Ledger!$B$3:$B$1002=$B$2),23)))
A29: =IFERROR(INDEX(Ledger!$A:$A,AGGREGATE(15,6,ROW(Ledger!$B$3:$B$1002)/(Ledger!$B$3:$B$1002=$B$2),24)),"") | B29: =IF($A29="","",INDEX(Ledger!$C:$C,AGGREGATE(15,6,ROW(Ledger!$B$3:$B$1002)/(Ledger!$B$3:$B$1002=$B$2),24))) | C29: =IF($A29="","",INDEX(Ledger!$D:$D,AGGREGATE(15,6,ROW(Ledger!$B$3:$B$1002)/(Ledger!$B$3:$B$1002=$B$2),24))) | D29: =IF($A29="","",INDEX(Ledger!$E:$E,AGGREGATE(15,6,ROW(Ledger!$B$3:$B$1002)/(Ledger!$B$3:$B$1002=$B$2),24))) | E29: =IF($A29="","",INDEX(Ledger!$F:$F,AGGREGATE(15,6,ROW(Ledger!$B$3:$B$1002)/(Ledger!$B$3:$B$1002=$B$2),24))) | F29: =IF($A29="","",INDEX(Ledger!$H:$H,AGGREGATE(15,6,ROW(Ledger!$B$3:$B$1002)/(Ledger!$B$3:$B$1002=$B$2),24))) | G29: =IF($A29="","",INDEX(Ledger!$I:$I,AGGREGATE(15,6,ROW(Ledger!$B$3:$B$1002)/(Ledger!$B$3:$B$1002=$B$2),24))) | H29: =IF($A29="","",INDEX(Ledger!$K:$K,AGGREGATE(15,6,ROW(Ledger!$B$3:$B$1002)/(Ledger!$B$3:$B$1002=$B$2),24)))
A30: =IFERROR(INDEX(Ledger!$A:$A,AGGREGATE(15,6,ROW(Ledger!$B$3:$B$1002)/(Ledger!$B$3:$B$1002=$B$2),25)),"") | B30: =IF($A30="","",INDEX(Ledger!$C:$C,AGGREGATE(15,6,ROW(Ledger!$B$3:$B$1002)/(Ledger!$B$3:$B$1002=$B$2),25))) | C30: =IF($A30="","",INDEX(Ledger!$D:$D,AGGREGATE(15,6,ROW(Ledger!$B$3:$B$1002)/(Ledger!$B$3:$B$1002=$B$2),25))) | D30: =IF($A30="","",INDEX(Ledger!$E:$E,AGGREGATE(15,6,ROW(Ledger!$B$3:$B$1002)/(Ledger!$B$3:$B$1002=$B$2),25))) | E30: =IF($A30="","",INDEX(Ledger!$F:$F,AGGREGATE(15,6,ROW(Ledger!$B$3:$B$1002)/(Ledger!$B$3:$B$1002=$B$2),25))) | F30: =IF($A30="","",INDEX(Ledger!$H:$H,AGGREGATE(15,6,ROW(Ledger!$B$3:$B$1002)/(Ledger!$B$3:$B$1002=$B$2),25))) | G30: =IF($A30="","",INDEX(Ledger!$I:$I,AGGREGATE(15,6,ROW(Ledger!$B$3:$B$1002)/(Ledger!$B$3:$B$1002=$B$2),25))) | H30: =IF($A30="","",INDEX(Ledger!$K:$K,AGGREGATE(15,6,ROW(Ledger!$B$3:$B$1002)/(Ledger!$B$3:$B$1002=$B$2),25)))
A31: =IFERROR(INDEX(Ledger!$A:$A,AGGREGATE(15,6,ROW(Ledger!$B$3:$B$1002)/(Ledger!$B$3:$B$1002=$B$2),26)),"") | B31: =IF($A31="","",INDEX(Ledger!$C:$C,AGGREGATE(15,6,ROW(Ledger!$B$3:$B$1002)/(Ledger!$B$3:$B$1002=$B$2),26))) | C31: =IF($A31="","",INDEX(Ledger!$D:$D,AGGREGATE(15,6,ROW(Ledger!$B$3:$B$1002)/(Ledger!$B$3:$B$1002=$B$2),26))) | D31: =IF($A31="","",INDEX(Ledger!$E:$E,AGGREGATE(15,6,ROW(Ledger!$B$3:$B$1002)/(Ledger!$B$3:$B$1002=$B$2),26))) | E31: =IF($A31="","",INDEX(Ledger!$F:$F,AGGREGATE(15,6,ROW(Ledger!$B$3:$B$1002)/(Ledger!$B$3:$B$1002=$B$2),26))) | F31: =IF($A31="","",INDEX(Ledger!$H:$H,AGGREGATE(15,6,ROW(Ledger!$B$3:$B$1002)/(Ledger!$B$3:$B$1002=$B$2),26))) | G31: =IF($A31="","",INDEX(Ledger!$I:$I,AGGREGATE(15,6,ROW(Ledger!$B$3:$B$1002)/(Ledger!$B$3:$B$1002=$B$2),26))) | H31: =IF($A31="","",INDEX(Ledger!$K:$K,AGGREGATE(15,6,ROW(Ledger!$B$3:$B$1002)/(Ledger!$B$3:$B$1002=$B$2),26)))
A32: =IFERROR(INDEX(Ledger!$A:$A,AGGREGATE(15,6,ROW(Ledger!$B$3:$B$1002)/(Ledger!$B$3:$B$1002=$B$2),27)),"") | B32: =IF($A32="","",INDEX(Ledger!$C:$C,AGGREGATE(15,6,ROW(Ledger!$B$3:$B$1002)/(Ledger!$B$3:$B$1002=$B$2),27))) | C32: =IF($A32="","",INDEX(Ledger!$D:$D,AGGREGATE(15,6,ROW(Ledger!$B$3:$B$1002)/(Ledger!$B$3:$B$1002=$B$2),27))) | D32: =IF($A32="","",INDEX(Ledger!$E:$E,AGGREGATE(15,6,ROW(Ledger!$B$3:$B$1002)/(Ledger!$B$3:$B$1002=$B$2),27))) | E32: =IF($A32="","",INDEX(Ledger!$F:$F,AGGREGATE(15,6,ROW(Ledger!$B$3:$B$1002)/(Ledger!$B$3:$B$1002=$B$2),27))) | F32: =IF($A32="","",INDEX(Ledger!$H:$H,AGGREGATE(15,6,ROW(Ledger!$B$3:$B$1002)/(Ledger!$B$3:$B$1002=$B$2),27))) | G32: =IF($A32="","",INDEX(Ledger!$I:$I,AGGREGATE(15,6,ROW(Ledger!$B$3:$B$1002)/(Ledger!$B$3:$B$1002=$B$2),27))) | H32: =IF($A32="","",INDEX(Ledger!$K:$K,AGGREGATE(15,6,ROW(Ledger!$B$3:$B$1002)/(Ledger!$B$3:$B$1002=$B$2),27)))
A33: =IFERROR(INDEX(Ledger!$A:$A,AGGREGATE(15,6,ROW(Ledger!$B$3:$B$1002)/(Ledger!$B$3:$B$1002=$B$2),28)),"") | B33: =IF($A33="","",INDEX(Ledger!$C:$C,AGGREGATE(15,6,ROW(Ledger!$B$3:$B$1002)/(Ledger!$B$3:$B$1002=$B$2),28))) | C33: =IF($A33="","",INDEX(Ledger!$D:$D,AGGREGATE(15,6,ROW(Ledger!$B$3:$B$1002)/(Ledger!$B$3:$B$1002=$B$2),28))) | D33: =IF($A33="","",INDEX(Ledger!$E:$E,AGGREGATE(15,6,ROW(Ledger!$B$3:$B$1002)/(Ledger!$B$3:$B$1002=$B$2),28))) | E33: =IF($A33="","",INDEX(Ledger!$F:$F,AGGREGATE(15,6,ROW(Ledger!$B$3:$B$1002)/(Ledger!$B$3:$B$1002=$B$2),28))) | F33: =IF($A33="","",INDEX(Ledger!$H:$H,AGGREGATE(15,6,ROW(Ledger!$B$3:$B$1002)/(Ledger!$B$3:$B$1002=$B$2),28))) | G33: =IF($A33="","",INDEX(Ledger!$I:$I,AGGREGATE(15,6,ROW(Ledger!$B$3:$B$1002)/(Ledger!$B$3:$B$1002=$B$2),28))) | H33: =IF($A33="","",INDEX(Ledger!$K:$K,AGGREGATE(15,6,ROW(Ledger!$B$3:$B$1002)/(Ledger!$B$3:$B$1002=$B$2),28)))
A34: =IFERROR(INDEX(Ledger!$A:$A,AGGREGATE(15,6,ROW(Ledger!$B$3:$B$1002)/(Ledger!$B$3:$B$1002=$B$2),29)),"") | B34: =IF($A34="","",INDEX(Ledger!$C:$C,AGGREGATE(15,6,ROW(Ledger!$B$3:$B$1002)/(Ledger!$B$3:$B$1002=$B$2),29))) | C34: =IF($A34="","",INDEX(Ledger!$D:$D,AGGREGATE(15,6,ROW(Ledger!$B$3:$B$1002)/(Ledger!$B$3:$B$1002=$B$2),29))) | D34: =IF($A34="","",INDEX(Ledger!$E:$E,AGGREGATE(15,6,ROW(Ledger!$B$3:$B$1002)/(Ledger!$B$3:$B$1002=$B$2),29))) | E34: =IF($A34="","",INDEX(Ledger!$F:$F,AGGREGATE(15,6,ROW(Ledger!$B$3:$B$1002)/(Ledger!$B$3:$B$1002=$B$2),29))) | F34: =IF($A34="","",INDEX(Ledger!$H:$H,AGGREGATE(15,6,ROW(Ledger!$B$3:$B$1002)/(Ledger!$B$3:$B$1002=$B$2),29))) | G34: =IF($A34="","",INDEX(Ledger!$I:$I,AGGREGATE(15,6,ROW(Ledger!$B$3:$B$1002)/(Ledger!$B$3:$B$1002=$B$2),29))) | H34: =IF($A34="","",INDEX(Ledger!$K:$K,AGGREGATE(15,6,ROW(Ledger!$B$3:$B$1002)/(Ledger!$B$3:$B$1002=$B$2),29)))
A35: =IFERROR(INDEX(Ledger!$A:$A,AGGREGATE(15,6,ROW(Ledger!$B$3:$B$1002)/(Ledger!$B$3:$B$1002=$B$2),30)),"") | B35: =IF($A35="","",INDEX(Ledger!$C:$C,AGGREGATE(15,6,ROW(Ledger!$B$3:$B$1002)/(Ledger!$B$3:$B$1002=$B$2),30))) | C35: =IF($A35="","",INDEX(Ledger!$D:$D,AGGREGATE(15,6,ROW(Ledger!$B$3:$B$1002)/(Ledger!$B$3:$B$1002=$B$2),30))) | D35: =IF($A35="","",INDEX(Ledger!$E:$E,AGGREGATE(15,6,ROW(Ledger!$B$3:$B$1002)/(Ledger!$B$3:$B$1002=$B$2),30))) | E35: =IF($A35="","",INDEX(Ledger!$F:$F,AGGREGATE(15,6,ROW(Ledger!$B$3:$B$1002)/(Ledger!$B$3:$B$1002=$B$2),30))) | F35: =IF($A35="","",INDEX(Ledger!$H:$H,AGGREGATE(15,6,ROW(Ledger!$B$3:$B$1002)/(Ledger!$B$3:$B$1002=$B$2),30))) | G35: =IF($A35="","",INDEX(Ledger!$I:$I,AGGREGATE(15,6,ROW(Ledger!$B$3:$B$1002)/(Ledger!$B$3:$B$1002=$B$2),30))) | H35: =IF($A35="","",INDEX(Ledger!$K:$K,AGGREGATE(15,6,ROW(Ledger!$B$3:$B$1002)/(Ledger!$B$3:$B$1002=$B$2),30)))
A36: =IFERROR(INDEX(Ledger!$A:$A,AGGREGATE(15,6,ROW(Ledger!$B$3:$B$1002)/(Ledger!$B$3:$B$1002=$B$2),31)),"") | B36: =IF($A36="","",INDEX(Ledger!$C:$C,AGGREGATE(15,6,ROW(Ledger!$B$3:$B$1002)/(Ledger!$B$3:$B$1002=$B$2),31))) | C36: =IF($A36="","",INDEX(Ledger!$D:$D,AGGREGATE(15,6,ROW(Ledger!$B$3:$B$1002)/(Ledger!$B$3:$B$1002=$B$2),31))) | D36: =IF($A36="","",INDEX(Ledger!$E:$E,AGGREGATE(15,6,ROW(Ledger!$B$3:$B$1002)/(Ledger!$B$3:$B$1002=$B$2),31))) | E36: =IF($A36="","",INDEX(Ledger!$F:$F,AGGREGATE(15,6,ROW(Ledger!$B$3:$B$1002)/(Ledger!$B$3:$B$1002=$B$2),31))) | F36: =IF($A36="","",INDEX(Ledger!$H:$H,AGGREGATE(15,6,ROW(Ledger!$B$3:$B$1002)/(Ledger!$B$3:$B$1002=$B$2),31))) | G36: =IF($A36="","",INDEX(Ledger!$I:$I,AGGREGATE(15,6,ROW(Ledger!$B$3:$B$1002)/(Ledger!$B$3:$B$1002=$B$2),31))) | H36: =IF($A36="","",INDEX(Ledger!$K:$K,AGGREGATE(15,6,ROW(Ledger!$B$3:$B$1002)/(Ledger!$B$3:$B$1002=$B$2),31)))
A37: =IFERROR(INDEX(Ledger!$A:$A,AGGREGATE(15,6,ROW(Ledger!$B$3:$B$1002)/(Ledger!$B$3:$B$1002=$B$2),32)),"") | B37: =IF($A37="","",INDEX(Ledger!$C:$C,AGGREGATE(15,6,ROW(Ledger!$B$3:$B$1002)/(Ledger!$B$3:$B$1002=$B$2),32))) | C37: =IF($A37="","",INDEX(Ledger!$D:$D,AGGREGATE(15,6,ROW(Ledger!$B$3:$B$1002)/(Ledger!$B$3:$B$1002=$B$2),32))) | D37: =IF($A37="","",INDEX(Ledger!$E:$E,AGGREGATE(15,6,ROW(Ledger!$B$3:$B$1002)/(Ledger!$B$3:$B$1002=$B$2),32))) | E37: =IF($A37="","",INDEX(Ledger!$F:$F,AGGREGATE(15,6,ROW(Ledger!$B$3:$B$1002)/(Ledger!$B$3:$B$1002=$B$2),32))) | F37: =IF($A37="","",INDEX(Ledger!$H:$H,AGGREGATE(15,6,ROW(Ledger!$B$3:$B$1002)/(Ledger!$B$3:$B$1002=$B$2),32))) | G37: =IF($A37="","",INDEX(Ledger!$I:$I,AGGREGATE(15,6,ROW(Ledger!$B$3:$B$1002)/(Ledger!$B$3:$B$1002=$B$2),32))) | H37: =IF($A37="","",INDEX(Ledger!$K:$K,AGGREGATE(15,6,ROW(Ledger!$B$3:$B$1002)/(Ledger!$B$3:$B$1002=$B$2),32)))
A38: =IFERROR(INDEX(Ledger!$A:$A,AGGREGATE(15,6,ROW(Ledger!$B$3:$B$1002)/(Ledger!$B$3:$B$1002=$B$2),33)),"") | B38: =IF($A38="","",INDEX(Ledger!$C:$C,AGGREGATE(15,6,ROW(Ledger!$B$3:$B$1002)/(Ledger!$B$3:$B$1002=$B$2),33))) | C38: =IF($A38="","",INDEX(Ledger!$D:$D,AGGREGATE(15,6,ROW(Ledger!$B$3:$B$1002)/(Ledger!$B$3:$B$1002=$B$2),33))) | D38: =IF($A38="","",INDEX(Ledger!$E:$E,AGGREGATE(15,6,ROW(Ledger!$B$3:$B$1002)/(Ledger!$B$3:$B$1002=$B$2),33))) | E38: =IF($A38="","",INDEX(Ledger!$F:$F,AGGREGATE(15,6,ROW(Ledger!$B$3:$B$1002)/(Ledger!$B$3:$B$1002=$B$2),33))) | F38: =IF($A38="","",INDEX(Ledger!$H:$H,AGGREGATE(15,6,ROW(Ledger!$B$3:$B$1002)/(Ledger!$B$3:$B$1002=$B$2),33))) | G38: =IF($A38="","",INDEX(Ledger!$I:$I,AGGREGATE(15,6,ROW(Ledger!$B$3:$B$1002)/(Ledger!$B$3:$B$1002=$B$2),33))) | H38: =IF($A38="","",INDEX(Ledger!$K:$K,AGGREGATE(15,6,ROW(Ledger!$B$3:$B$1002)/(Ledger!$B$3:$B$1002=$B$2),33)))
A39: =IFERROR(INDEX(Ledger!$A:$A,AGGREGATE(15,6,ROW(Ledger!$B$3:$B$1002)/(Ledger!$B$3:$B$1002=$B$2),34)),"") | B39: =IF($A39="","",INDEX(Ledger!$C:$C,AGGREGATE(15,6,ROW(Ledger!$B$3:$B$1002)/(Ledger!$B$3:$B$1002=$B$2),34))) | C39: =IF($A39="","",INDEX(Ledger!$D:$D,AGGREGATE(15,6,ROW(Ledger!$B$3:$B$1002)/(Ledger!$B$3:$B$1002=$B$2),34))) | D39: =IF($A39="","",INDEX(Ledger!$E:$E,AGGREGATE(15,6,ROW(Ledger!$B$3:$B$1002)/(Ledger!$B$3:$B$1002=$B$2),34))) | E39: =IF($A39="","",INDEX(Ledger!$F:$F,AGGREGATE(15,6,ROW(Ledger!$B$3:$B$1002)/(Ledger!$B$3:$B$1002=$B$2),34))) | F39: =IF($A39="","",INDEX(Ledger!$H:$H,AGGREGATE(15,6,ROW(Ledger!$B$3:$B$1002)/(Ledger!$B$3:$B$1002=$B$2),34))) | G39: =IF($A39="","",INDEX(Ledger!$I:$I,AGGREGATE(15,6,ROW(Ledger!$B$3:$B$1002)/(Ledger!$B$3:$B$1002=$B$2),34))) | H39: =IF($A39="","",INDEX(Ledger!$K:$K,AGGREGATE(15,6,ROW(Ledger!$B$3:$B$1002)/(Ledger!$B$3:$B$1002=$B$2),34)))
A40: =IFERROR(INDEX(Ledger!$A:$A,AGGREGATE(15,6,ROW(Ledger!$B$3:$B$1002)/(Ledger!$B$3:$B$1002=$B$2),35)),"") | B40: =IF($A40="","",INDEX(Ledger!$C:$C,AGGREGATE(15,6,ROW(Ledger!$B$3:$B$1002)/(Ledger!$B$3:$B$1002=$B$2),35))) | C40: =IF($A40="","",INDEX(Ledger!$D:$D,AGGREGATE(15,6,ROW(Ledger!$B$3:$B$1002)/(Ledger!$B$3:$B$1002=$B$2),35))) | D40: =IF($A40="","",INDEX(Ledger!$E:$E,AGGREGATE(15,6,ROW(Ledger!$B$3:$B$1002)/(Ledger!$B$3:$B$1002=$B$2),35))) | E40: =IF($A40="","",INDEX(Ledger!$F:$F,AGGREGATE(15,6,ROW(Ledger!$B$3:$B$1002)/(Ledger!$B$3:$B$1002=$B$2),35))) | F40: =IF($A40="","",INDEX(Ledger!$H:$H,AGGREGATE(15,6,ROW(Ledger!$B$3:$B$1002)/(Ledger!$B$3:$B$1002=$B$2),35))) | G40: =IF($A40="","",INDEX(Ledger!$I:$I,AGGREGATE(15,6,ROW(Ledger!$B$3:$B$1002)/(Ledger!$B$3:$B$1002=$B$2),35))) | H40: =IF($A40="","",INDEX(Ledger!$K:$K,AGGREGATE(15,6,ROW(Ledger!$B$3:$B$1002)/(Ledger!$B$3:$B$1002=$B$2),35)))
A41: =IFERROR(INDEX(Ledger!$A:$A,AGGREGATE(15,6,ROW(Ledger!$B$3:$B$1002)/(Ledger!$B$3:$B$1002=$B$2),36)),"") | B41: =IF($A41="","",INDEX(Ledger!$C:$C,AGGREGATE(15,6,ROW(Ledger!$B$3:$B$1002)/(Ledger!$B$3:$B$1002=$B$2),36))) | C41: =IF($A41="","",INDEX(Ledger!$D:$D,AGGREGATE(15,6,ROW(Ledger!$B$3:$B$1002)/(Ledger!$B$3:$B$1002=$B$2),36))) | D41: =IF($A41="","",INDEX(Ledger!$E:$E,AGGREGATE(15,6,ROW(Ledger!$B$3:$B$1002)/(Ledger!$B$3:$B$1002=$B$2),36))) | E41: =IF($A41="","",INDEX(Ledger!$F:$F,AGGREGATE(15,6,ROW(Ledger!$B$3:$B$1002)/(Ledger!$B$3:$B$1002=$B$2),36))) | F41: =IF($A41="","",INDEX(Ledger!$H:$H,AGGREGATE(15,6,ROW(Ledger!$B$3:$B$1002)/(Ledger!$B$3:$B$1002=$B$2),36))) | G41: =IF($A41="","",INDEX(Ledger!$I:$I,AGGREGATE(15,6,ROW(Ledger!$B$3:$B$1002)/(Ledger!$B$3:$B$1002=$B$2),36))) | H41: =IF($A41="","",INDEX(Ledger!$K:$K,AGGREGATE(15,6,ROW(Ledger!$B$3:$B$1002)/(Ledger!$B$3:$B$1002=$B$2),36)))
A42: =IFERROR(INDEX(Ledger!$A:$A,AGGREGATE(15,6,ROW(Ledger!$B$3:$B$1002)/(Ledger!$B$3:$B$1002=$B$2),37)),"") | B42: =IF($A42="","",INDEX(Ledger!$C:$C,AGGREGATE(15,6,ROW(Ledger!$B$3:$B$1002)/(Ledger!$B$3:$B$1002=$B$2),37))) | C42: =IF($A42="","",INDEX(Ledger!$D:$D,AGGREGATE(15,6,ROW(Ledger!$B$3:$B$1002)/(Ledger!$B$3:$B$1002=$B$2),37))) | D42: =IF($A42="","",INDEX(Ledger!$E:$E,AGGREGATE(15,6,ROW(Ledger!$B$3:$B$1002)/(Ledger!$B$3:$B$1002=$B$2),37))) | E42: =IF($A42="","",INDEX(Ledger!$F:$F,AGGREGATE(15,6,ROW(Ledger!$B$3:$B$1002)/(Ledger!$B$3:$B$1002=$B$2),37))) | F42: =IF($A42="","",INDEX(Ledger!$H:$H,AGGREGATE(15,6,ROW(Ledger!$B$3:$B$1002)/(Ledger!$B$3:$B$1002=$B$2),37))) | G42: =IF($A42="","",INDEX(Ledger!$I:$I,AGGREGATE(15,6,ROW(Ledger!$B$3:$B$1002)/(Ledger!$B$3:$B$1002=$B$2),37))) | H42: =IF($A42="","",INDEX(Ledger!$K:$K,AGGREGATE(15,6,ROW(Ledger!$B$3:$B$1002)/(Ledger!$B$3:$B$1002=$B$2),37)))
A43: =IFERROR(INDEX(Ledger!$A:$A,AGGREGATE(15,6,ROW(Ledger!$B$3:$B$1002)/(Ledger!$B$3:$B$1002=$B$2),38)),"") | B43: =IF($A43="","",INDEX(Ledger!$C:$C,AGGREGATE(15,6,ROW(Ledger!$B$3:$B$1002)/(Ledger!$B$3:$B$1002=$B$2),38))) | C43: =IF($A43="","",INDEX(Ledger!$D:$D,AGGREGATE(15,6,ROW(Ledger!$B$3:$B$1002)/(Ledger!$B$3:$B$1002=$B$2),38))) | D43: =IF($A43="","",INDEX(Ledger!$E:$E,AGGREGATE(15,6,ROW(Ledger!$B$3:$B$1002)/(Ledger!$B$3:$B$1002=$B$2),38))) | E43: =IF($A43="","",INDEX(Ledger!$F:$F,AGGREGATE(15,6,ROW(Ledger!$B$3:$B$1002)/(Ledger!$B$3:$B$1002=$B$2),38))) | F43: =IF($A43="","",INDEX(Ledger!$H:$H,AGGREGATE(15,6,ROW(Ledger!$B$3:$B$1002)/(Ledger!$B$3:$B$1002=$B$2),38))) | G43: =IF($A43="","",INDEX(Ledger!$I:$I,AGGREGATE(15,6,ROW(Ledger!$B$3:$B$1002)/(Ledger!$B$3:$B$1002=$B$2),38))) | H43: =IF($A43="","",INDEX(Ledger!$K:$K,AGGREGATE(15,6,ROW(Ledger!$B$3:$B$1002)/(Ledger!$B$3:$B$1002=$B$2),38)))
A44: =IFERROR(INDEX(Ledger!$A:$A,AGGREGATE(15,6,ROW(Ledger!$B$3:$B$1002)/(Ledger!$B$3:$B$1002=$B$2),39)),"") | B44: =IF($A44="","",INDEX(Ledger!$C:$C,AGGREGATE(15,6,ROW(Ledger!$B$3:$B$1002)/(Ledger!$B$3:$B$1002=$B$2),39))) | C44: =IF($A44="","",INDEX(Ledger!$D:$D,AGGREGATE(15,6,ROW(Ledger!$B$3:$B$1002)/(Ledger!$B$3:$B$1002=$B$2),39))) | D44: =IF($A44="","",INDEX(Ledger!$E:$E,AGGREGATE(15,6,ROW(Ledger!$B$3:$B$1002)/(Ledger!$B$3:$B$1002=$B$2),39))) | E44: =IF($A44="","",INDEX(Ledger!$F:$F,AGGREGATE(15,6,ROW(Ledger!$B$3:$B$1002)/(Ledger!$B$3:$B$1002=$B$2),39))) | F44: =IF($A44="","",INDEX(Ledger!$H:$H,AGGREGATE(15,6,ROW(Ledger!$B$3:$B$1002)/(Ledger!$B$3:$B$1002=$B$2),39))) | G44: =IF($A44="","",INDEX(Ledger!$I:$I,AGGREGATE(15,6,ROW(Ledger!$B$3:$B$1002)/(Ledger!$B$3:$B$1002=$B$2),39))) | H44: =IF($A44="","",INDEX(Ledger!$K:$K,AGGREGATE(15,6,ROW(Ledger!$B$3:$B$1002)/(Ledger!$B$3:$B$1002=$B$2),39)))
A45: =IFERROR(INDEX(Ledger!$A:$A,AGGREGATE(15,6,ROW(Ledger!$B$3:$B$1002)/(Ledger!$B$3:$B$1002=$B$2),40)),"") | B45: =IF($A45="","",INDEX(Ledger!$C:$C,AGGREGATE(15,6,ROW(Ledger!$B$3:$B$1002)/(Ledger!$B$3:$B$1002=$B$2),40))) | C45: =IF($A45="","",INDEX(Ledger!$D:$D,AGGREGATE(15,6,ROW(Ledger!$B$3:$B$1002)/(Ledger!$B$3:$B$1002=$B$2),40))) | D45: =IF($A45="","",INDEX(Ledger!$E:$E,AGGREGATE(15,6,ROW(Ledger!$B$3:$B$1002)/(Ledger!$B$3:$B$1002=$B$2),40))) | E45: =IF($A45="","",INDEX(Ledger!$F:$F,AGGREGATE(15,6,ROW(Ledger!$B$3:$B$1002)/(Ledger!$B$3:$B$1002=$B$2),40))) | F45: =IF($A45="","",INDEX(Ledger!$H:$H,AGGREGATE(15,6,ROW(Ledger!$B$3:$B$1002)/(Ledger!$B$3:$B$1002=$B$2),40))) | G45: =IF($A45="","",INDEX(Ledger!$I:$I,AGGREGATE(15,6,ROW(Ledger!$B$3:$B$1002)/(Ledger!$B$3:$B$1002=$B$2),40))) | H45: =IF($A45="","",INDEX(Ledger!$K:$K,AGGREGATE(15,6,ROW(Ledger!$B$3:$B$1002)/(Ledger!$B$3:$B$1002=$B$2),40)))
A46: =IFERROR(INDEX(Ledger!$A:$A,AGGREGATE(15,6,ROW(Ledger!$B$3:$B$1002)/(Ledger!$B$3:$B$1002=$B$2),41)),"") | B46: =IF($A46="","",INDEX(Ledger!$C:$C,AGGREGATE(15,6,ROW(Ledger!$B$3:$B$1002)/(Ledger!$B$3:$B$1002=$B$2),41))) | C46: =IF($A46="","",INDEX(Ledger!$D:$D,AGGREGATE(15,6,ROW(Ledger!$B$3:$B$1002)/(Ledger!$B$3:$B$1002=$B$2),41))) | D46: =IF($A46="","",INDEX(Ledger!$E:$E,AGGREGATE(15,6,ROW(Ledger!$B$3:$B$1002)/(Ledger!$B$3:$B$1002=$B$2),41))) | E46: =IF($A46="","",INDEX(Ledger!$F:$F,AGGREGATE(15,6,ROW(Ledger!$B$3:$B$1002)/(Ledger!$B$3:$B$1002=$B$2),41))) | F46: =IF($A46="","",INDEX(Ledger!$H:$H,AGGREGATE(15,6,ROW(Ledger!$B$3:$B$1002)/(Ledger!$B$3:$B$1002=$B$2),41))) | G46: =IF($A46="","",INDEX(Ledger!$I:$I,AGGREGATE(15,6,ROW(Ledger!$B$3:$B$1002)/(Ledger!$B$3:$B$1002=$B$2),41))) | H46: =IF($A46="","",INDEX(Ledger!$K:$K,AGGREGATE(15,6,ROW(Ledger!$B$3:$B$1002)/(Ledger!$B$3:$B$1002=$B$2),41)))
A47: =IFERROR(INDEX(Ledger!$A:$A,AGGREGATE(15,6,ROW(Ledger!$B$3:$B$1002)/(Ledger!$B$3:$B$1002=$B$2),42)),"") | B47: =IF($A47="","",INDEX(Ledger!$C:$C,AGGREGATE(15,6,ROW(Ledger!$B$3:$B$1002)/(Ledger!$B$3:$B$1002=$B$2),42))) | C47: =IF($A47="","",INDEX(Ledger!$D:$D,AGGREGATE(15,6,ROW(Ledger!$B$3:$B$1002)/(Ledger!$B$3:$B$1002=$B$2),42))) | D47: =IF($A47="","",INDEX(Ledger!$E:$E,AGGREGATE(15,6,ROW(Ledger!$B$3:$B$1002)/(Ledger!$B$3:$B$1002=$B$2),42))) | E47: =IF($A47="","",INDEX(Ledger!$F:$F,AGGREGATE(15,6,ROW(Ledger!$B$3:$B$1002)/(Ledger!$B$3:$B$1002=$B$2),42))) | F47: =IF($A47="","",INDEX(Ledger!$H:$H,AGGREGATE(15,6,ROW(Ledger!$B$3:$B$1002)/(Ledger!$B$3:$B$1002=$B$2),42))) | G47: =IF($A47="","",INDEX(Ledger!$I:$I,AGGREGATE(15,6,ROW(Ledger!$B$3:$B$1002)/(Ledger!$B$3:$B$1002=$B$2),42))) | H47: =IF($A47="","",INDEX(Ledger!$K:$K,AGGREGATE(15,6,ROW(Ledger!$B$3:$B$1002)/(Ledger!$B$3:$B$1002=$B$2),42)))
A48: =IFERROR(INDEX(Ledger!$A:$A,AGGREGATE(15,6,ROW(Ledger!$B$3:$B$1002)/(Ledger!$B$3:$B$1002=$B$2),43)),"") | B48: =IF($A48="","",INDEX(Ledger!$C:$C,AGGREGATE(15,6,ROW(Ledger!$B$3:$B$1002)/(Ledger!$B$3:$B$1002=$B$2),43))) | C48: =IF($A48="","",INDEX(Ledger!$D:$D,AGGREGATE(15,6,ROW(Ledger!$B$3:$B$1002)/(Ledger!$B$3:$B$1002=$B$2),43))) | D48: =IF($A48="","",INDEX(Ledger!$E:$E,AGGREGATE(15,6,ROW(Ledger!$B$3:$B$1002)/(Ledger!$B$3:$B$1002=$B$2),43))) | E48: =IF($A48="","",INDEX(Ledger!$F:$F,AGGREGATE(15,6,ROW(Ledger!$B$3:$B$1002)/(Ledger!$B$3:$B$1002=$B$2),43))) | F48: =IF($A48="","",INDEX(Ledger!$H:$H,AGGREGATE(15,6,ROW(Ledger!$B$3:$B$1002)/(Ledger!$B$3:$B$1002=$B$2),43))) | G48: =IF($A48="","",INDEX(Ledger!$I:$I,AGGREGATE(15,6,ROW(Ledger!$B$3:$B$1002)/(Ledger!$B$3:$B$1002=$B$2),43))) | H48: =IF($A48="","",INDEX(Ledger!$K:$K,AGGREGATE(15,6,ROW(Ledger!$B$3:$B$1002)/(Ledger!$B$3:$B$1002=$B$2),43)))
A49: =IFERROR(INDEX(Ledger!$A:$A,AGGREGATE(15,6,ROW(Ledger!$B$3:$B$1002)/(Ledger!$B$3:$B$1002=$B$2),44)),"") | B49: =IF($A49="","",INDEX(Ledger!$C:$C,AGGREGATE(15,6,ROW(Ledger!$B$3:$B$1002)/(Ledger!$B$3:$B$1002=$B$2),44))) | C49: =IF($A49="","",INDEX(Ledger!$D:$D,AGGREGATE(15,6,ROW(Ledger!$B$3:$B$1002)/(Ledger!$B$3:$B$1002=$B$2),44))) | D49: =IF($A49="","",INDEX(Ledger!$E:$E,AGGREGATE(15,6,ROW(Ledger!$B$3:$B$1002)/(Ledger!$B$3:$B$1002=$B$2),44))) | E49: =IF($A49="","",INDEX(Ledger!$F:$F,AGGREGATE(15,6,ROW(Ledger!$B$3:$B$1002)/(Ledger!$B$3:$B$1002=$B$2),44))) | F49: =IF($A49="","",INDEX(Ledger!$H:$H,AGGREGATE(15,6,ROW(Ledger!$B$3:$B$1002)/(Ledger!$B$3:$B$1002=$B$2),44))) | G49: =IF($A49="","",INDEX(Ledger!$I:$I,AGGREGATE(15,6,ROW(Ledger!$B$3:$B$1002)/(Ledger!$B$3:$B$1002=$B$2),44))) | H49: =IF($A49="","",INDEX(Ledger!$K:$K,AGGREGATE(15,6,ROW(Ledger!$B$3:$B$1002)/(Ledger!$B$3:$B$1002=$B$2),44)))
A50: =IFERROR(INDEX(Ledger!$A:$A,AGGREGATE(15,6,ROW(Ledger!$B$3:$B$1002)/(Ledger!$B$3:$B$1002=$B$2),45)),"") | B50: =IF($A50="","",INDEX(Ledger!$C:$C,AGGREGATE(15,6,ROW(Ledger!$B$3:$B$1002)/(Ledger!$B$3:$B$1002=$B$2),45))) | C50: =IF($A50="","",INDEX(Ledger!$D:$D,AGGREGATE(15,6,ROW(Ledger!$B$3:$B$1002)/(Ledger!$B$3:$B$1002=$B$2),45))) | D50: =IF($A50="","",INDEX(Ledger!$E:$E,AGGREGATE(15,6,ROW(Ledger!$B$3:$B$1002)/(Ledger!$B$3:$B$1002=$B$2),45))) | E50: =IF($A50="","",INDEX(Ledger!$F:$F,AGGREGATE(15,6,ROW(Ledger!$B$3:$B$1002)/(Ledger!$B$3:$B$1002=$B$2),45))) | F50: =IF($A50="","",INDEX(Ledger!$H:$H,AGGREGATE(15,6,ROW(Ledger!$B$3:$B$1002)/(Ledger!$B$3:$B$1002=$B$2),45))) | G50: =IF($A50="","",INDEX(Ledger!$I:$I,AGGREGATE(15,6,ROW(Ledger!$B$3:$B$1002)/(Ledger!$B$3:$B$1002=$B$2),45))) | H50: =IF($A50="","",INDEX(Ledger!$K:$K,AGGREGATE(15,6,ROW(Ledger!$B$3:$B$1002)/(Ledger!$B$3:$B$1002=$B$2),45)))
A51: =IFERROR(INDEX(Ledger!$A:$A,AGGREGATE(15,6,ROW(Ledger!$B$3:$B$1002)/(Ledger!$B$3:$B$1002=$B$2),46)),"") | B51: =IF($A51="","",INDEX(Ledger!$C:$C,AGGREGATE(15,6,ROW(Ledger!$B$3:$B$1002)/(Ledger!$B$3:$B$1002=$B$2),46))) | C51: =IF($A51="","",INDEX(Ledger!$D:$D,AGGREGATE(15,6,ROW(Ledger!$B$3:$B$1002)/(Ledger!$B$3:$B$1002=$B$2),46))) | D51: =IF($A51="","",INDEX(Ledger!$E:$E,AGGREGATE(15,6,ROW(Ledger!$B$3:$B$1002)/(Ledger!$B$3:$B$1002=$B$2),46))) | E51: =IF($A51="","",INDEX(Ledger!$F:$F,AGGREGATE(15,6,ROW(Ledger!$B$3:$B$1002)/(Ledger!$B$3:$B$1002=$B$2),46))) | F51: =IF($A51="","",INDEX(Ledger!$H:$H,AGGREGATE(15,6,ROW(Ledger!$B$3:$B$1002)/(Ledger!$B$3:$B$1002=$B$2),46))) | G51: =IF($A51="","",INDEX(Ledger!$I:$I,AGGREGATE(15,6,ROW(Ledger!$B$3:$B$1002)/(Ledger!$B$3:$B$1002=$B$2),46))) | H51: =IF($A51="","",INDEX(Ledger!$K:$K,AGGREGATE(15,6,ROW(Ledger!$B$3:$B$1002)/(Ledger!$B$3:$B$1002=$B$2),46)))
A52: =IFERROR(INDEX(Ledger!$A:$A,AGGREGATE(15,6,ROW(Ledger!$B$3:$B$1002)/(Ledger!$B$3:$B$1002=$B$2),47)),"") | B52: =IF($A52="","",INDEX(Ledger!$C:$C,AGGREGATE(15,6,ROW(Ledger!$B$3:$B$1002)/(Ledger!$B$3:$B$1002=$B$2),47))) | C52: =IF($A52="","",INDEX(Ledger!$D:$D,AGGREGATE(15,6,ROW(Ledger!$B$3:$B$1002)/(Ledger!$B$3:$B$1002=$B$2),47))) | D52: =IF($A52="","",INDEX(Ledger!$E:$E,AGGREGATE(15,6,ROW(Ledger!$B$3:$B$1002)/(Ledger!$B$3:$B$1002=$B$2),47))) | E52: =IF($A52="","",INDEX(Ledger!$F:$F,AGGREGATE(15,6,ROW(Ledger!$B$3:$B$1002)/(Ledger!$B$3:$B$1002=$B$2),47))) | F52: =IF($A52="","",INDEX(Ledger!$H:$H,AGGREGATE(15,6,ROW(Ledger!$B$3:$B$1002)/(Ledger!$B$3:$B$1002=$B$2),47))) | G52: =IF($A52="","",INDEX(Ledger!$I:$I,AGGREGATE(15,6,ROW(Ledger!$B$3:$B$1002)/(Ledger!$B$3:$B$1002=$B$2),47))) | H52: =IF($A52="","",INDEX(Ledger!$K:$K,AGGREGATE(15,6,ROW(Ledger!$B$3:$B$1002)/(Ledger!$B$3:$B$1002=$B$2),47)))
A53: =IFERROR(INDEX(Ledger!$A:$A,AGGREGATE(15,6,ROW(Ledger!$B$3:$B$1002)/(Ledger!$B$3:$B$1002=$B$2),48)),"") | B53: =IF($A53="","",INDEX(Ledger!$C:$C,AGGREGATE(15,6,ROW(Ledger!$B$3:$B$1002)/(Ledger!$B$3:$B$1002=$B$2),48))) | C53: =IF($A53="","",INDEX(Ledger!$D:$D,AGGREGATE(15,6,ROW(Ledger!$B$3:$B$1002)/(Ledger!$B$3:$B$1002=$B$2),48))) | D53: =IF($A53="","",INDEX(Ledger!$E:$E,AGGREGATE(15,6,ROW(Ledger!$B$3:$B$1002)/(Ledger!$B$3:$B$1002=$B$2),48))) | E53: =IF($A53="","",INDEX(Ledger!$F:$F,AGGREGATE(15,6,ROW(Ledger!$B$3:$B$1002)/(Ledger!$B$3:$B$1002=$B$2),48))) | F53: =IF($A53="","",INDEX(Ledger!$H:$H,AGGREGATE(15,6,ROW(Ledger!$B$3:$B$1002)/(Ledger!$B$3:$B$1002=$B$2),48))) | G53: =IF($A53="","",INDEX(Ledger!$I:$I,AGGREGATE(15,6,ROW(Ledger!$B$3:$B$1002)/(Ledger!$B$3:$B$1002=$B$2),48))) | H53: =IF($A53="","",INDEX(Ledger!$K:$K,AGGREGATE(15,6,ROW(Ledger!$B$3:$B$1002)/(Ledger!$B$3:$B$1002=$B$2),48)))
A54: =IFERROR(INDEX(Ledger!$A:$A,AGGREGATE(15,6,ROW(Ledger!$B$3:$B$1002)/(Ledger!$B$3:$B$1002=$B$2),49)),"") | B54: =IF($A54="","",INDEX(Ledger!$C:$C,AGGREGATE(15,6,ROW(Ledger!$B$3:$B$1002)/(Ledger!$B$3:$B$1002=$B$2),49))) | C54: =IF($A54="","",INDEX(Ledger!$D:$D,AGGREGATE(15,6,ROW(Ledger!$B$3:$B$1002)/(Ledger!$B$3:$B$1002=$B$2),49))) | D54: =IF($A54="","",INDEX(Ledger!$E:$E,AGGREGATE(15,6,ROW(Ledger!$B$3:$B$1002)/(Ledger!$B$3:$B$1002=$B$2),49))) | E54: =IF($A54="","",INDEX(Ledger!$F:$F,AGGREGATE(15,6,ROW(Ledger!$B$3:$B$1002)/(Ledger!$B$3:$B$1002=$B$2),49))) | F54: =IF($A54="","",INDEX(Ledger!$H:$H,AGGREGATE(15,6,ROW(Ledger!$B$3:$B$1002)/(Ledger!$B$3:$B$1002=$B$2),49))) | G54: =IF($A54="","",INDEX(Ledger!$I:$I,AGGREGATE(15,6,ROW(Ledger!$B$3:$B$1002)/(Ledger!$B$3:$B$1002=$B$2),49))) | H54: =IF($A54="","",INDEX(Ledger!$K:$K,AGGREGATE(15,6,ROW(Ledger!$B$3:$B$1002)/(Ledger!$B$3:$B$1002=$B$2),49)))
A55: =IFERROR(INDEX(Ledger!$A:$A,AGGREGATE(15,6,ROW(Ledger!$B$3:$B$1002)/(Ledger!$B$3:$B$1002=$B$2),50)),"") | B55: =IF($A55="","",INDEX(Ledger!$C:$C,AGGREGATE(15,6,ROW(Ledger!$B$3:$B$1002)/(Ledger!$B$3:$B$1002=$B$2),50))) | C55: =IF($A55="","",INDEX(Ledger!$D:$D,AGGREGATE(15,6,ROW(Ledger!$B$3:$B$1002)/(Ledger!$B$3:$B$1002=$B$2),50))) | D55: =IF($A55="","",INDEX(Ledger!$E:$E,AGGREGATE(15,6,ROW(Ledger!$B$3:$B$1002)/(Ledger!$B$3:$B$1002=$B$2),50))) | E55: =IF($A55="","",INDEX(Ledger!$F:$F,AGGREGATE(15,6,ROW(Ledger!$B$3:$B$1002)/(Ledger!$B$3:$B$1002=$B$2),50))) | F55: =IF($A55="","",INDEX(Ledger!$H:$H,AGGREGATE(15,6,ROW(Ledger!$B$3:$B$1002)/(Ledger!$B$3:$B$1002=$B$2),50))) | G55: =IF($A55="","",INDEX(Ledger!$I:$I,AGGREGATE(15,6,ROW(Ledger!$B$3:$B$1002)/(Ledger!$B$3:$B$1002=$B$2),50))) | H55: =IF($A55="","",INDEX(Ledger!$K:$K,AGGREGATE(15,6,ROW(Ledger!$B$3:$B$1002)/(Ledger!$B$3:$B$1002=$B$2),50)))
A56: =IFERROR(INDEX(Ledger!$A:$A,AGGREGATE(15,6,ROW(Ledger!$B$3:$B$1002)/(Ledger!$B$3:$B$1002=$B$2),51)),"") | B56: =IF($A56="","",INDEX(Ledger!$C:$C,AGGREGATE(15,6,ROW(Ledger!$B$3:$B$1002)/(Ledger!$B$3:$B$1002=$B$2),51))) | C56: =IF($A56="","",INDEX(Ledger!$D:$D,AGGREGATE(15,6,ROW(Ledger!$B$3:$B$1002)/(Ledger!$B$3:$B$1002=$B$2),51))) | D56: =IF($A56="","",INDEX(Ledger!$E:$E,AGGREGATE(15,6,ROW(Ledger!$B$3:$B$1002)/(Ledger!$B$3:$B$1002=$B$2),51))) | E56: =IF($A56="","",INDEX(Ledger!$F:$F,AGGREGATE(15,6,ROW(Ledger!$B$3:$B$1002)/(Ledger!$B$3:$B$1002=$B$2),51))) | F56: =IF($A56="","",INDEX(Ledger!$H:$H,AGGREGATE(15,6,ROW(Ledger!$B$3:$B$1002)/(Ledger!$B$3:$B$1002=$B$2),51))) | G56: =IF($A56="","",INDEX(Ledger!$I:$I,AGGREGATE(15,6,ROW(Ledger!$B$3:$B$1002)/(Ledger!$B$3:$B$1002=$B$2),51))) | H56: =IF($A56="","",INDEX(Ledger!$K:$K,AGGREGATE(15,6,ROW(Ledger!$B$3:$B$1002)/(Ledger!$B$3:$B$1002=$B$2),51)))
A57: =IFERROR(INDEX(Ledger!$A:$A,AGGREGATE(15,6,ROW(Ledger!$B$3:$B$1002)/(Ledger!$B$3:$B$1002=$B$2),52)),"") | B57: =IF($A57="","",INDEX(Ledger!$C:$C,AGGREGATE(15,6,ROW(Ledger!$B$3:$B$1002)/(Ledger!$B$3:$B$1002=$B$2),52))) | C57: =IF($A57="","",INDEX(Ledger!$D:$D,AGGREGATE(15,6,ROW(Ledger!$B$3:$B$1002)/(Ledger!$B$3:$B$1002=$B$2),52))) | D57: =IF($A57="","",INDEX(Ledger!$E:$E,AGGREGATE(15,6,ROW(Ledger!$B$3:$B$1002)/(Ledger!$B$3:$B$1002=$B$2),52))) | E57: =IF($A57="","",INDEX(Ledger!$F:$F,AGGREGATE(15,6,ROW(Ledger!$B$3:$B$1002)/(Ledger!$B$3:$B$1002=$B$2),52))) | F57: =IF($A57="","",INDEX(Ledger!$H:$H,AGGREGATE(15,6,ROW(Ledger!$B$3:$B$1002)/(Ledger!$B$3:$B$1002=$B$2),52))) | G57: =IF($A57="","",INDEX(Ledger!$I:$I,AGGREGATE(15,6,ROW(Ledger!$B$3:$B$1002)/(Ledger!$B$3:$B$1002=$B$2),52))) | H57: =IF($A57="","",INDEX(Ledger!$K:$K,AGGREGATE(15,6,ROW(Ledger!$B$3:$B$1002)/(Ledger!$B$3:$B$1002=$B$2),52)))
A58: =IFERROR(INDEX(Ledger!$A:$A,AGGREGATE(15,6,ROW(Ledger!$B$3:$B$1002)/(Ledger!$B$3:$B$1002=$B$2),53)),"") | B58: =IF($A58="","",INDEX(Ledger!$C:$C,AGGREGATE(15,6,ROW(Ledger!$B$3:$B$1002)/(Ledger!$B$3:$B$1002=$B$2),53))) | C58: =IF($A58="","",INDEX(Ledger!$D:$D,AGGREGATE(15,6,ROW(Ledger!$B$3:$B$1002)/(Ledger!$B$3:$B$1002=$B$2),53))) | D58: =IF($A58="","",INDEX(Ledger!$E:$E,AGGREGATE(15,6,ROW(Ledger!$B$3:$B$1002)/(Ledger!$B$3:$B$1002=$B$2),53))) | E58: =IF($A58="","",INDEX(Ledger!$F:$F,AGGREGATE(15,6,ROW(Ledger!$B$3:$B$1002)/(Ledger!$B$3:$B$1002=$B$2),53))) | F58: =IF($A58="","",INDEX(Ledger!$H:$H,AGGREGATE(15,6,ROW(Ledger!$B$3:$B$1002)/(Ledger!$B$3:$B$1002=$B$2),53))) | G58: =IF($A58="","",INDEX(Ledger!$I:$I,AGGREGATE(15,6,ROW(Ledger!$B$3:$B$1002)/(Ledger!$B$3:$B$1002=$B$2),53))) | H58: =IF($A58="","",INDEX(Ledger!$K:$K,AGGREGATE(15,6,ROW(Ledger!$B$3:$B$1002)/(Ledger!$B$3:$B$1002=$B$2),53)))
A59: =IFERROR(INDEX(Ledger!$A:$A,AGGREGATE(15,6,ROW(Ledger!$B$3:$B$1002)/(Ledger!$B$3:$B$1002=$B$2),54)),"") | B59: =IF($A59="","",INDEX(Ledger!$C:$C,AGGREGATE(15,6,ROW(Ledger!$B$3:$B$1002)/(Ledger!$B$3:$B$1002=$B$2),54))) | C59: =IF($A59="","",INDEX(Ledger!$D:$D,AGGREGATE(15,6,ROW(Ledger!$B$3:$B$1002)/(Ledger!$B$3:$B$1002=$B$2),54))) | D59: =IF($A59="","",INDEX(Ledger!$E:$E,AGGREGATE(15,6,ROW(Ledger!$B$3:$B$1002)/(Ledger!$B$3:$B$1002=$B$2),54))) | E59: =IF($A59="","",INDEX(Ledger!$F:$F,AGGREGATE(15,6,ROW(Ledger!$B$3:$B$1002)/(Ledger!$B$3:$B$1002=$B$2),54))) | F59: =IF($A59="","",INDEX(Ledger!$H:$H,AGGREGATE(15,6,ROW(Ledger!$B$3:$B$1002)/(Ledger!$B$3:$B$1002=$B$2),54))) | G59: =IF($A59="","",INDEX(Ledger!$I:$I,AGGREGATE(15,6,ROW(Ledger!$B$3:$B$1002)/(Ledger!$B$3:$B$1002=$B$2),54))) | H59: =IF($A59="","",INDEX(Ledger!$K:$K,AGGREGATE(15,6,ROW(Ledger!$B$3:$B$1002)/(Ledger!$B$3:$B$1002=$B$2),54)))
A60: =IFERROR(INDEX(Ledger!$A:$A,AGGREGATE(15,6,ROW(Ledger!$B$3:$B$1002)/(Ledger!$B$3:$B$1002=$B$2),55)),"") | B60: =IF($A60="","",INDEX(Ledger!$C:$C,AGGREGATE(15,6,ROW(Ledger!$B$3:$B$1002)/(Ledger!$B$3:$B$1002=$B$2),55))) | C60: =IF($A60="","",INDEX(Ledger!$D:$D,AGGREGATE(15,6,ROW(Ledger!$B$3:$B$1002)/(Ledger!$B$3:$B$1002=$B$2),55))) | D60: =IF($A60="","",INDEX(Ledger!$E:$E,AGGREGATE(15,6,ROW(Ledger!$B$3:$B$1002)/(Ledger!$B$3:$B$1002=$B$2),55))) | E60: =IF($A60="","",INDEX(Ledger!$F:$F,AGGREGATE(15,6,ROW(Ledger!$B$3:$B$1002)/(Ledger!$B$3:$B$1002=$B$2),55))) | F60: =IF($A60="","",INDEX(Ledger!$H:$H,AGGREGATE(15,6,ROW(Ledger!$B$3:$B$1002)/(Ledger!$B$3:$B$1002=$B$2),55))) | G60: =IF($A60="","",INDEX(Ledger!$I:$I,AGGREGATE(15,6,ROW(Ledger!$B$3:$B$1002)/(Ledger!$B$3:$B$1002=$B$2),55))) | H60: =IF($A60="","",INDEX(Ledger!$K:$K,AGGREGATE(15,6,ROW(Ledger!$B$3:$B$1002)/(Ledger!$B$3:$B$1002=$B$2),55)))
A61: =IFERROR(INDEX(Ledger!$A:$A,AGGREGATE(15,6,ROW(Ledger!$B$3:$B$1002)/(Ledger!$B$3:$B$1002=$B$2),56)),"") | B61: =IF($A61="","",INDEX(Ledger!$C:$C,AGGREGATE(15,6,ROW(Ledger!$B$3:$B$1002)/(Ledger!$B$3:$B$1002=$B$2),56))) | C61: =IF($A61="","",INDEX(Ledger!$D:$D,AGGREGATE(15,6,ROW(Ledger!$B$3:$B$1002)/(Ledger!$B$3:$B$1002=$B$2),56))) | D61: =IF($A61="","",INDEX(Ledger!$E:$E,AGGREGATE(15,6,ROW(Ledger!$B$3:$B$1002)/(Ledger!$B$3:$B$1002=$B$2),56))) | E61: =IF($A61="","",INDEX(Ledger!$F:$F,AGGREGATE(15,6,ROW(Ledger!$B$3:$B$1002)/(Ledger!$B$3:$B$1002=$B$2),56))) | F61: =IF($A61="","",INDEX(Ledger!$H:$H,AGGREGATE(15,6,ROW(Ledger!$B$3:$B$1002)/(Ledger!$B$3:$B$1002=$B$2),56))) | G61: =IF($A61="","",INDEX(Ledger!$I:$I,AGGREGATE(15,6,ROW(Ledger!$B$3:$B$1002)/(Ledger!$B$3:$B$1002=$B$2),56))) | H61: =IF($A61="","",INDEX(Ledger!$K:$K,AGGREGATE(15,6,ROW(Ledger!$B$3:$B$1002)/(Ledger!$B$3:$B$1002=$B$2),56)))
A62: =IFERROR(INDEX(Ledger!$A:$A,AGGREGATE(15,6,ROW(Ledger!$B$3:$B$1002)/(Ledger!$B$3:$B$1002=$B$2),57)),"") | B62: =IF($A62="","",INDEX(Ledger!$C:$C,AGGREGATE(15,6,ROW(Ledger!$B$3:$B$1002)/(Ledger!$B$3:$B$1002=$B$2),57))) | C62: =IF($A62="","",INDEX(Ledger!$D:$D,AGGREGATE(15,6,ROW(Ledger!$B$3:$B$1002)/(Ledger!$B$3:$B$1002=$B$2),57))) | D62: =IF($A62="","",INDEX(Ledger!$E:$E,AGGREGATE(15,6,ROW(Ledger!$B$3:$B$1002)/(Ledger!$B$3:$B$1002=$B$2),57))) | E62: =IF($A62="","",INDEX(Ledger!$F:$F,AGGREGATE(15,6,ROW(Ledger!$B$3:$B$1002)/(Ledger!$B$3:$B$1002=$B$2),57))) | F62: =IF($A62="","",INDEX(Ledger!$H:$H,AGGREGATE(15,6,ROW(Ledger!$B$3:$B$1002)/(Ledger!$B$3:$B$1002=$B$2),57))) | G62: =IF($A62="","",INDEX(Ledger!$I:$I,AGGREGATE(15,6,ROW(Ledger!$B$3:$B$1002)/(Ledger!$B$3:$B$1002=$B$2),57))) | H62: =IF($A62="","",INDEX(Ledger!$K:$K,AGGREGATE(15,6,ROW(Ledger!$B$3:$B$1002)/(Ledger!$B$3:$B$1002=$B$2),57)))
A63: =IFERROR(INDEX(Ledger!$A:$A,AGGREGATE(15,6,ROW(Ledger!$B$3:$B$1002)/(Ledger!$B$3:$B$1002=$B$2),58)),"") | B63: =IF($A63="","",INDEX(Ledger!$C:$C,AGGREGATE(15,6,ROW(Ledger!$B$3:$B$1002)/(Ledger!$B$3:$B$1002=$B$2),58))) | C63: =IF($A63="","",INDEX(Ledger!$D:$D,AGGREGATE(15,6,ROW(Ledger!$B$3:$B$1002)/(Ledger!$B$3:$B$1002=$B$2),58))) | D63: =IF($A63="","",INDEX(Ledger!$E:$E,AGGREGATE(15,6,ROW(Ledger!$B$3:$B$1002)/(Ledger!$B$3:$B$1002=$B$2),58))) | E63: =IF($A63="","",INDEX(Ledger!$F:$F,AGGREGATE(15,6,ROW(Ledger!$B$3:$B$1002)/(Ledger!$B$3:$B$1002=$B$2),58))) | F63: =IF($A63="","",INDEX(Ledger!$H:$H,AGGREGATE(15,6,ROW(Ledger!$B$3:$B$1002)/(Ledger!$B$3:$B$1002=$B$2),58))) | G63: =IF($A63="","",INDEX(Ledger!$I:$I,AGGREGATE(15,6,ROW(Ledger!$B$3:$B$1002)/(Ledger!$B$3:$B$1002=$B$2),58))) | H63: =IF($A63="","",INDEX(Ledger!$K:$K,AGGREGATE(15,6,ROW(Ledger!$B$3:$B$1002)/(Ledger!$B$3:$B$1002=$B$2),58)))
A64: =IFERROR(INDEX(Ledger!$A:$A,AGGREGATE(15,6,ROW(Ledger!$B$3:$B$1002)/(Ledger!$B$3:$B$1002=$B$2),59)),"") | B64: =IF($A64="","",INDEX(Ledger!$C:$C,AGGREGATE(15,6,ROW(Ledger!$B$3:$B$1002)/(Ledger!$B$3:$B$1002=$B$2),59))) | C64: =IF($A64="","",INDEX(Ledger!$D:$D,AGGREGATE(15,6,ROW(Ledger!$B$3:$B$1002)/(Ledger!$B$3:$B$1002=$B$2),59))) | D64: =IF($A64="","",INDEX(Ledger!$E:$E,AGGREGATE(15,6,ROW(Ledger!$B$3:$B$1002)/(Ledger!$B$3:$B$1002=$B$2),59))) | E64: =IF($A64="","",INDEX(Ledger!$F:$F,AGGREGATE(15,6,ROW(Ledger!$B$3:$B$1002)/(Ledger!$B$3:$B$1002=$B$2),59))) | F64: =IF($A64="","",INDEX(Ledger!$H:$H,AGGREGATE(15,6,ROW(Ledger!$B$3:$B$1002)/(Ledger!$B$3:$B$1002=$B$2),59))) | G64: =IF($A64="","",INDEX(Ledger!$I:$I,AGGREGATE(15,6,ROW(Ledger!$B$3:$B$1002)/(Ledger!$B$3:$B$1002=$B$2),59))) | H64: =IF($A64="","",INDEX(Ledger!$K:$K,AGGREGATE(15,6,ROW(Ledger!$B$3:$B$1002)/(Ledger!$B$3:$B$1002=$B$2),59)))
A65: =IFERROR(INDEX(Ledger!$A:$A,AGGREGATE(15,6,ROW(Ledger!$B$3:$B$1002)/(Ledger!$B$3:$B$1002=$B$2),60)),"") | B65: =IF($A65="","",INDEX(Ledger!$C:$C,AGGREGATE(15,6,ROW(Ledger!$B$3:$B$1002)/(Ledger!$B$3:$B$1002=$B$2),60))) | C65: =IF($A65="","",INDEX(Ledger!$D:$D,AGGREGATE(15,6,ROW(Ledger!$B$3:$B$1002)/(Ledger!$B$3:$B$1002=$B$2),60))) | D65: =IF($A65="","",INDEX(Ledger!$E:$E,AGGREGATE(15,6,ROW(Ledger!$B$3:$B$1002)/(Ledger!$B$3:$B$1002=$B$2),60))) | E65: =IF($A65="","",INDEX(Ledger!$F:$F,AGGREGATE(15,6,ROW(Ledger!$B$3:$B$1002)/(Ledger!$B$3:$B$1002=$B$2),60))) | F65: =IF($A65="","",INDEX(Ledger!$H:$H,AGGREGATE(15,6,ROW(Ledger!$B$3:$B$1002)/(Ledger!$B$3:$B$1002=$B$2),60))) | G65: =IF($A65="","",INDEX(Ledger!$I:$I,AGGREGATE(15,6,ROW(Ledger!$B$3:$B$1002)/(Ledger!$B$3:$B$1002=$B$2),60))) | H65: =IF($A65="","",INDEX(Ledger!$K:$K,AGGREGATE(15,6,ROW(Ledger!$B$3:$B$1002)/(Ledger!$B$3:$B$1002=$B$2),60)))
A66: =IFERROR(INDEX(Ledger!$A:$A,AGGREGATE(15,6,ROW(Ledger!$B$3:$B$1002)/(Ledger!$B$3:$B$1002=$B$2),61)),"") | B66: =IF($A66="","",INDEX(Ledger!$C:$C,AGGREGATE(15,6,ROW(Ledger!$B$3:$B$1002)/(Ledger!$B$3:$B$1002=$B$2),61))) | C66: =IF($A66="","",INDEX(Ledger!$D:$D,AGGREGATE(15,6,ROW(Ledger!$B$3:$B$1002)/(Ledger!$B$3:$B$1002=$B$2),61))) | D66: =IF($A66="","",INDEX(Ledger!$E:$E,AGGREGATE(15,6,ROW(Ledger!$B$3:$B$1002)/(Ledger!$B$3:$B$1002=$B$2),61))) | E66: =IF($A66="","",INDEX(Ledger!$F:$F,AGGREGATE(15,6,ROW(Ledger!$B$3:$B$1002)/(Ledger!$B$3:$B$1002=$B$2),61))) | F66: =IF($A66="","",INDEX(Ledger!$H:$H,AGGREGATE(15,6,ROW(Ledger!$B$3:$B$1002)/(Ledger!$B$3:$B$1002=$B$2),61))) | G66: =IF($A66="","",INDEX(Ledger!$I:$I,AGGREGATE(15,6,ROW(Ledger!$B$3:$B$1002)/(Ledger!$B$3:$B$1002=$B$2),61))) | H66: =IF($A66="","",INDEX(Ledger!$K:$K,AGGREGATE(15,6,ROW(Ledger!$B$3:$B$1002)/(Ledger!$B$3:$B$1002=$B$2),61)))
A67: =IFERROR(INDEX(Ledger!$A:$A,AGGREGATE(15,6,ROW(Ledger!$B$3:$B$1002)/(Ledger!$B$3:$B$1002=$B$2),62)),"") | B67: =IF($A67="","",INDEX(Ledger!$C:$C,AGGREGATE(15,6,ROW(Ledger!$B$3:$B$1002)/(Ledger!$B$3:$B$1002=$B$2),62))) | C67: =IF($A67="","",INDEX(Ledger!$D:$D,AGGREGATE(15,6,ROW(Ledger!$B$3:$B$1002)/(Ledger!$B$3:$B$1002=$B$2),62))) | D67: =IF($A67="","",INDEX(Ledger!$E:$E,AGGREGATE(15,6,ROW(Ledger!$B$3:$B$1002)/(Ledger!$B$3:$B$1002=$B$2),62))) | E67: =IF($A67="","",INDEX(Ledger!$F:$F,AGGREGATE(15,6,ROW(Ledger!$B$3:$B$1002)/(Ledger!$B$3:$B$1002=$B$2),62))) | F67: =IF($A67="","",INDEX(Ledger!$H:$H,AGGREGATE(15,6,ROW(Ledger!$B$3:$B$1002)/(Ledger!$B$3:$B$1002=$B$2),62))) | G67: =IF($A67="","",INDEX(Ledger!$I:$I,AGGREGATE(15,6,ROW(Ledger!$B$3:$B$1002)/(Ledger!$B$3:$B$1002=$B$2),62))) | H67: =IF($A67="","",INDEX(Ledger!$K:$K,AGGREGATE(15,6,ROW(Ledger!$B$3:$B$1002)/(Ledger!$B$3:$B$1002=$B$2),62)))
A68: =IFERROR(INDEX(Ledger!$A:$A,AGGREGATE(15,6,ROW(Ledger!$B$3:$B$1002)/(Ledger!$B$3:$B$1002=$B$2),63)),"") | B68: =IF($A68="","",INDEX(Ledger!$C:$C,AGGREGATE(15,6,ROW(Ledger!$B$3:$B$1002)/(Ledger!$B$3:$B$1002=$B$2),63))) | C68: =IF($A68="","",INDEX(Ledger!$D:$D,AGGREGATE(15,6,ROW(Ledger!$B$3:$B$1002)/(Ledger!$B$3:$B$1002=$B$2),63))) | D68: =IF($A68="","",INDEX(Ledger!$E:$E,AGGREGATE(15,6,ROW(Ledger!$B$3:$B$1002)/(Ledger!$B$3:$B$1002=$B$2),63))) | E68: =IF($A68="","",INDEX(Ledger!$F:$F,AGGREGATE(15,6,ROW(Ledger!$B$3:$B$1002)/(Ledger!$B$3:$B$1002=$B$2),63))) | F68: =IF($A68="","",INDEX(Ledger!$H:$H,AGGREGATE(15,6,ROW(Ledger!$B$3:$B$1002)/(Ledger!$B$3:$B$1002=$B$2),63))) | G68: =IF($A68="","",INDEX(Ledger!$I:$I,AGGREGATE(15,6,ROW(Ledger!$B$3:$B$1002)/(Ledger!$B$3:$B$1002=$B$2),63))) | H68: =IF($A68="","",INDEX(Ledger!$K:$K,AGGREGATE(15,6,ROW(Ledger!$B$3:$B$1002)/(Ledger!$B$3:$B$1002=$B$2),63)))
A69: =IFERROR(INDEX(Ledger!$A:$A,AGGREGATE(15,6,ROW(Ledger!$B$3:$B$1002)/(Ledger!$B$3:$B$1002=$B$2),64)),"") | B69: =IF($A69="","",INDEX(Ledger!$C:$C,AGGREGATE(15,6,ROW(Ledger!$B$3:$B$1002)/(Ledger!$B$3:$B$1002=$B$2),64))) | C69: =IF($A69="","",INDEX(Ledger!$D:$D,AGGREGATE(15,6,ROW(Ledger!$B$3:$B$1002)/(Ledger!$B$3:$B$1002=$B$2),64))) | D69: =IF($A69="","",INDEX(Ledger!$E:$E,AGGREGATE(15,6,ROW(Ledger!$B$3:$B$1002)/(Ledger!$B$3:$B$1002=$B$2),64))) | E69: =IF($A69="","",INDEX(Ledger!$F:$F,AGGREGATE(15,6,ROW(Ledger!$B$3:$B$1002)/(Ledger!$B$3:$B$1002=$B$2),64))) | F69: =IF($A69="","",INDEX(Ledger!$H:$H,AGGREGATE(15,6,ROW(Ledger!$B$3:$B$1002)/(Ledger!$B$3:$B$1002=$B$2),64))) | G69: =IF($A69="","",INDEX(Ledger!$I:$I,AGGREGATE(15,6,ROW(Ledger!$B$3:$B$1002)/(Ledger!$B$3:$B$1002=$B$2),64))) | H69: =IF($A69="","",INDEX(Ledger!$K:$K,AGGREGATE(15,6,ROW(Ledger!$B$3:$B$1002)/(Ledger!$B$3:$B$1002=$B$2),64)))
A70: =IFERROR(INDEX(Ledger!$A:$A,AGGREGATE(15,6,ROW(Ledger!$B$3:$B$1002)/(Ledger!$B$3:$B$1002=$B$2),65)),"") | B70: =IF($A70="","",INDEX(Ledger!$C:$C,AGGREGATE(15,6,ROW(Ledger!$B$3:$B$1002)/(Ledger!$B$3:$B$1002=$B$2),65))) | C70: =IF($A70="","",INDEX(Ledger!$D:$D,AGGREGATE(15,6,ROW(Ledger!$B$3:$B$1002)/(Ledger!$B$3:$B$1002=$B$2),65))) | D70: =IF($A70="","",INDEX(Ledger!$E:$E,AGGREGATE(15,6,ROW(Ledger!$B$3:$B$1002)/(Ledger!$B$3:$B$1002=$B$2),65))) | E70: =IF($A70="","",INDEX(Ledger!$F:$F,AGGREGATE(15,6,ROW(Ledger!$B$3:$B$1002)/(Ledger!$B$3:$B$1002=$B$2),65))) | F70: =IF($A70="","",INDEX(Ledger!$H:$H,AGGREGATE(15,6,ROW(Ledger!$B$3:$B$1002)/(Ledger!$B$3:$B$1002=$B$2),65))) | G70: =IF($A70="","",INDEX(Ledger!$I:$I,AGGREGATE(15,6,ROW(Ledger!$B$3:$B$1002)/(Ledger!$B$3:$B$1002=$B$2),65))) | H70: =IF($A70="","",INDEX(Ledger!$K:$K,AGGREGATE(15,6,ROW(Ledger!$B$3:$B$1002)/(Ledger!$B$3:$B$1002=$B$2),65)))
A71: =IFERROR(INDEX(Ledger!$A:$A,AGGREGATE(15,6,ROW(Ledger!$B$3:$B$1002)/(Ledger!$B$3:$B$1002=$B$2),66)),"") | B71: =IF($A71="","",INDEX(Ledger!$C:$C,AGGREGATE(15,6,ROW(Ledger!$B$3:$B$1002)/(Ledger!$B$3:$B$1002=$B$2),66))) | C71: =IF($A71="","",INDEX(Ledger!$D:$D,AGGREGATE(15,6,ROW(Ledger!$B$3:$B$1002)/(Ledger!$B$3:$B$1002=$B$2),66))) | D71: =IF($A71="","",INDEX(Ledger!$E:$E,AGGREGATE(15,6,ROW(Ledger!$B$3:$B$1002)/(Ledger!$B$3:$B$1002=$B$2),66))) | E71: =IF($A71="","",INDEX(Ledger!$F:$F,AGGREGATE(15,6,ROW(Ledger!$B$3:$B$1002)/(Ledger!$B$3:$B$1002=$B$2),66))) | F71: =IF($A71="","",INDEX(Ledger!$H:$H,AGGREGATE(15,6,ROW(Ledger!$B$3:$B$1002)/(Ledger!$B$3:$B$1002=$B$2),66))) | G71: =IF($A71="","",INDEX(Ledger!$I:$I,AGGREGATE(15,6,ROW(Ledger!$B$3:$B$1002)/(Ledger!$B$3:$B$1002=$B$2),66))) | H71: =IF($A71="","",INDEX(Ledger!$K:$K,AGGREGATE(15,6,ROW(Ledger!$B$3:$B$1002)/(Ledger!$B$3:$B$1002=$B$2),66)))
A72: =IFERROR(INDEX(Ledger!$A:$A,AGGREGATE(15,6,ROW(Ledger!$B$3:$B$1002)/(Ledger!$B$3:$B$1002=$B$2),67)),"") | B72: =IF($A72="","",INDEX(Ledger!$C:$C,AGGREGATE(15,6,ROW(Ledger!$B$3:$B$1002)/(Ledger!$B$3:$B$1002=$B$2),67))) | C72: =IF($A72="","",INDEX(Ledger!$D:$D,AGGREGATE(15,6,ROW(Ledger!$B$3:$B$1002)/(Ledger!$B$3:$B$1002=$B$2),67))) | D72: =IF($A72="","",INDEX(Ledger!$E:$E,AGGREGATE(15,6,ROW(Ledger!$B$3:$B$1002)/(Ledger!$B$3:$B$1002=$B$2),67))) | E72: =IF($A72="","",INDEX(Ledger!$F:$F,AGGREGATE(15,6,ROW(Ledger!$B$3:$B$1002)/(Ledger!$B$3:$B$1002=$B$2),67))) | F72: =IF($A72="","",INDEX(Ledger!$H:$H,AGGREGATE(15,6,ROW(Ledger!$B$3:$B$1002)/(Ledger!$B$3:$B$1002=$B$2),67))) | G72: =IF($A72="","",INDEX(Ledger!$I:$I,AGGREGATE(15,6,ROW(Ledger!$B$3:$B$1002)/(Ledger!$B$3:$B$1002=$B$2),67))) | H72: =IF($A72="","",INDEX(Ledger!$K:$K,AGGREGATE(15,6,ROW(Ledger!$B$3:$B$1002)/(Ledger!$B$3:$B$1002=$B$2),67)))
A73: =IFERROR(INDEX(Ledger!$A:$A,AGGREGATE(15,6,ROW(Ledger!$B$3:$B$1002)/(Ledger!$B$3:$B$1002=$B$2),68)),"") | B73: =IF($A73="","",INDEX(Ledger!$C:$C,AGGREGATE(15,6,ROW(Ledger!$B$3:$B$1002)/(Ledger!$B$3:$B$1002=$B$2),68))) | C73: =IF($A73="","",INDEX(Ledger!$D:$D,AGGREGATE(15,6,ROW(Ledger!$B$3:$B$1002)/(Ledger!$B$3:$B$1002=$B$2),68))) | D73: =IF($A73="","",INDEX(Ledger!$E:$E,AGGREGATE(15,6,ROW(Ledger!$B$3:$B$1002)/(Ledger!$B$3:$B$1002=$B$2),68))) | E73: =IF($A73="","",INDEX(Ledger!$F:$F,AGGREGATE(15,6,ROW(Ledger!$B$3:$B$1002)/(Ledger!$B$3:$B$1002=$B$2),68))) | F73: =IF($A73="","",INDEX(Ledger!$H:$H,AGGREGATE(15,6,ROW(Ledger!$B$3:$B$1002)/(Ledger!$B$3:$B$1002=$B$2),68))) | G73: =IF($A73="","",INDEX(Ledger!$I:$I,AGGREGATE(15,6,ROW(Ledger!$B$3:$B$1002)/(Ledger!$B$3:$B$1002=$B$2),68))) | H73: =IF($A73="","",INDEX(Ledger!$K:$K,AGGREGATE(15,6,ROW(Ledger!$B$3:$B$1002)/(Ledger!$B$3:$B$1002=$B$2),68)))
A74: =IFERROR(INDEX(Ledger!$A:$A,AGGREGATE(15,6,ROW(Ledger!$B$3:$B$1002)/(Ledger!$B$3:$B$1002=$B$2),69)),"") | B74: =IF($A74="","",INDEX(Ledger!$C:$C,AGGREGATE(15,6,ROW(Ledger!$B$3:$B$1002)/(Ledger!$B$3:$B$1002=$B$2),69))) | C74: =IF($A74="","",INDEX(Ledger!$D:$D,AGGREGATE(15,6,ROW(Ledger!$B$3:$B$1002)/(Ledger!$B$3:$B$1002=$B$2),69))) | D74: =IF($A74="","",INDEX(Ledger!$E:$E,AGGREGATE(15,6,ROW(Ledger!$B$3:$B$1002)/(Ledger!$B$3:$B$1002=$B$2),69))) | E74: =IF($A74="","",INDEX(Ledger!$F:$F,AGGREGATE(15,6,ROW(Ledger!$B$3:$B$1002)/(Ledger!$B$3:$B$1002=$B$2),69))) | F74: =IF($A74="","",INDEX(Ledger!$H:$H,AGGREGATE(15,6,ROW(Ledger!$B$3:$B$1002)/(Ledger!$B$3:$B$1002=$B$2),69))) | G74: =IF($A74="","",INDEX(Ledger!$I:$I,AGGREGATE(15,6,ROW(Ledger!$B$3:$B$1002)/(Ledger!$B$3:$B$1002=$B$2),69))) | H74: =IF($A74="","",INDEX(Ledger!$K:$K,AGGREGATE(15,6,ROW(Ledger!$B$3:$B$1002)/(Ledger!$B$3:$B$1002=$B$2),69)))
A75: =IFERROR(INDEX(Ledger!$A:$A,AGGREGATE(15,6,ROW(Ledger!$B$3:$B$1002)/(Ledger!$B$3:$B$1002=$B$2),70)),"") | B75: =IF($A75="","",INDEX(Ledger!$C:$C,AGGREGATE(15,6,ROW(Ledger!$B$3:$B$1002)/(Ledger!$B$3:$B$1002=$B$2),70))) | C75: =IF($A75="","",INDEX(Ledger!$D:$D,AGGREGATE(15,6,ROW(Ledger!$B$3:$B$1002)/(Ledger!$B$3:$B$1002=$B$2),70))) | D75: =IF($A75="","",INDEX(Ledger!$E:$E,AGGREGATE(15,6,ROW(Ledger!$B$3:$B$1002)/(Ledger!$B$3:$B$1002=$B$2),70))) | E75: =IF($A75="","",INDEX(Ledger!$F:$F,AGGREGATE(15,6,ROW(Ledger!$B$3:$B$1002)/(Ledger!$B$3:$B$1002=$B$2),70))) | F75: =IF($A75="","",INDEX(Ledger!$H:$H,AGGREGATE(15,6,ROW(Ledger!$B$3:$B$1002)/(Ledger!$B$3:$B$1002=$B$2),70))) | G75: =IF($A75="","",INDEX(Ledger!$I:$I,AGGREGATE(15,6,ROW(Ledger!$B$3:$B$1002)/(Ledger!$B$3:$B$1002=$B$2),70))) | H75: =IF($A75="","",INDEX(Ledger!$K:$K,AGGREGATE(15,6,ROW(Ledger!$B$3:$B$1002)/(Ledger!$B$3:$B$1002=$B$2),70)))
A76: =IFERROR(INDEX(Ledger!$A:$A,AGGREGATE(15,6,ROW(Ledger!$B$3:$B$1002)/(Ledger!$B$3:$B$1002=$B$2),71)),"") | B76: =IF($A76="","",INDEX(Ledger!$C:$C,AGGREGATE(15,6,ROW(Ledger!$B$3:$B$1002)/(Ledger!$B$3:$B$1002=$B$2),71))) | C76: =IF($A76="","",INDEX(Ledger!$D:$D,AGGREGATE(15,6,ROW(Ledger!$B$3:$B$1002)/(Ledger!$B$3:$B$1002=$B$2),71))) | D76: =IF($A76="","",INDEX(Ledger!$E:$E,AGGREGATE(15,6,ROW(Ledger!$B$3:$B$1002)/(Ledger!$B$3:$B$1002=$B$2),71))) | E76: =IF($A76="","",INDEX(Ledger!$F:$F,AGGREGATE(15,6,ROW(Ledger!$B$3:$B$1002)/(Ledger!$B$3:$B$1002=$B$2),71))) | F76: =IF($A76="","",INDEX(Ledger!$H:$H,AGGREGATE(15,6,ROW(Ledger!$B$3:$B$1002)/(Ledger!$B$3:$B$1002=$B$2),71))) | G76: =IF($A76="","",INDEX(Ledger!$I:$I,AGGREGATE(15,6,ROW(Ledger!$B$3:$B$1002)/(Ledger!$B$3:$B$1002=$B$2),71))) | H76: =IF($A76="","",INDEX(Ledger!$K:$K,AGGREGATE(15,6,ROW(Ledger!$B$3:$B$1002)/(Ledger!$B$3:$B$1002=$B$2),71)))
A77: =IFERROR(INDEX(Ledger!$A:$A,AGGREGATE(15,6,ROW(Ledger!$B$3:$B$1002)/(Ledger!$B$3:$B$1002=$B$2),72)),"") | B77: =IF($A77="","",INDEX(Ledger!$C:$C,AGGREGATE(15,6,ROW(Ledger!$B$3:$B$1002)/(Ledger!$B$3:$B$1002=$B$2),72))) | C77: =IF($A77="","",INDEX(Ledger!$D:$D,AGGREGATE(15,6,ROW(Ledger!$B$3:$B$1002)/(Ledger!$B$3:$B$1002=$B$2),72))) | D77: =IF($A77="","",INDEX(Ledger!$E:$E,AGGREGATE(15,6,ROW(Ledger!$B$3:$B$1002)/(Ledger!$B$3:$B$1002=$B$2),72))) | E77: =IF($A77="","",INDEX(Ledger!$F:$F,AGGREGATE(15,6,ROW(Ledger!$B$3:$B$1002)/(Ledger!$B$3:$B$1002=$B$2),72))) | F77: =IF($A77="","",INDEX(Ledger!$H:$H,AGGREGATE(15,6,ROW(Ledger!$B$3:$B$1002)/(Ledger!$B$3:$B$1002=$B$2),72))) | G77: =IF($A77="","",INDEX(Ledger!$I:$I,AGGREGATE(15,6,ROW(Ledger!$B$3:$B$1002)/(Ledger!$B$3:$B$1002=$B$2),72))) | H77: =IF($A77="","",INDEX(Ledger!$K:$K,AGGREGATE(15,6,ROW(Ledger!$B$3:$B$1002)/(Ledger!$B$3:$B$1002=$B$2),72)))
A78: =IFERROR(INDEX(Ledger!$A:$A,AGGREGATE(15,6,ROW(Ledger!$B$3:$B$1002)/(Ledger!$B$3:$B$1002=$B$2),73)),"") | B78: =IF($A78="","",INDEX(Ledger!$C:$C,AGGREGATE(15,6,ROW(Ledger!$B$3:$B$1002)/(Ledger!$B$3:$B$1002=$B$2),73))) | C78: =IF($A78="","",INDEX(Ledger!$D:$D,AGGREGATE(15,6,ROW(Ledger!$B$3:$B$1002)/(Ledger!$B$3:$B$1002=$B$2),73))) | D78: =IF($A78="","",INDEX(Ledger!$E:$E,AGGREGATE(15,6,ROW(Ledger!$B$3:$B$1002)/(Ledger!$B$3:$B$1002=$B$2),73))) | E78: =IF($A78="","",INDEX(Ledger!$F:$F,AGGREGATE(15,6,ROW(Ledger!$B$3:$B$1002)/(Ledger!$B$3:$B$1002=$B$2),73))) | F78: =IF($A78="","",INDEX(Ledger!$H:$H,AGGREGATE(15,6,ROW(Ledger!$B$3:$B$1002)/(Ledger!$B$3:$B$1002=$B$2),73))) | G78: =IF($A78="","",INDEX(Ledger!$I:$I,AGGREGATE(15,6,ROW(Ledger!$B$3:$B$1002)/(Ledger!$B$3:$B$1002=$B$2),73))) | H78: =IF($A78="","",INDEX(Ledger!$K:$K,AGGREGATE(15,6,ROW(Ledger!$B$3:$B$1002)/(Ledger!$B$3:$B$1002=$B$2),73)))
A79: =IFERROR(INDEX(Ledger!$A:$A,AGGREGATE(15,6,ROW(Ledger!$B$3:$B$1002)/(Ledger!$B$3:$B$1002=$B$2),74)),"") | B79: =IF($A79="","",INDEX(Ledger!$C:$C,AGGREGATE(15,6,ROW(Ledger!$B$3:$B$1002)/(Ledger!$B$3:$B$1002=$B$2),74))) | C79: =IF($A79="","",INDEX(Ledger!$D:$D,AGGREGATE(15,6,ROW(Ledger!$B$3:$B$1002)/(Ledger!$B$3:$B$1002=$B$2),74))) | D79: =IF($A79="","",INDEX(Ledger!$E:$E,AGGREGATE(15,6,ROW(Ledger!$B$3:$B$1002)/(Ledger!$B$3:$B$1002=$B$2),74))) | E79: =IF($A79="","",INDEX(Ledger!$F:$F,AGGREGATE(15,6,ROW(Ledger!$B$3:$B$1002)/(Ledger!$B$3:$B$1002=$B$2),74))) | F79: =IF($A79="","",INDEX(Ledger!$H:$H,AGGREGATE(15,6,ROW(Ledger!$B$3:$B$1002)/(Ledger!$B$3:$B$1002=$B$2),74))) | G79: =IF($A79="","",INDEX(Ledger!$I:$I,AGGREGATE(15,6,ROW(Ledger!$B$3:$B$1002)/(Ledger!$B$3:$B$1002=$B$2),74))) | H79: =IF($A79="","",INDEX(Ledger!$K:$K,AGGREGATE(15,6,ROW(Ledger!$B$3:$B$1002)/(Ledger!$B$3:$B$1002=$B$2),74)))
A80: =IFERROR(INDEX(Ledger!$A:$A,AGGREGATE(15,6,ROW(Ledger!$B$3:$B$1002)/(Ledger!$B$3:$B$1002=$B$2),75)),"") | B80: =IF($A80="","",INDEX(Ledger!$C:$C,AGGREGATE(15,6,ROW(Ledger!$B$3:$B$1002)/(Ledger!$B$3:$B$1002=$B$2),75))) | C80: =IF($A80="","",INDEX(Ledger!$D:$D,AGGREGATE(15,6,ROW(Ledger!$B$3:$B$1002)/(Ledger!$B$3:$B$1002=$B$2),75))) | D80: =IF($A80="","",INDEX(Ledger!$E:$E,AGGREGATE(15,6,ROW(Ledger!$B$3:$B$1002)/(Ledger!$B$3:$B$1002=$B$2),75))) | E80: =IF($A80="","",INDEX(Ledger!$F:$F,AGGREGATE(15,6,ROW(Ledger!$B$3:$B$1002)/(Ledger!$B$3:$B$1002=$B$2),75))) | F80: =IF($A80="","",INDEX(Ledger!$H:$H,AGGREGATE(15,6,ROW(Ledger!$B$3:$B$1002)/(Ledger!$B$3:$B$1002=$B$2),75))) | G80: =IF($A80="","",INDEX(Ledger!$I:$I,AGGREGATE(15,6,ROW(Ledger!$B$3:$B$1002)/(Ledger!$B$3:$B$1002=$B$2),75))) | H80: =IF($A80="","",INDEX(Ledger!$K:$K,AGGREGATE(15,6,ROW(Ledger!$B$3:$B$1002)/(Ledger!$B$3:$B$1002=$B$2),75)))
A81: =IFERROR(INDEX(Ledger!$A:$A,AGGREGATE(15,6,ROW(Ledger!$B$3:$B$1002)/(Ledger!$B$3:$B$1002=$B$2),76)),"") | B81: =IF($A81="","",INDEX(Ledger!$C:$C,AGGREGATE(15,6,ROW(Ledger!$B$3:$B$1002)/(Ledger!$B$3:$B$1002=$B$2),76))) | C81: =IF($A81="","",INDEX(Ledger!$D:$D,AGGREGATE(15,6,ROW(Ledger!$B$3:$B$1002)/(Ledger!$B$3:$B$1002=$B$2),76))) | D81: =IF($A81="","",INDEX(Ledger!$E:$E,AGGREGATE(15,6,ROW(Ledger!$B$3:$B$1002)/(Ledger!$B$3:$B$1002=$B$2),76))) | E81: =IF($A81="","",INDEX(Ledger!$F:$F,AGGREGATE(15,6,ROW(Ledger!$B$3:$B$1002)/(Ledger!$B$3:$B$1002=$B$2),76))) | F81: =IF($A81="","",INDEX(Ledger!$H:$H,AGGREGATE(15,6,ROW(Ledger!$B$3:$B$1002)/(Ledger!$B$3:$B$1002=$B$2),76))) | G81: =IF($A81="","",INDEX(Ledger!$I:$I,AGGREGATE(15,6,ROW(Ledger!$B$3:$B$1002)/(Ledger!$B$3:$B$1002=$B$2),76))) | H81: =IF($A81="","",INDEX(Ledger!$K:$K,AGGREGATE(15,6,ROW(Ledger!$B$3:$B$1002)/(Ledger!$B$3:$B$1002=$B$2),76)))
A82: =IFERROR(INDEX(Ledger!$A:$A,AGGREGATE(15,6,ROW(Ledger!$B$3:$B$1002)/(Ledger!$B$3:$B$1002=$B$2),77)),"") | B82: =IF($A82="","",INDEX(Ledger!$C:$C,AGGREGATE(15,6,ROW(Ledger!$B$3:$B$1002)/(Ledger!$B$3:$B$1002=$B$2),77))) | C82: =IF($A82="","",INDEX(Ledger!$D:$D,AGGREGATE(15,6,ROW(Ledger!$B$3:$B$1002)/(Ledger!$B$3:$B$1002=$B$2),77))) | D82: =IF($A82="","",INDEX(Ledger!$E:$E,AGGREGATE(15,6,ROW(Ledger!$B$3:$B$1002)/(Ledger!$B$3:$B$1002=$B$2),77))) | E82: =IF($A82="","",INDEX(Ledger!$F:$F,AGGREGATE(15,6,ROW(Ledger!$B$3:$B$1002)/(Ledger!$B$3:$B$1002=$B$2),77))) | F82: =IF($A82="","",INDEX(Ledger!$H:$H,AGGREGATE(15,6,ROW(Ledger!$B$3:$B$1002)/(Ledger!$B$3:$B$1002=$B$2),77))) | G82: =IF($A82="","",INDEX(Ledger!$I:$I,AGGREGATE(15,6,ROW(Ledger!$B$3:$B$1002)/(Ledger!$B$3:$B$1002=$B$2),77))) | H82: =IF($A82="","",INDEX(Ledger!$K:$K,AGGREGATE(15,6,ROW(Ledger!$B$3:$B$1002)/(Ledger!$B$3:$B$1002=$B$2),77)))
A83: =IFERROR(INDEX(Ledger!$A:$A,AGGREGATE(15,6,ROW(Ledger!$B$3:$B$1002)/(Ledger!$B$3:$B$1002=$B$2),78)),"") | B83: =IF($A83="","",INDEX(Ledger!$C:$C,AGGREGATE(15,6,ROW(Ledger!$B$3:$B$1002)/(Ledger!$B$3:$B$1002=$B$2),78))) | C83: =IF($A83="","",INDEX(Ledger!$D:$D,AGGREGATE(15,6,ROW(Ledger!$B$3:$B$1002)/(Ledger!$B$3:$B$1002=$B$2),78))) | D83: =IF($A83="","",INDEX(Ledger!$E:$E,AGGREGATE(15,6,ROW(Ledger!$B$3:$B$1002)/(Ledger!$B$3:$B$1002=$B$2),78))) | E83: =IF($A83="","",INDEX(Ledger!$F:$F,AGGREGATE(15,6,ROW(Ledger!$B$3:$B$1002)/(Ledger!$B$3:$B$1002=$B$2),78))) | F83: =IF($A83="","",INDEX(Ledger!$H:$H,AGGREGATE(15,6,ROW(Ledger!$B$3:$B$1002)/(Ledger!$B$3:$B$1002=$B$2),78))) | G83: =IF($A83="","",INDEX(Ledger!$I:$I,AGGREGATE(15,6,ROW(Ledger!$B$3:$B$1002)/(Ledger!$B$3:$B$1002=$B$2),78))) | H83: =IF($A83="","",INDEX(Ledger!$K:$K,AGGREGATE(15,6,ROW(Ledger!$B$3:$B$1002)/(Ledger!$B$3:$B$1002=$B$2),78)))
A84: =IFERROR(INDEX(Ledger!$A:$A,AGGREGATE(15,6,ROW(Ledger!$B$3:$B$1002)/(Ledger!$B$3:$B$1002=$B$2),79)),"") | B84: =IF($A84="","",INDEX(Ledger!$C:$C,AGGREGATE(15,6,ROW(Ledger!$B$3:$B$1002)/(Ledger!$B$3:$B$1002=$B$2),79))) | C84: =IF($A84="","",INDEX(Ledger!$D:$D,AGGREGATE(15,6,ROW(Ledger!$B$3:$B$1002)/(Ledger!$B$3:$B$1002=$B$2),79))) | D84: =IF($A84="","",INDEX(Ledger!$E:$E,AGGREGATE(15,6,ROW(Ledger!$B$3:$B$1002)/(Ledger!$B$3:$B$1002=$B$2),79))) | E84: =IF($A84="","",INDEX(Ledger!$F:$F,AGGREGATE(15,6,ROW(Ledger!$B$3:$B$1002)/(Ledger!$B$3:$B$1002=$B$2),79))) | F84: =IF($A84="","",INDEX(Ledger!$H:$H,AGGREGATE(15,6,ROW(Ledger!$B$3:$B$1002)/(Ledger!$B$3:$B$1002=$B$2),79))) | G84: =IF($A84="","",INDEX(Ledger!$I:$I,AGGREGATE(15,6,ROW(Ledger!$B$3:$B$1002)/(Ledger!$B$3:$B$1002=$B$2),79))) | H84: =IF($A84="","",INDEX(Ledger!$K:$K,AGGREGATE(15,6,ROW(Ledger!$B$3:$B$1002)/(Ledger!$B$3:$B$1002=$B$2),79)))
A85: =IFERROR(INDEX(Ledger!$A:$A,AGGREGATE(15,6,ROW(Ledger!$B$3:$B$1002)/(Ledger!$B$3:$B$1002=$B$2),80)),"") | B85: =IF($A85="","",INDEX(Ledger!$C:$C,AGGREGATE(15,6,ROW(Ledger!$B$3:$B$1002)/(Ledger!$B$3:$B$1002=$B$2),80))) | C85: =IF($A85="","",INDEX(Ledger!$D:$D,AGGREGATE(15,6,ROW(Ledger!$B$3:$B$1002)/(Ledger!$B$3:$B$1002=$B$2),80))) | D85: =IF($A85="","",INDEX(Ledger!$E:$E,AGGREGATE(15,6,ROW(Ledger!$B$3:$B$1002)/(Ledger!$B$3:$B$1002=$B$2),80))) | E85: =IF($A85="","",INDEX(Ledger!$F:$F,AGGREGATE(15,6,ROW(Ledger!$B$3:$B$1002)/(Ledger!$B$3:$B$1002=$B$2),80))) | F85: =IF($A85="","",INDEX(Ledger!$H:$H,AGGREGATE(15,6,ROW(Ledger!$B$3:$B$1002)/(Ledger!$B$3:$B$1002=$B$2),80))) | G85: =IF($A85="","",INDEX(Ledger!$I:$I,AGGREGATE(15,6,ROW(Ledger!$B$3:$B$1002)/(Ledger!$B$3:$B$1002=$B$2),80))) | H85: =IF($A85="","",INDEX(Ledger!$K:$K,AGGREGATE(15,6,ROW(Ledger!$B$3:$B$1002)/(Ledger!$B$3:$B$1002=$B$2),80)))
A86: =IFERROR(INDEX(Ledger!$A:$A,AGGREGATE(15,6,ROW(Ledger!$B$3:$B$1002)/(Ledger!$B$3:$B$1002=$B$2),81)),"") | B86: =IF($A86="","",INDEX(Ledger!$C:$C,AGGREGATE(15,6,ROW(Ledger!$B$3:$B$1002)/(Ledger!$B$3:$B$1002=$B$2),81))) | C86: =IF($A86="","",INDEX(Ledger!$D:$D,AGGREGATE(15,6,ROW(Ledger!$B$3:$B$1002)/(Ledger!$B$3:$B$1002=$B$2),81))) | D86: =IF($A86="","",INDEX(Ledger!$E:$E,AGGREGATE(15,6,ROW(Ledger!$B$3:$B$1002)/(Ledger!$B$3:$B$1002=$B$2),81))) | E86: =IF($A86="","",INDEX(Ledger!$F:$F,AGGREGATE(15,6,ROW(Ledger!$B$3:$B$1002)/(Ledger!$B$3:$B$1002=$B$2),81))) | F86: =IF($A86="","",INDEX(Ledger!$H:$H,AGGREGATE(15,6,ROW(Ledger!$B$3:$B$1002)/(Ledger!$B$3:$B$1002=$B$2),81))) | G86: =IF($A86="","",INDEX(Ledger!$I:$I,AGGREGATE(15,6,ROW(Ledger!$B$3:$B$1002)/(Ledger!$B$3:$B$1002=$B$2),81))) | H86: =IF($A86="","",INDEX(Ledger!$K:$K,AGGREGATE(15,6,ROW(Ledger!$B$3:$B$1002)/(Ledger!$B$3:$B$1002=$B$2),81)))
A87: =IFERROR(INDEX(Ledger!$A:$A,AGGREGATE(15,6,ROW(Ledger!$B$3:$B$1002)/(Ledger!$B$3:$B$1002=$B$2),82)),"") | B87: =IF($A87="","",INDEX(Ledger!$C:$C,AGGREGATE(15,6,ROW(Ledger!$B$3:$B$1002)/(Ledger!$B$3:$B$1002=$B$2),82))) | C87: =IF($A87="","",INDEX(Ledger!$D:$D,AGGREGATE(15,6,ROW(Ledger!$B$3:$B$1002)/(Ledger!$B$3:$B$1002=$B$2),82))) | D87: =IF($A87="","",INDEX(Ledger!$E:$E,AGGREGATE(15,6,ROW(Ledger!$B$3:$B$1002)/(Ledger!$B$3:$B$1002=$B$2),82))) | E87: =IF($A87="","",INDEX(Ledger!$F:$F,AGGREGATE(15,6,ROW(Ledger!$B$3:$B$1002)/(Ledger!$B$3:$B$1002=$B$2),82))) | F87: =IF($A87="","",INDEX(Ledger!$H:$H,AGGREGATE(15,6,ROW(Ledger!$B$3:$B$1002)/(Ledger!$B$3:$B$1002=$B$2),82))) | G87: =IF($A87="","",INDEX(Ledger!$I:$I,AGGREGATE(15,6,ROW(Ledger!$B$3:$B$1002)/(Ledger!$B$3:$B$1002=$B$2),82))) | H87: =IF($A87="","",INDEX(Ledger!$K:$K,AGGREGATE(15,6,ROW(Ledger!$B$3:$B$1002)/(Ledger!$B$3:$B$1002=$B$2),82)))
A88: =IFERROR(INDEX(Ledger!$A:$A,AGGREGATE(15,6,ROW(Ledger!$B$3:$B$1002)/(Ledger!$B$3:$B$1002=$B$2),83)),"") | B88: =IF($A88="","",INDEX(Ledger!$C:$C,AGGREGATE(15,6,ROW(Ledger!$B$3:$B$1002)/(Ledger!$B$3:$B$1002=$B$2),83))) | C88: =IF($A88="","",INDEX(Ledger!$D:$D,AGGREGATE(15,6,ROW(Ledger!$B$3:$B$1002)/(Ledger!$B$3:$B$1002=$B$2),83))) | D88: =IF($A88="","",INDEX(Ledger!$E:$E,AGGREGATE(15,6,ROW(Ledger!$B$3:$B$1002)/(Ledger!$B$3:$B$1002=$B$2),83))) | E88: =IF($A88="","",INDEX(Ledger!$F:$F,AGGREGATE(15,6,ROW(Ledger!$B$3:$B$1002)/(Ledger!$B$3:$B$1002=$B$2),83))) | F88: =IF($A88="","",INDEX(Ledger!$H:$H,AGGREGATE(15,6,ROW(Ledger!$B$3:$B$1002)/(Ledger!$B$3:$B$1002=$B$2),83))) | G88: =IF($A88="","",INDEX(Ledger!$I:$I,AGGREGATE(15,6,ROW(Ledger!$B$3:$B$1002)/(Ledger!$B$3:$B$1002=$B$2),83))) | H88: =IF($A88="","",INDEX(Ledger!$K:$K,AGGREGATE(15,6,ROW(Ledger!$B$3:$B$1002)/(Ledger!$B$3:$B$1002=$B$2),83)))
A89: =IFERROR(INDEX(Ledger!$A:$A,AGGREGATE(15,6,ROW(Ledger!$B$3:$B$1002)/(Ledger!$B$3:$B$1002=$B$2),84)),"") | B89: =IF($A89="","",INDEX(Ledger!$C:$C,AGGREGATE(15,6,ROW(Ledger!$B$3:$B$1002)/(Ledger!$B$3:$B$1002=$B$2),84))) | C89: =IF($A89="","",INDEX(Ledger!$D:$D,AGGREGATE(15,6,ROW(Ledger!$B$3:$B$1002)/(Ledger!$B$3:$B$1002=$B$2),84))) | D89: =IF($A89="","",INDEX(Ledger!$E:$E,AGGREGATE(15,6,ROW(Ledger!$B$3:$B$1002)/(Ledger!$B$3:$B$1002=$B$2),84))) | E89: =IF($A89="","",INDEX(Ledger!$F:$F,AGGREGATE(15,6,ROW(Ledger!$B$3:$B$1002)/(Ledger!$B$3:$B$1002=$B$2),84))) | F89: =IF($A89="","",INDEX(Ledger!$H:$H,AGGREGATE(15,6,ROW(Ledger!$B$3:$B$1002)/(Ledger!$B$3:$B$1002=$B$2),84))) | G89: =IF($A89="","",INDEX(Ledger!$I:$I,AGGREGATE(15,6,ROW(Ledger!$B$3:$B$1002)/(Ledger!$B$3:$B$1002=$B$2),84))) | H89: =IF($A89="","",INDEX(Ledger!$K:$K,AGGREGATE(15,6,ROW(Ledger!$B$3:$B$1002)/(Ledger!$B$3:$B$1002=$B$2),84)))
A90: =IFERROR(INDEX(Ledger!$A:$A,AGGREGATE(15,6,ROW(Ledger!$B$3:$B$1002)/(Ledger!$B$3:$B$1002=$B$2),85)),"") | B90: =IF($A90="","",INDEX(Ledger!$C:$C,AGGREGATE(15,6,ROW(Ledger!$B$3:$B$1002)/(Ledger!$B$3:$B$1002=$B$2),85))) | C90: =IF($A90="","",INDEX(Ledger!$D:$D,AGGREGATE(15,6,ROW(Ledger!$B$3:$B$1002)/(Ledger!$B$3:$B$1002=$B$2),85))) | D90: =IF($A90="","",INDEX(Ledger!$E:$E,AGGREGATE(15,6,ROW(Ledger!$B$3:$B$1002)/(Ledger!$B$3:$B$1002=$B$2),85))) | E90: =IF($A90="","",INDEX(Ledger!$F:$F,AGGREGATE(15,6,ROW(Ledger!$B$3:$B$1002)/(Ledger!$B$3:$B$1002=$B$2),85))) | F90: =IF($A90="","",INDEX(Ledger!$H:$H,AGGREGATE(15,6,ROW(Ledger!$B$3:$B$1002)/(Ledger!$B$3:$B$1002=$B$2),85))) | G90: =IF($A90="","",INDEX(Ledger!$I:$I,AGGREGATE(15,6,ROW(Ledger!$B$3:$B$1002)/(Ledger!$B$3:$B$1002=$B$2),85))) | H90: =IF($A90="","",INDEX(Ledger!$K:$K,AGGREGATE(15,6,ROW(Ledger!$B$3:$B$1002)/(Ledger!$B$3:$B$1002=$B$2),85)))
A91: =IFERROR(INDEX(Ledger!$A:$A,AGGREGATE(15,6,ROW(Ledger!$B$3:$B$1002)/(Ledger!$B$3:$B$1002=$B$2),86)),"") | B91: =IF($A91="","",INDEX(Ledger!$C:$C,AGGREGATE(15,6,ROW(Ledger!$B$3:$B$1002)/(Ledger!$B$3:$B$1002=$B$2),86))) | C91: =IF($A91="","",INDEX(Ledger!$D:$D,AGGREGATE(15,6,ROW(Ledger!$B$3:$B$1002)/(Ledger!$B$3:$B$1002=$B$2),86))) | D91: =IF($A91="","",INDEX(Ledger!$E:$E,AGGREGATE(15,6,ROW(Ledger!$B$3:$B$1002)/(Ledger!$B$3:$B$1002=$B$2),86))) | E91: =IF($A91="","",INDEX(Ledger!$F:$F,AGGREGATE(15,6,ROW(Ledger!$B$3:$B$1002)/(Ledger!$B$3:$B$1002=$B$2),86))) | F91: =IF($A91="","",INDEX(Ledger!$H:$H,AGGREGATE(15,6,ROW(Ledger!$B$3:$B$1002)/(Ledger!$B$3:$B$1002=$B$2),86))) | G91: =IF($A91="","",INDEX(Ledger!$I:$I,AGGREGATE(15,6,ROW(Ledger!$B$3:$B$1002)/(Ledger!$B$3:$B$1002=$B$2),86))) | H91: =IF($A91="","",INDEX(Ledger!$K:$K,AGGREGATE(15,6,ROW(Ledger!$B$3:$B$1002)/(Ledger!$B$3:$B$1002=$B$2),86)))
A92: =IFERROR(INDEX(Ledger!$A:$A,AGGREGATE(15,6,ROW(Ledger!$B$3:$B$1002)/(Ledger!$B$3:$B$1002=$B$2),87)),"") | B92: =IF($A92="","",INDEX(Ledger!$C:$C,AGGREGATE(15,6,ROW(Ledger!$B$3:$B$1002)/(Ledger!$B$3:$B$1002=$B$2),87))) | C92: =IF($A92="","",INDEX(Ledger!$D:$D,AGGREGATE(15,6,ROW(Ledger!$B$3:$B$1002)/(Ledger!$B$3:$B$1002=$B$2),87))) | D92: =IF($A92="","",INDEX(Ledger!$E:$E,AGGREGATE(15,6,ROW(Ledger!$B$3:$B$1002)/(Ledger!$B$3:$B$1002=$B$2),87))) | E92: =IF($A92="","",INDEX(Ledger!$F:$F,AGGREGATE(15,6,ROW(Ledger!$B$3:$B$1002)/(Ledger!$B$3:$B$1002=$B$2),87))) | F92: =IF($A92="","",INDEX(Ledger!$H:$H,AGGREGATE(15,6,ROW(Ledger!$B$3:$B$1002)/(Ledger!$B$3:$B$1002=$B$2),87))) | G92: =IF($A92="","",INDEX(Ledger!$I:$I,AGGREGATE(15,6,ROW(Ledger!$B$3:$B$1002)/(Ledger!$B$3:$B$1002=$B$2),87))) | H92: =IF($A92="","",INDEX(Ledger!$K:$K,AGGREGATE(15,6,ROW(Ledger!$B$3:$B$1002)/(Ledger!$B$3:$B$1002=$B$2),87)))
A93: =IFERROR(INDEX(Ledger!$A:$A,AGGREGATE(15,6,ROW(Ledger!$B$3:$B$1002)/(Ledger!$B$3:$B$1002=$B$2),88)),"") | B93: =IF($A93="","",INDEX(Ledger!$C:$C,AGGREGATE(15,6,ROW(Ledger!$B$3:$B$1002)/(Ledger!$B$3:$B$1002=$B$2),88))) | C93: =IF($A93="","",INDEX(Ledger!$D:$D,AGGREGATE(15,6,ROW(Ledger!$B$3:$B$1002)/(Ledger!$B$3:$B$1002=$B$2),88))) | D93: =IF($A93="","",INDEX(Ledger!$E:$E,AGGREGATE(15,6,ROW(Ledger!$B$3:$B$1002)/(Ledger!$B$3:$B$1002=$B$2),88))) | E93: =IF($A93="","",INDEX(Ledger!$F:$F,AGGREGATE(15,6,ROW(Ledger!$B$3:$B$1002)/(Ledger!$B$3:$B$1002=$B$2),88))) | F93: =IF($A93="","",INDEX(Ledger!$H:$H,AGGREGATE(15,6,ROW(Ledger!$B$3:$B$1002)/(Ledger!$B$3:$B$1002=$B$2),88))) | G93: =IF($A93="","",INDEX(Ledger!$I:$I,AGGREGATE(15,6,ROW(Ledger!$B$3:$B$1002)/(Ledger!$B$3:$B$1002=$B$2),88))) | H93: =IF($A93="","",INDEX(Ledger!$K:$K,AGGREGATE(15,6,ROW(Ledger!$B$3:$B$1002)/(Ledger!$B$3:$B$1002=$B$2),88)))
A94: =IFERROR(INDEX(Ledger!$A:$A,AGGREGATE(15,6,ROW(Ledger!$B$3:$B$1002)/(Ledger!$B$3:$B$1002=$B$2),89)),"") | B94: =IF($A94="","",INDEX(Ledger!$C:$C,AGGREGATE(15,6,ROW(Ledger!$B$3:$B$1002)/(Ledger!$B$3:$B$1002=$B$2),89))) | C94: =IF($A94="","",INDEX(Ledger!$D:$D,AGGREGATE(15,6,ROW(Ledger!$B$3:$B$1002)/(Ledger!$B$3:$B$1002=$B$2),89))) | D94: =IF($A94="","",INDEX(Ledger!$E:$E,AGGREGATE(15,6,ROW(Ledger!$B$3:$B$1002)/(Ledger!$B$3:$B$1002=$B$2),89))) | E94: =IF($A94="","",INDEX(Ledger!$F:$F,AGGREGATE(15,6,ROW(Ledger!$B$3:$B$1002)/(Ledger!$B$3:$B$1002=$B$2),89))) | F94: =IF($A94="","",INDEX(Ledger!$H:$H,AGGREGATE(15,6,ROW(Ledger!$B$3:$B$1002)/(Ledger!$B$3:$B$1002=$B$2),89))) | G94: =IF($A94="","",INDEX(Ledger!$I:$I,AGGREGATE(15,6,ROW(Ledger!$B$3:$B$1002)/(Ledger!$B$3:$B$1002=$B$2),89))) | H94: =IF($A94="","",INDEX(Ledger!$K:$K,AGGREGATE(15,6,ROW(Ledger!$B$3:$B$1002)/(Ledger!$B$3:$B$1002=$B$2),89)))
A95: =IFERROR(INDEX(Ledger!$A:$A,AGGREGATE(15,6,ROW(Ledger!$B$3:$B$1002)/(Ledger!$B$3:$B$1002=$B$2),90)),"") | B95: =IF($A95="","",INDEX(Ledger!$C:$C,AGGREGATE(15,6,ROW(Ledger!$B$3:$B$1002)/(Ledger!$B$3:$B$1002=$B$2),90))) | C95: =IF($A95="","",INDEX(Ledger!$D:$D,AGGREGATE(15,6,ROW(Ledger!$B$3:$B$1002)/(Ledger!$B$3:$B$1002=$B$2),90))) | D95: =IF($A95="","",INDEX(Ledger!$E:$E,AGGREGATE(15,6,ROW(Ledger!$B$3:$B$1002)/(Ledger!$B$3:$B$1002=$B$2),90))) | E95: =IF($A95="","",INDEX(Ledger!$F:$F,AGGREGATE(15,6,ROW(Ledger!$B$3:$B$1002)/(Ledger!$B$3:$B$1002=$B$2),90))) | F95: =IF($A95="","",INDEX(Ledger!$H:$H,AGGREGATE(15,6,ROW(Ledger!$B$3:$B$1002)/(Ledger!$B$3:$B$1002=$B$2),90))) | G95: =IF($A95="","",INDEX(Ledger!$I:$I,AGGREGATE(15,6,ROW(Ledger!$B$3:$B$1002)/(Ledger!$B$3:$B$1002=$B$2),90))) | H95: =IF($A95="","",INDEX(Ledger!$K:$K,AGGREGATE(15,6,ROW(Ledger!$B$3:$B$1002)/(Ledger!$B$3:$B$1002=$B$2),90)))
A96: =IFERROR(INDEX(Ledger!$A:$A,AGGREGATE(15,6,ROW(Ledger!$B$3:$B$1002)/(Ledger!$B$3:$B$1002=$B$2),91)),"") | B96: =IF($A96="","",INDEX(Ledger!$C:$C,AGGREGATE(15,6,ROW(Ledger!$B$3:$B$1002)/(Ledger!$B$3:$B$1002=$B$2),91))) | C96: =IF($A96="","",INDEX(Ledger!$D:$D,AGGREGATE(15,6,ROW(Ledger!$B$3:$B$1002)/(Ledger!$B$3:$B$1002=$B$2),91))) | D96: =IF($A96="","",INDEX(Ledger!$E:$E,AGGREGATE(15,6,ROW(Ledger!$B$3:$B$1002)/(Ledger!$B$3:$B$1002=$B$2),91))) | E96: =IF($A96="","",INDEX(Ledger!$F:$F,AGGREGATE(15,6,ROW(Ledger!$B$3:$B$1002)/(Ledger!$B$3:$B$1002=$B$2),91))) | F96: =IF($A96="","",INDEX(Ledger!$H:$H,AGGREGATE(15,6,ROW(Ledger!$B$3:$B$1002)/(Ledger!$B$3:$B$1002=$B$2),91))) | G96: =IF($A96="","",INDEX(Ledger!$I:$I,AGGREGATE(15,6,ROW(Ledger!$B$3:$B$1002)/(Ledger!$B$3:$B$1002=$B$2),91))) | H96: =IF($A96="","",INDEX(Ledger!$K:$K,AGGREGATE(15,6,ROW(Ledger!$B$3:$B$1002)/(Ledger!$B$3:$B$1002=$B$2),91)))
A97: =IFERROR(INDEX(Ledger!$A:$A,AGGREGATE(15,6,ROW(Ledger!$B$3:$B$1002)/(Ledger!$B$3:$B$1002=$B$2),92)),"") | B97: =IF($A97="","",INDEX(Ledger!$C:$C,AGGREGATE(15,6,ROW(Ledger!$B$3:$B$1002)/(Ledger!$B$3:$B$1002=$B$2),92))) | C97: =IF($A97="","",INDEX(Ledger!$D:$D,AGGREGATE(15,6,ROW(Ledger!$B$3:$B$1002)/(Ledger!$B$3:$B$1002=$B$2),92))) | D97: =IF($A97="","",INDEX(Ledger!$E:$E,AGGREGATE(15,6,ROW(Ledger!$B$3:$B$1002)/(Ledger!$B$3:$B$1002=$B$2),92))) | E97: =IF($A97="","",INDEX(Ledger!$F:$F,AGGREGATE(15,6,ROW(Ledger!$B$3:$B$1002)/(Ledger!$B$3:$B$1002=$B$2),92))) | F97: =IF($A97="","",INDEX(Ledger!$H:$H,AGGREGATE(15,6,ROW(Ledger!$B$3:$B$1002)/(Ledger!$B$3:$B$1002=$B$2),92))) | G97: =IF($A97="","",INDEX(Ledger!$I:$I,AGGREGATE(15,6,ROW(Ledger!$B$3:$B$1002)/(Ledger!$B$3:$B$1002=$B$2),92))) | H97: =IF($A97="","",INDEX(Ledger!$K:$K,AGGREGATE(15,6,ROW(Ledger!$B$3:$B$1002)/(Ledger!$B$3:$B$1002=$B$2),92)))
A98: =IFERROR(INDEX(Ledger!$A:$A,AGGREGATE(15,6,ROW(Ledger!$B$3:$B$1002)/(Ledger!$B$3:$B$1002=$B$2),93)),"") | B98: =IF($A98="","",INDEX(Ledger!$C:$C,AGGREGATE(15,6,ROW(Ledger!$B$3:$B$1002)/(Ledger!$B$3:$B$1002=$B$2),93))) | C98: =IF($A98="","",INDEX(Ledger!$D:$D,AGGREGATE(15,6,ROW(Ledger!$B$3:$B$1002)/(Ledger!$B$3:$B$1002=$B$2),93))) | D98: =IF($A98="","",INDEX(Ledger!$E:$E,AGGREGATE(15,6,ROW(Ledger!$B$3:$B$1002)/(Ledger!$B$3:$B$1002=$B$2),93))) | E98: =IF($A98="","",INDEX(Ledger!$F:$F,AGGREGATE(15,6,ROW(Ledger!$B$3:$B$1002)/(Ledger!$B$3:$B$1002=$B$2),93))) | F98: =IF($A98="","",INDEX(Ledger!$H:$H,AGGREGATE(15,6,ROW(Ledger!$B$3:$B$1002)/(Ledger!$B$3:$B$1002=$B$2),93))) | G98: =IF($A98="","",INDEX(Ledger!$I:$I,AGGREGATE(15,6,ROW(Ledger!$B$3:$B$1002)/(Ledger!$B$3:$B$1002=$B$2),93))) | H98: =IF($A98="","",INDEX(Ledger!$K:$K,AGGREGATE(15,6,ROW(Ledger!$B$3:$B$1002)/(Ledger!$B$3:$B$1002=$B$2),93)))
A99: =IFERROR(INDEX(Ledger!$A:$A,AGGREGATE(15,6,ROW(Ledger!$B$3:$B$1002)/(Ledger!$B$3:$B$1002=$B$2),94)),"") | B99: =IF($A99="","",INDEX(Ledger!$C:$C,AGGREGATE(15,6,ROW(Ledger!$B$3:$B$1002)/(Ledger!$B$3:$B$1002=$B$2),94))) | C99: =IF($A99="","",INDEX(Ledger!$D:$D,AGGREGATE(15,6,ROW(Ledger!$B$3:$B$1002)/(Ledger!$B$3:$B$1002=$B$2),94))) | D99: =IF($A99="","",INDEX(Ledger!$E:$E,AGGREGATE(15,6,ROW(Ledger!$B$3:$B$1002)/(Ledger!$B$3:$B$1002=$B$2),94))) | E99: =IF($A99="","",INDEX(Ledger!$F:$F,AGGREGATE(15,6,ROW(Ledger!$B$3:$B$1002)/(Ledger!$B$3:$B$1002=$B$2),94))) | F99: =IF($A99="","",INDEX(Ledger!$H:$H,AGGREGATE(15,6,ROW(Ledger!$B$3:$B$1002)/(Ledger!$B$3:$B$1002=$B$2),94))) | G99: =IF($A99="","",INDEX(Ledger!$I:$I,AGGREGATE(15,6,ROW(Ledger!$B$3:$B$1002)/(Ledger!$B$3:$B$1002=$B$2),94))) | H99: =IF($A99="","",INDEX(Ledger!$K:$K,AGGREGATE(15,6,ROW(Ledger!$B$3:$B$1002)/(Ledger!$B$3:$B$1002=$B$2),94)))
A100: =IFERROR(INDEX(Ledger!$A:$A,AGGREGATE(15,6,ROW(Ledger!$B$3:$B$1002)/(Ledger!$B$3:$B$1002=$B$2),95)),"") | B100: =IF($A100="","",INDEX(Ledger!$C:$C,AGGREGATE(15,6,ROW(Ledger!$B$3:$B$1002)/(Ledger!$B$3:$B$1002=$B$2),95))) | C100: =IF($A100="","",INDEX(Ledger!$D:$D,AGGREGATE(15,6,ROW(Ledger!$B$3:$B$1002)/(Ledger!$B$3:$B$1002=$B$2),95))) | D100: =IF($A100="","",INDEX(Ledger!$E:$E,AGGREGATE(15,6,ROW(Ledger!$B$3:$B$1002)/(Ledger!$B$3:$B$1002=$B$2),95))) | E100: =IF($A100="","",INDEX(Ledger!$F:$F,AGGREGATE(15,6,ROW(Ledger!$B$3:$B$1002)/(Ledger!$B$3:$B$1002=$B$2),95))) | F100: =IF($A100="","",INDEX(Ledger!$H:$H,AGGREGATE(15,6,ROW(Ledger!$B$3:$B$1002)/(Ledger!$B$3:$B$1002=$B$2),95))) | G100: =IF($A100="","",INDEX(Ledger!$I:$I,AGGREGATE(15,6,ROW(Ledger!$B$3:$B$1002)/(Ledger!$B$3:$B$1002=$B$2),95))) | H100: =IF($A100="","",INDEX(Ledger!$K:$K,AGGREGATE(15,6,ROW(Ledger!$B$3:$B$1002)/(Ledger!$B$3:$B$1002=$B$2),95)))
...

Sheet Help
A1: DIPSEVA कसे वापरावे — 5 मिनिट मार्गदर्शक
A3: 1) Items मध्ये वस्तू + भाडे + Opening Stock लिहा.
A4: 2) Customers मध्ये ग्राहक + फोन + Opening Due लिहा.
A5: 3) रोजची नोंद फक्त Ledger मध्ये: Date|Customer|Type|Item|Qty|Paid.
A6: Issue=sामान दिले (Bill auto), Return=परत (फक्त Qty), Payment=पैसे (फक्त Paid).
A7: 4) Yogesh: Issue 850+Paid 600, Issue 900+Paid 0 => Baki 1150. Payment 500 => 650.
A8: 5) Dashboard/Khata/Stock auto. Statement मध्ये ग्राहक निवडा + WhatsApp copy.
A9: 6) App मधूनच entry करा. Sheet फक्त backup. निळ्या cell मध्ये हाताने लिहू नका.
