Workbook
Name SlicerCache_Table_1_Col_1: #N/A
Name SlicerCache_Table_1_Col_3: #N/A
Name SlicerCache_Table_1_Col_7: #N/A

Sheet Sales
A1: DATE | B1: ITEM ID | C1: ITEM NAME | D1: QUANTITY | E1: PRICE | F1: TOTAL | G1: CUSTOMER NAME | H1: PAYMENT METHOD | I1: PAYMENT RECEIVED | J1: PAYMENT BALANCE | K1: RETURN QUANTITY | L1: BALANCE QUANTITY | M1: Narration
A2: 46204 | B2: CTRNG | C2: {=_xlfn.XLOOKUP(B2, Inventory!A:A, Inventory!B:B, "")} -> CTRNG | D2: 1 | E2: 850 | F2: =D2*E2 -> 850 | G2: Yogesh Caterers | I2: 600 | J2: =IF(F2-I2=0,"",F2-I2) -> 250 | K2: 1 | L2: =IF(D2-K2,"",D2-K2) -> 0
A3: 46204 | B3: GD | C3: {=_xlfn.XLOOKUP(B3, Inventory!A:A, Inventory!B:B, "")} -> Gadi | D3: 10 | E3: 15 | F3: =D3*E3 -> 150 | G3: Samarth Sound | I3: 150 | J3: =IF(F3-I3=0,"",F3-I3) | K3: 10 | L3: =IF(D3-K3,"",D3-K3) -> 0
A4: 46204 | B4: AAH | C4: {=_xlfn.XLOOKUP(B4, Inventory!A:A, Inventory!B:B, "")} -> Amp Ahuja | D4: 1 | E4: 800 | F4: =D4*E4 -> 800 | G4: Samarth Sound | I4: 800 | J4: =IF(F4-I4=0,"",F4-I4) | K4: 1 | L4: =IF(D4-K4,"",D4-K4) -> 0
A5: 46204 | B5: CH | C5: {=_xlfn.XLOOKUP(B5, Inventory!A:A, Inventory!B:B, "")} -> Chair | D5: 20 | E5: {=_xlfn.XLOOKUP(B5, Inventory!A:A, Inventory!D:D, 0)} -> 4 | F5: =D5*E5 -> 80 | G5: Tulja Bhavani Mandap | J5: =IF(F5-I5=0,"",F5-I5) -> 80 | K5: 20 | L5: =IF(D5-K5,"",D5-K5) -> 0
A6: 46204 | B6: CH | C6: {=_xlfn.XLOOKUP(B6, Inventory!A:A, Inventory!B:B, "")} -> Chair | D6: 70 | E6: {=_xlfn.XLOOKUP(B6, Inventory!A:A, Inventory!D:D, 0)} -> 4 | F6: =D6*E6 -> 280 | G6: Tulja Bhavani Mandap | J6: =IF(F6-I6=0,"",F6-I6) -> 280 | K6: 70 | L6: =IF(D6-K6,"",D6-K6) -> 0
A7: 46204 | B7: TBL | C7: {=_xlfn.XLOOKUP(B7, Inventory!A:A, Inventory!B:B, "")} -> Table | D7: 39 | E7: {=_xlfn.XLOOKUP(B7, Inventory!A:A, Inventory!D:D, 0)} -> 20 | F7: 1000 | G7: CASH | I7: 1000 | J7: =IF(F7-I7=0,"",F7-I7) | K7: 39 | L7: =IF(D7-K7,"",D7-K7) -> 0 | M7: Avinash gaikwad
A8: 46204 | B8: DSH | C8: {=_xlfn.XLOOKUP(B8, Inventory!A:A, Inventory!B:B, "")} -> Dish | D8: 200 | E8: 2 | F8: 540 | G8: CASH | I8: 540 | J8: =IF(F8-I8=0,"",F8-I8) | K8: 200 | L8: =IF(D8-K8,"",D8-K8) -> 0 | M8: Avinash gaikwad
A9: 46206 | B9: CTRNG | C9: {=_xlfn.XLOOKUP(B9, Inventory!A:A, Inventory!B:B, "")} -> CTRNG | D9: 1 | E9: 50 | F9: =D9*E9 -> 50 | G9: CASH | J9: =IF(F9-I9=0,"",F9-I9) -> 50 | K9: 1 | L9: =IF(D9-K9,"",D9-K9) -> 0 | M9: Vijay jadhav
A10: 46206 | B10: HLC | C10: {=_xlfn.XLOOKUP(B10, Inventory!A:A, Inventory!B:B, "")} -> Halad Chair | D10: 1 | E10: {=_xlfn.XLOOKUP(B10, Inventory!A:A, Inventory!D:D, 0)} -> 300 | F10: =D10*E10 -> 300 | G10: Sunil Garandwal | I10: 300 | J10: =IF(F10-I10=0,"",F10-I10) | K10: 1 | L10: =IF(D10-K10,"",D10-K10) -> 0
A11: 46207 | B11: CTRNG | C11: {=_xlfn.XLOOKUP(B11, Inventory!A:A, Inventory!B:B, "")} -> CTRNG | D11: 1 | E11: 330 | F11: =D11*E11 -> 330 | G11: Abhiman Kharat | I11: 100 | J11: =IF(F11-I11=0,"",F11-I11) -> 230 | K11: 1 | L11: =IF(D11-K11,"",D11-K11) -> 0
A12: 46206 | B12: CTRNG | C12: {=_xlfn.XLOOKUP(B12, Inventory!A:A, Inventory!B:B, "")} -> CTRNG | D12: 1 | E12: 450 | F12: =D12*E12 -> 450 | G12: Ganesh Mandap T | J12: =IF(F12-I12=0,"",F12-I12) -> 450 | K12: 1 | L12: =IF(D12-K12,"",D12-K12) -> 0
A13: 46206 | B13: HLC | C13: {=_xlfn.XLOOKUP(B13, Inventory!A:A, Inventory!B:B, "")} -> Halad Chair | D13: 1 | E13: {=_xlfn.XLOOKUP(B13, Inventory!A:A, Inventory!D:D, 0)} -> 300 | F13: =D13*E13 -> 300 | G13: Ganesh Mandap T | J13: =IF(F13-I13=0,"",F13-I13) -> 300 | K13: 1 | L13: =IF(D13-K13,"",D13-K13) -> 0
A14: 46206 | C14: {=_xlfn.XLOOKUP(B14, Inventory!A:A, Inventory!B:B, "")} | E14: {=_xlfn.XLOOKUP(B14, Inventory!A:A, Inventory!D:D, 0)} -> 0 | F14: =D14*E14 -> 0 | G14: Atul Salve | I14: 1000 | J14: =IF(F14-I14=0,"",F14-I14) -> -1000 | L14: =IF(D14-K14,"",D14-K14) -> 0
A15: 46207 | B15: SMI | C15: {=_xlfn.XLOOKUP(B15, Inventory!A:A, Inventory!B:B, "")} -> Samai | D15: 1 | E15: {=_xlfn.XLOOKUP(B15, Inventory!A:A, Inventory!D:D, 0)} -> 300 | F15: =D15*E15 -> 300 | G15: Vishva Mandap | I15: 300 | J15: =IF(F15-I15=0,"",F15-I15) | K15: 1 | L15: =IF(D15-K15,"",D15-K15) -> 0
A16: 46207 | B16: CHCVR | C16: {=_xlfn.XLOOKUP(B16, Inventory!A:A, Inventory!B:B, "")} -> Chair Cover | D16: 10 | E16: {=_xlfn.XLOOKUP(B16, Inventory!A:A, Inventory!D:D, 0)} -> 10 | F16: =D16*E16 -> 100 | G16: Vishva Mandap | I16: 100 | J16: =IF(F16-I16=0,"",F16-I16) | K16: 1 | L16: =IF(D16-K16,"",D16-K16)
A17: 46208 | B17: PLN | C17: {=_xlfn.XLOOKUP(B17, Inventory!A:A, Inventory!B:B, "")} -> Palna | D17: 1 | E17: {=_xlfn.XLOOKUP(B17, Inventory!A:A, Inventory!D:D, 0)} -> 500 | F17: =D17*E17 -> 500 | G17: Ayush Mandap | I17: 0 | J17: =IF(F17-I17=0,"",F17-I17) -> 500 | K17: 1 | L17: =IF(D17-K17,"",D17-K17) -> 0
A18: 46208 | B18: MSF | C18: {=_xlfn.XLOOKUP(B18, Inventory!A:A, Inventory!B:B, "")} -> Maharaja Sofa | D18: 1 | E18: {=_xlfn.XLOOKUP(B18, Inventory!A:A, Inventory!D:D, 0)} -> 700 | F18: =D18*E18 -> 700 | G18: Ayush Mandap | I18: 700 | J18: =IF(F18-I18=0,"",F18-I18) | K18: 1 | L18: =IF(D18-K18,"",D18-K18) -> 0
A19: 46208 | B19: TBL | C19: {=_xlfn.XLOOKUP(B19, Inventory!A:A, Inventory!B:B, "")} -> Table | D19: 15 | E19: {=_xlfn.XLOOKUP(B19, Inventory!A:A, Inventory!D:D, 0)} -> 20 | F19: =D19*E19 -> 300 | G19: Ayush Mandap | I19: 300 | J19: =IF(F19-I19=0,"",F19-I19) | K19: 1 | L19: =IF(D19-K19,"",D19-K19)
A20: 46208 | B20: SHF | C20: {=_xlfn.XLOOKUP(B20, Inventory!A:A, Inventory!B:B, "")} -> Shafing Dish | D20: 5 | E20: {=_xlfn.XLOOKUP(B20, Inventory!A:A, Inventory!D:D, 0)} -> 50 | F20: =D20*E20 -> 250 | G20: Ayush Mandap | I20: 250 | J20: =IF(F20-I20=0,"",F20-I20) | K20: 1 | L20: =IF(D20-K20,"",D20-K20)
A21: 46208 | B21: PLN | C21: {=_xlfn.XLOOKUP(B21, Inventory!A:A, Inventory!B:B, "")} -> Palna | D21: 1 | E21: {=_xlfn.XLOOKUP(B21, Inventory!A:A, Inventory!D:D, 0)} -> 500 | F21: =D21*E21 -> 500 | G21: Ayush Mandap | I21: 500 | J21: =IF(F21-I21=0,"",F21-I21) | K21: 1 | L21: =IF(D21-K21,"",D21-K21) -> 0
A22: 46208 | B22: CTRNG | C22: {=_xlfn.XLOOKUP(B22, Inventory!A:A, Inventory!B:B, "")} -> CTRNG | D22: 1 | E22: 900 | F22: =D22*E22 -> 900 | G22: Yogesh Caterers | J22: =IF(F22-I22=0,"",F22-I22) -> 900 | K22: 1 | L22: =IF(D22-K22,"",D22-K22) -> 0
A23: 46207 | B23: FN | C23: {=_xlfn.XLOOKUP(B23, Inventory!A:A, Inventory!B:B, "")} -> Fan | D23: 4 | E23: 150 | F23: =D23*E23 -> 600 | G23: CASH | I23: 600 | J23: =IF(F23-I23=0,"",F23-I23) | L23: =IF(D23-K23,"",D23-K23) | M23: Ajay Hiwrale
A24: 46204 | B24: GD SET | C24: {=_xlfn.XLOOKUP(B24, Inventory!A:A, Inventory!B:B, "")} -> Gadi Set | D24: 10 | E24: 100 | F24: =D24*E24 -> 1000 | G24: CASH | I24: 1000 | J24: =IF(F24-I24=0,"",F24-I24) | K24: 10 | L24: =IF(D24-K24,"",D24-K24) -> 0
A25: 46204 | B25: RTBL | C25: {=_xlfn.XLOOKUP(B25, Inventory!A:A, Inventory!B:B, "")} -> Round Table | D25: 1 | E25: 200 | F25: =D25*E25 -> 200 | G25: CASH | I25: 200 | J25: =IF(F25-I25=0,"",F25-I25) | K25: 1 | L25: =IF(D25-K25,"",D25-K25) -> 0
A26: 46204 | B26: PRD | C26: {=_xlfn.XLOOKUP(B26, Inventory!A:A, Inventory!B:B, "")} -> Parda | D26: 1 | E26: {=_xlfn.XLOOKUP(B26, Inventory!A:A, Inventory!D:D, 0)} -> 100 | F26: =D26*E26 -> 100 | G26: CASH | I26: 100 | J26: =IF(F26-I26=0,"",F26-I26) | K26: 1 | L26: =IF(D26-K26,"",D26-K26) -> 0
A27: 46207 | B27: DRM | C27: {=_xlfn.XLOOKUP(B27, Inventory!A:A, Inventory!B:B, "")} -> Drum | D27: 1 | E27: {=_xlfn.XLOOKUP(B27, Inventory!A:A, Inventory!D:D, 0)} -> 20 | F27: 120 | G27: CASH | I27: 120 | J27: =IF(F27-I27=0,"",F27-I27) | L27: =IF(D27-K27,"",D27-K27) | M27: Pritam patil
A28: 46208 | B28: CH | C28: {=_xlfn.XLOOKUP(B28, Inventory!A:A, Inventory!B:B, "")} -> Chair | D28: 5 | E28: 10 | F28: =D28*E28 -> 50 | G28: CASH | I28: 50 | J28: =IF(F28-I28=0,"",F28-I28) | K28: 1 | L28: =IF(D28-K28,"",D28-K28)
A29: 46208 | B29: DSH | C29: {=_xlfn.XLOOKUP(B29, Inventory!A:A, Inventory!B:B, "")} -> Dish | D29: 50 | E29: 4 | F29: 250 | G29: CASH | I29: 250 | J29: =IF(F29-I29=0,"",F29-I29) | K29: 1 | L29: =IF(D29-K29,"",D29-K29) | M29: Prem Pandit
A30: 46209 | B30: MT | C30: {=_xlfn.XLOOKUP(B30, Inventory!A:A, Inventory!B:B, "")} -> Matt | D30: 2 | E30: 50 | F30: =D30*E30 -> 100 | G30: CASH | I30: 100 | J30: =IF(F30-I30=0,"",F30-I30) | K30: 1 | L30: =IF(D30-K30,"",D30-K30) | M30: Vijay Dabhade
A31: 46208 | B31: ASN | C31: {=_xlfn.XLOOKUP(B31, Inventory!A:A, Inventory!B:B, "")} -> Asanpatti | D31: 8 | E31: 20 | F31: =D31*E31 -> 160 | G31: CASH | I31: 160 | J31: =IF(F31-I31=0,"",F31-I31) | K31: 1 | L31: =IF(D31-K31,"",D31-K31)
A32: 46209 | B32: CTRNG | C32: {=_xlfn.XLOOKUP(B32, Inventory!A:A, Inventory!B:B, "")} -> CTRNG | D32: 1 | E32: 100 | F32: =D32*E32 -> 100 | G32: CASH | I32: 100 | J32: =IF(F32-I32=0,"",F32-I32) | K32: 1 | L32: =IF(D32-K32,"",D32-K32) -> 0
A33: 46210 | B33: THRMS | C33: {=_xlfn.XLOOKUP(B33, Inventory!A:A, Inventory!B:B, "")} -> Thermos | D33: 1 | E33: {=_xlfn.XLOOKUP(B33, Inventory!A:A, Inventory!D:D, 0)} -> 50 | F33: =D33*E33 -> 50 | G33: CASH | J33: =IF(F33-I33=0,"",F33-I33) -> 50 | K33: 1 | L33: =IF(D33-K33,"",D33-K33) -> 0 | M33: Bhagwat Pawar
A34: 46211 | B34: CH | C34: {=_xlfn.XLOOKUP(B34, Inventory!A:A, Inventory!B:B, "")} -> Chair | D34: 37 | E34: 10 | F34: =D34*E34 -> 370 | G34: CASH | I34: 370 | J34: =IF(F34-I34=0,"",F34-I34) | K34: 37 | L34: =IF(D34-K34,"",D34-K34) -> 0
A35: 46211 | B35: TBL | C35: {=_xlfn.XLOOKUP(B35, Inventory!A:A, Inventory!B:B, "")} -> Table | D35: 9 | E35: {=_xlfn.XLOOKUP(B35, Inventory!A:A, Inventory!D:D, 0)} -> 20 | F35: =D35*E35 -> 180 | G35: CASH | I35: 180 | J35: =IF(F35-I35=0,"",F35-I35) | K35: 9 | L35: =IF(D35-K35,"",D35-K35) -> 0
A36: 46211 | B36: FRL | C36: {=_xlfn.XLOOKUP(B36, Inventory!A:A, Inventory!B:B, "")} -> Freel | D36: 5 | E36: {=_xlfn.XLOOKUP(B36, Inventory!A:A, Inventory!D:D, 0)} -> 30 | F36: =D36*E36 -> 150 | G36: CASH | I36: 150 | J36: =IF(F36-I36=0,"",F36-I36) | K36: 5 | L36: =IF(D36-K36,"",D36-K36) -> 0
A37: 46212 | B37: CTRNG | C37: {=_xlfn.XLOOKUP(B37, Inventory!A:A, Inventory!B:B, "")} -> CTRNG | D37: 1 | E37: 275 | F37: =D37*E37 -> 275 | G37: CASH | I37: 275 | J37: =IF(F37-I37=0,"",F37-I37) | K37: 1 | L37: =IF(D37-K37,"",D37-K37) -> 0
A38: 46212 | B38: CH | C38: {=_xlfn.XLOOKUP(B38, Inventory!A:A, Inventory!B:B, "")} -> Chair | D38: 4 | E38: 10 | F38: =D38*E38 -> 40 | G38: CASH | I38: 40 | J38: =IF(F38-I38=0,"",F38-I38) | K38: 4 | L38: =IF(D38-K38,"",D38-K38) -> 0
A39: 46212 | B39: ASN | C39: {=_xlfn.XLOOKUP(B39, Inventory!A:A, Inventory!B:B, "")} -> Asanpatti | D39: 8 | E39: {=_xlfn.XLOOKUP(B39, Inventory!A:A, Inventory!D:D, 0)} -> 10 | F39: =D39*E39 -> 80 | G39: CASH | I39: 80 | J39: =IF(F39-I39=0,"",F39-I39) | K39: 8 | L39: =IF(D39-K39,"",D39-K39) -> 0
A40: 46213 | B40: AB | C40: {=_xlfn.XLOOKUP(B40, Inventory!A:A, Inventory!B:B, "")} -> Ahuja Speaker | D40: 1 | E40: {=_xlfn.XLOOKUP(B40, Inventory!A:A, Inventory!D:D, 0)} -> 500 | F40: =D40*E40 -> 500 | G40: CASH | J40: =IF(F40-I40=0,"",F40-I40) -> 500 | K40: 1 | L40: =IF(D40-K40,"",D40-K40) -> 0
A41: 46213 | B41: CTRNG | C41: {=_xlfn.XLOOKUP(B41, Inventory!A:A, Inventory!B:B, "")} -> CTRNG | D41: 1 | E41: 100 | F41: =D41*E41 -> 100 | G41: CASH | J41: =IF(F41-I41=0,"",F41-I41) -> 100 | L41: =IF(D41-K41,"",D41-K41) | M41: Prem Jangale
A42: 46213 | B42: CTRNG | C42: {=_xlfn.XLOOKUP(B42, Inventory!A:A, Inventory!B:B, "")} -> CTRNG | D42: 1 | E42: 100 | F42: =D42*E42 -> 100 | G42: CASH | J42: =IF(F42-I42=0,"",F42-I42) -> 100 | L42: =IF(D42-K42,"",D42-K42)
A43: 46213 | B43: SMI | C43: {=_xlfn.XLOOKUP(B43, Inventory!A:A, Inventory!B:B, "")} -> Samai | D43: 1 | E43: {=_xlfn.XLOOKUP(B43, Inventory!A:A, Inventory!D:D, 0)} -> 300 | F43: =D43*E43 -> 300 | G43: CASH | J43: =IF(F43-I43=0,"",F43-I43) -> 300 | L43: =IF(D43-K43,"",D43-K43) | M43: Indriya Jewellers
A44: 46208 | B44: SF | C44: {=_xlfn.XLOOKUP(B44, Inventory!A:A, Inventory!B:B, "")} -> Sofa | D44: 2 | E44: {=_xlfn.XLOOKUP(B44, Inventory!A:A, Inventory!D:D, 0)} -> 150 | F44: =D44*E44 -> 300 | G44: Shri Decorators | I44: 300 | J44: =IF(F44-I44=0,"",F44-I44) | K44: 1 | L44: =IF(D44-K44,"",D44-K44)
A45: 46209 | B45: CTRNG | C45: {=_xlfn.XLOOKUP(B45, Inventory!A:A, Inventory!B:B, "")} -> CTRNG | D45: 1 | E45: 50 | F45: =D45*E45 -> 50 | G45: Nagve Patil Caterers | I45: 50 | J45: =IF(F45-I45=0,"",F45-I45) | K45: 1 | L45: =IF(D45-K45,"",D45-K45) -> 0
A46: 46210 | B46: SF | C46: {=_xlfn.XLOOKUP(B46, Inventory!A:A, Inventory!B:B, "")} -> Sofa | D46: 1 | E46: {=_xlfn.XLOOKUP(B46, Inventory!A:A, Inventory!D:D, 0)} -> 150 | F46: =D46*E46 -> 150 | G46: Dip Mandap | I46: 150 | J46: =IF(F46-I46=0,"",F46-I46) | K46: 1 | L46: =IF(D46-K46,"",D46-K46) -> 0
A47: 46210 | B47: CTRNG | C47: {=_xlfn.XLOOKUP(B47, Inventory!A:A, Inventory!B:B, "")} -> CTRNG | D47: 3 | E47: 50 | F47: =D47*E47 -> 150 | G47: Dip Mandap | I47: 150 | J47: =IF(F47-I47=0,"",F47-I47) | K47: 1 | L47: =IF(D47-K47,"",D47-K47) | M47: Sofa Cover
A48: 46210 | B48: THRMS | C48: {=_xlfn.XLOOKUP(B48, Inventory!A:A, Inventory!B:B, "")} -> Thermos | D48: 1 | E48: {=_xlfn.XLOOKUP(B48, Inventory!A:A, Inventory!D:D, 0)} -> 50 | F48: =D48*E48 -> 50 | G48: Dip Mandap | I48: 50 | J48: =IF(F48-I48=0,"",F48-I48) | K48: 1 | L48: =IF(D48-K48,"",D48-K48) -> 0
A49: 46210 | B49: CH | C49: {=_xlfn.XLOOKUP(B49, Inventory!A:A, Inventory!B:B, "")} -> Chair | D49: 30 | E49: {=_xlfn.XLOOKUP(B49, Inventory!A:A, Inventory!D:D, 0)} -> 4 | F49: =D49*E49 -> 120 | G49: Mahalakshmi Mandap | I49: 120 | J49: =IF(F49-I49=0,"",F49-I49) | K49: 1 | L49: =IF(D49-K49,"",D49-K49)
A50: 46210 | B50: TBL | C50: {=_xlfn.XLOOKUP(B50, Inventory!A:A, Inventory!B:B, "")} -> Table | D50: 1 | E50: {=_xlfn.XLOOKUP(B50, Inventory!A:A, Inventory!D:D, 0)} -> 20 | F50: =D50*E50 -> 20 | G50: Mahalakshmi Mandap | I50: 20 | J50: =IF(F50-I50=0,"",F50-I50) | K50: 1 | L50: =IF(D50-K50,"",D50-K50) -> 0
A51: 46210 | B51: GD SET | C51: {=_xlfn.XLOOKUP(B51, Inventory!A:A, Inventory!B:B, "")} -> Gadi Set | D51: 1 | E51: 6000 | F51: =D51*E51 -> 6000 | G51: Rajdhani Mandap | I51: 4000 | J51: =IF(F51-I51=0,"",F51-I51) -> 2000 | L51: =IF(D51-K51,"",D51-K51)
A52: 46210 | B52: GD | C52: {=_xlfn.XLOOKUP(B52, Inventory!A:A, Inventory!B:B, "")} -> Gadi | D52: 20 | E52: {=_xlfn.XLOOKUP(B52, Inventory!A:A, Inventory!D:D, 0)} -> 15 | F52: =D52*E52 -> 300 | G52: Sunil Garandwal | I52: 300 | J52: =IF(F52-I52=0,"",F52-I52) | K52: 1 | L52: =IF(D52-K52,"",D52-K52)
A53: 46210 | B53: CH | C53: {=_xlfn.XLOOKUP(B53, Inventory!A:A, Inventory!B:B, "")} -> Chair | D53: 20 | E53: {=_xlfn.XLOOKUP(B53, Inventory!A:A, Inventory!D:D, 0)} -> 4 | F53: =D53*E53 -> 80 | G53: Sunil Garandwal | I53: 80 | J53: =IF(F53-I53=0,"",F53-I53) | K53: 1 | L53: =IF(D53-K53,"",D53-K53)
A54: 46211 | B54: CTRNG | C54: {=_xlfn.XLOOKUP(B54, Inventory!A:A, Inventory!B:B, "")} -> CTRNG | D54: 1 | E54: 600 | F54: =D54*E54 -> 600 | G54: Pruthviraj Mandap | I54: 600 | J54: =IF(F54-I54=0,"",F54-I54) | K54: 1 | L54: =IF(D54-K54,"",D54-K54) -> 0
A55: 46210 | C55: {=_xlfn.XLOOKUP(B55, Inventory!A:A, Inventory!B:B, "")} | E55: {=_xlfn.XLOOKUP(B55, Inventory!A:A, Inventory!D:D, 0)} -> 0 | F55: =D55*E55 -> 0 | J55: =IF(F55-I55=0,"",F55-I55) | L55: =IF(D55-K55,"",D55-K55) -> 0
A56: 46210 | C56: {=_xlfn.XLOOKUP(B56, Inventory!A:A, Inventory!B:B, "")} | E56: {=_xlfn.XLOOKUP(B56, Inventory!A:A, Inventory!D:D, 0)} -> 0 | F56: =D56*E56 -> 0 | J56: =IF(F56-I56=0,"",F56-I56) | L56: =IF(D56-K56,"",D56-K56) -> 0
A57: 46210 | C57: {=_xlfn.XLOOKUP(B57, Inventory!A:A, Inventory!B:B, "")} | E57: {=_xlfn.XLOOKUP(B57, Inventory!A:A, Inventory!D:D, 0)} -> 0 | F57: =D57*E57 -> 0 | J57: =IF(F57-I57=0,"",F57-I57) | L57: =IF(D57-K57,"",D57-K57) -> 0
A58: 46210 | C58: {=_xlfn.XLOOKUP(B58, Inventory!A:A, Inventory!B:B, "")} | E58: {=_xlfn.XLOOKUP(B58, Inventory!A:A, Inventory!D:D, 0)} -> 0 | F58: =D58*E58 -> 0 | J58: =IF(F58-I58=0,"",F58-I58)
C59: {=_xlfn.XLOOKUP(B59, Inventory!A:A, Inventory!B:B, "")} | E59: {=_xlfn.XLOOKUP(B59, Inventory!A:A, Inventory!D:D, 0)} -> 0 | F59: =D59*E59 -> 0 | J59: =IF(F59-I59=0,"",F59-I59)
C60: {=_xlfn.XLOOKUP(B60, Inventory!A:A, Inventory!B:B, "")} | E60: {=_xlfn.XLOOKUP(B60, Inventory!A:A, Inventory!D:D, 0)} -> 0 | F60: =D60*E60 -> 0 | J60: =IF(F60-I60=0,"",F60-I60)
C61: {=_xlfn.XLOOKUP(B61, Inventory!A:A, Inventory!B:B, "")} | E61: {=_xlfn.XLOOKUP(B61, Inventory!A:A, Inventory!D:D, 0)} -> 0 | F61: =D61*E61 -> 0 | J61: =IF(F61-I61=0,"",F61-I61)
C62: {=_xlfn.XLOOKUP(B62, Inventory!A:A, Inventory!B:B, "")} | F62: =D62*E62 -> 0 | J62: =IF(F62-I62=0,"",F62-I62)
C63: {=_xlfn.XLOOKUP(B63, Inventory!A:A, Inventory!B:B, "")} | F63: =D63*E63 -> 0 | J63: =IF(F63-I63=0,"",F63-I63)
C64: {=_xlfn.XLOOKUP(B64, Inventory!A:A, Inventory!B:B, "")} | J64: =IF(F64-I64=0,"",F64-I64)
C65: {=_xlfn.XLOOKUP(B65, Inventory!A:A, Inventory!B:B, "")} | J65: =IF(F65-I65=0,"",F65-I65)
C66: {=_xlfn.XLOOKUP(B66, Inventory!A:A, Inventory!B:B, "")} | J66: =IF(F66-I66=0,"",F66-I66)
J67: =IF(F67-I67=0,"",F67-I67)
N161: Gautam bagul
C251: {=IFERROR(_xlfn.XLOOKUP(B251, Inventory!A:A, Inventory!B:B),"")} | J251: =IF(F251-I251=0,"",F251-I251) | L251: =IF(D251-K251=0,"",D251-K251)
C252: {=IFERROR(_xlfn.XLOOKUP(B252, Inventory!A:A, Inventory!B:B),"")} | J252: =IF(F252-I252=0,"",F252-I252) | L252: =IF(D252-K252=0,"",D252-K252)
C253: {=IFERROR(_xlfn.XLOOKUP(B253, Inventory!A:A, Inventory!B:B),"")} | J253: =IF(F253-I253=0,"",F253-I253) | L253: =IF(D253-K253=0,"",D253-K253)
C254: {=IFERROR(_xlfn.XLOOKUP(B254, Inventory!A:A, Inventory!B:B),"")} | J254: =IF(F254-I254=0,"",F254-I254) | L254: =IF(D254-K254=0,"",D254-K254)
C255: {=IFERROR(_xlfn.XLOOKUP(B255, Inventory!A:A, Inventory!B:B),"")} | J255: =IF(F255-I255=0,"",F255-I255) | L255: =IF(D255-K255=0,"",D255-K255)
C256: {=IFERROR(_xlfn.XLOOKUP(B256, Inventory!A:A, Inventory!B:B),"")} | J256: =IF(F256-I256=0,"",F256-I256) | L256: =IF(D256-K256=0,"",D256-K256)
C257: {=IFERROR(_xlfn.XLOOKUP(B257, Inventory!A:A, Inventory!B:B),"")} | J257: =IF(F257-I257=0,"",F257-I257) | L257: =IF(D257-K257=0,"",D257-K257)
C258: {=IFERROR(_xlfn.XLOOKUP(B258, Inventory!A:A, Inventory!B:B),"")} | L258: =IF(D258-K258=0,"",D258-K258)
C259: {=IFERROR(_xlfn.XLOOKUP(B259, Inventory!A:A, Inventory!B:B),"")} | L259: =IF(D259-K259=0,"",D259-K259)
C260: {=IFERROR(_xlfn.XLOOKUP(B260, Inventory!A:A, Inventory!B:B),"")} | L260: =IF(D260-K260=0,"",D260-K260)
C261: {=IFERROR(_xlfn.XLOOKUP(B261, Inventory!A:A, Inventory!B:B),"")} | L261: =IF(D261-K261=0,"",D261-K261)
C262: {=IFERROR(_xlfn.XLOOKUP(B262, Inventory!A:A, Inventory!B:B),"")} | L262: =IF(D262-K262=0,"",D262-K262)
C263: {=IFERROR(_xlfn.XLOOKUP(B263, Inventory!A:A, Inventory!B:B),"")} | L263: =IF(D263-K263=0,"",D263-K263)
C264: {=IFERROR(_xlfn.XLOOKUP(B264, Inventory!A:A, Inventory!B:B),"")} | L264: =IF(D264-K264=0,"",D264-K264)
C265: {=IFERROR(_xlfn.XLOOKUP(B265, Inventory!A:A, Inventory!B:B),"")} | L265: =IF(D265-K265=0,"",D265-K265)
C266: {=IFERROR(_xlfn.XLOOKUP(B266, Inventory!A:A, Inventory!B:B),"")} | L266: =IF(D266-K266=0,"",D266-K266)
C267: {=IFERROR(_xlfn.XLOOKUP(B267, Inventory!A:A, Inventory!B:B),"")} | L267: =IF(D267-K267=0,"",D267-K267)
C268: {=IFERROR(_xlfn.XLOOKUP(B268, Inventory!A:A, Inventory!B:B),"")} | L268: =IF(D268-K268=0,"",D268-K268)
C269: {=IFERROR(_xlfn.XLOOKUP(B269, Inventory!A:A, Inventory!B:B),"")} | L269: =IF(D269-K269=0,"",D269-K269)
C270: {=IFERROR(_xlfn.XLOOKUP(B270, Inventory!A:A, Inventory!B:B),"")} | L270: =IF(D270-K270=0,"",D270-K270)
L271: =IF(D271-K271=0,"",D271-K271)
L272: =IF(D272-K272=0,"",D272-K272)
L273: =IF(D273-K273=0,"",D273-K273)
L274: =IF(D274-K274=0,"",D274-K274)
L275: =IF(D275-K275=0,"",D275-K275)
L276: =IF(D276-K276=0,"",D276-K276)
L277: =IF(D277-K277=0,"",D277-K277)
L278: =IF(D278-K278=0,"",D278-K278)
L279: =IF(D279-K279=0,"",D279-K279)
L280: =IF(D280-K280=0,"",D280-K280)
L281: =IF(D281-K281=0,"",D281-K281)
L282: =IF(D282-K282=0,"",D282-K282)
...

Sheet Dashboard
B3: TOTAL REVENUE | D3: =M3 -> 16235 | F3: MINIMUM STOCK | H3: =SUMPRODUCT((Inventory!G2:G100<=Inventory!H2:H100)*(Inventory!A2:A100<>"")) -> 55 | J3: =IFERROR(__xludf.DUMMYFUNCTION("FILTER(Inventory!B2:B9, Inventory!G2:G9 <= Inventory!H2:H9)"),"Opening Balance") -> Opening Balance | L3: Date | M3: =sum(M4:M33) -> 16235
J4: =IFERROR(__xludf.DUMMYFUNCTION("""COMPUTED_VALUE"""),"CTRNG") -> CTRNG | L4: 46204 | M4: =SUMIF(Sales!A:A,L4,Sales!I:I) -> 4390
B5: GROSS REVENUE | D5: =SUM(Sales!F:F) -> 21325 | J5: =IFERROR(__xludf.DUMMYFUNCTION("""COMPUTED_VALUE"""),"Jumbo Cooler") -> Jumbo Cooler | L5: 46205 | M5: =SUMIF(Sales!A:A,L5,Sales!I:I) -> 0
J6: =IFERROR(__xludf.DUMMYFUNCTION("""COMPUTED_VALUE"""),"Chair ") -> Chair | L6: 46206 | M6: =SUMIF(Sales!A:A,L6,Sales!I:I) -> 1300
B7: PENDING PAYMENT | D7: =D3-D5 -> -5090 | J7: =IFERROR(__xludf.DUMMYFUNCTION("""COMPUTED_VALUE"""),"Round Table ") -> Round Table | L7: 46207 | M7: =SUMIF(Sales!A:A,L7,Sales!I:I) -> 1220
J8: =IFERROR(__xludf.DUMMYFUNCTION("""COMPUTED_VALUE"""),"Fan") -> Fan | L8: 46208 | M8: =SUMIF(Sales!A:A,L8,Sales!I:I) -> 2510
J9: =IFERROR(__xludf.DUMMYFUNCTION("""COMPUTED_VALUE"""),"Gadi ") -> Gadi | L9: 46209 | M9: =SUMIF(Sales!A:A,L9,Sales!I:I) -> 250
B10: PAYMENT BALANCE | D10: =SUM(Sales!J:J) -> 5090 | J10: =IFERROR(__xludf.DUMMYFUNCTION("""COMPUTED_VALUE"""),"Drum") -> Drum | L10: 46210 | M10: =SUMIF(Sales!A:A,L10,Sales!I:I) -> 4870
L11: 46211 | M11: =SUMIF(Sales!A:A,L11,Sales!I:I) -> 1300
B12: PREV MONTH BALANCE | D12: =D5-D3 -> 5090 | L12: 46212 | M12: =SUMIF(Sales!A:A,L12,Sales!I:I) -> 395
L13: 46213 | M13: =SUMIF(Sales!A:A,L13,Sales!I:I) -> 0
L14: 46214 | M14: =SUMIF(Sales!A:A,L14,Sales!I:I) -> 0
L15: 46215 | M15: =SUMIF(Sales!A:A,L15,Sales!I:I) -> 0
L16: 46216 | M16: =SUMIF(Sales!A:A,L16,Sales!I:I) -> 0
L17: 46217 | M17: =SUMIF(Sales!A:A,L17,Sales!I:I) -> 0
L18: 46218 | M18: =SUMIF(Sales!A:A,L18,Sales!I:I) -> 0
L19: 46219 | M19: =SUMIF(Sales!A:A,L19,Sales!I:I) -> 0
L20: 46220 | M20: =SUMIF(Sales!A:A,L20,Sales!I:I) -> 0
L21: 46221 | M21: =SUMIF(Sales!A:A,L21,Sales!I:I) -> 0
L22: 46222 | M22: =SUMIF(Sales!A:A,L22,Sales!I:I) -> 0
L23: 46223 | M23: =SUMIF(Sales!A:A,L23,Sales!I:I) -> 0
L24: 46224 | M24: =SUMIF(Sales!A:A,L24,Sales!I:I) -> 0
... L33: 46233 | M33: =SUMIF(Sales!A:A,L33,Sales!I:I) -> 0

Sheet ST Cust
C7: STATEMENT
G10: Date :
C12: Select Name : | E12: Yogesh Caterers | J12: Total | K12: =SUM(K15:K100) -> 600 | L12: =SUM(L15:L100)-K12 -> 550
C14: DATE | D14: ITEM ID | E14: ITEM NAME | F14: QTY | G14: PRICE | H14: TOTAL | I14: NAME | J14: PAY METHOD | K14: PAY RECIEVED | L14: PAY BALANCE | M14: RETURN QTY | N14: BALANCE QTY | O14: NARRATION | P14: Cumm. Add
C15: =IFERROR(__xludf.DUMMYFUNCTION("FILTER(Sales!A:M, Sales!G:G = E12)"),46204.0) -> 46204 | D15: =IFERROR(__xludf.DUMMYFUNCTION("""COMPUTED_VALUE"""),"CTRNG") -> CTRNG | E15: =IFERROR(__xludf.DUMMYFUNCTION("""COMPUTED_VALUE"""),"CTRNG") -> CTRNG | F15: =IFERROR(__xludf.DUMMYFUNCTION("""COMPUTED_VALUE"""),1.0) -> 1 | G15: =IFERROR(__xludf.DUMMYFUNCTION("""COMPUTED_VALUE"""),850.0) -> 850 | H15: =IFERROR(__xludf.DUMMYFUNCTION("""COMPUTED_VALUE"""),850.0) -> 850 | I15: =IFERROR(__xludf.DUMMYFUNCTION("""COMPUTED_VALUE"""),"Yogesh Caterers") -> Yogesh Caterers | K15: =IFERROR(__xludf.DUMMYFUNCTION("""COMPUTED_VALUE"""),600.0) -> 600 | L15: =IFERROR(__xludf.DUMMYFUNCTION("""COMPUTED_VALUE"""),250.0) -> 250 | M15: =IFERROR(__xludf.DUMMYFUNCTION("""COMPUTED_VALUE"""),1.0) -> 1 | N15: =IFERROR(__xludf.DUMMYFUNCTION("""COMPUTED_VALUE"""),0.0) -> 0 | P15: =L15 -> 250
C16: =IFERROR(__xludf.DUMMYFUNCTION("""COMPUTED_VALUE"""),46208.0) -> 46208 | D16: =IFERROR(__xludf.DUMMYFUNCTION("""COMPUTED_VALUE"""),"CTRNG") -> CTRNG | E16: =IFERROR(__xludf.DUMMYFUNCTION("""COMPUTED_VALUE"""),"CTRNG") -> CTRNG | F16: =IFERROR(__xludf.DUMMYFUNCTION("""COMPUTED_VALUE"""),1.0) -> 1 | G16: =IFERROR(__xludf.DUMMYFUNCTION("""COMPUTED_VALUE"""),900.0) -> 900 | H16: =IFERROR(__xludf.DUMMYFUNCTION("""COMPUTED_VALUE"""),900.0) -> 900 | I16: =IFERROR(__xludf.DUMMYFUNCTION("""COMPUTED_VALUE"""),"Yogesh Caterers") -> Yogesh Caterers | L16: =IFERROR(__xludf.DUMMYFUNCTION("""COMPUTED_VALUE"""),900.0) -> 900 | M16: =IFERROR(__xludf.DUMMYFUNCTION("""COMPUTED_VALUE"""),1.0) -> 1 | N16: =IFERROR(__xludf.DUMMYFUNCTION("""COMPUTED_VALUE"""),0.0) -> 0 | P16: =P15+L16 -> 1150
P17: =P16+L17 -> 1150
P18: =P17+L18 -> 1150
P19: =P18+L19 -> 1150
P20: =P19+L20 -> 1150
P21: =P20+L21 -> 1150
P22: =P21+L22 -> 1150
P23: =P22+L23 -> 1150

Sheet ST INV
C7: STATEMENT
G10: Date :
C12: Select Name : | E12: Jumbo Cooler | J12: Total | K12: =SUM(K15:K100) -> 0 | L12: =SUM(L15:L100) -> 0
C14: DATE | D14: ITEM ID | E14: ITEM NAME | F14: QTY | G14: PRICE | H14: TOTAL | I14: NAME | J14: PAY METHOD | K14: PAY RECIEVED | L14: PAY BALANCE | M14: RETURN QTY | N14: BALANCE QTY | O14: NARRATION
C15: =IFERROR(__xludf.DUMMYFUNCTION("FILTER(Sales!A:M, Sales!C:C = E12)"),"#N/A") -> #N/A

Sheet INV BAL
G2: INVENTORY BALANCE
A5: =IFERROR(__xludf.DUMMYFUNCTION("QUERY(Sales!A:M,""SELECT * WHERE Col12 IS NOT NULL"",1)"),"DATE") -> DATE | B5: =IFERROR(__xludf.DUMMYFUNCTION("""COMPUTED_VALUE"""),"ITEM ID") -> ITEM ID | C5: =IFERROR(__xludf.DUMMYFUNCTION("""COMPUTED_VALUE"""),"ITEM NAME") -> ITEM NAME | D5: =IFERROR(__xludf.DUMMYFUNCTION("""COMPUTED_VALUE"""),"QUANTITY") -> QUANTITY | E5: =IFERROR(__xludf.DUMMYFUNCTION("""COMPUTED_VALUE"""),"PRICE") -> PRICE | F5: =IFERROR(__xludf.DUMMYFUNCTION("""COMPUTED_VALUE"""),"TOTAL") -> TOTAL | G5: =IFERROR(__xludf.DUMMYFUNCTION("""COMPUTED_VALUE"""),"CUSTOMER NAME") -> CUSTOMER NAME | H5: =IFERROR(__xludf.DUMMYFUNCTION("""COMPUTED_VALUE"""),"PAYMENT METHOD ") -> PAYMENT METHOD | I5: =IFERROR(__xludf.DUMMYFUNCTION("""COMPUTED_VALUE"""),"PAYMENT RECEIVED ") -> PAYMENT RECEIVED | J5: =IFERROR(__xludf.DUMMYFUNCTION("""COMPUTED_VALUE"""),"PAYMENT BALANCE ") -> PAYMENT BALANCE | K5: =IFERROR(__xludf.DUMMYFUNCTION("""COMPUTED_VALUE"""),"RETURN QUANTITY ") -> RETURN QUANTITY | L5: =IFERROR(__xludf.DUMMYFUNCTION("""COMPUTED_VALUE"""),"BALANCE QUANTITY") -> BALANCE QUANTITY | M5: =IFERROR(__xludf.DUMMYFUNCTION("""COMPUTED_VALUE"""),"Narration") -> Narration
A6: =IFERROR(__xludf.DUMMYFUNCTION("""COMPUTED_VALUE"""),46204.0) -> 46204 | B6: =IFERROR(__xludf.DUMMYFUNCTION("""COMPUTED_VALUE"""),"CTRNG") -> CTRNG | C6: =IFERROR(__xludf.DUMMYFUNCTION("""COMPUTED_VALUE"""),"CTRNG") -> CTRNG | D6: =IFERROR(__xludf.DUMMYFUNCTION("""COMPUTED_VALUE"""),1.0) -> 1 | E6: =IFERROR(__xludf.DUMMYFUNCTION("""COMPUTED_VALUE"""),850.0) -> 850 | F6: =IFERROR(__xludf.DUMMYFUNCTION("""COMPUTED_VALUE"""),850.0) -> 850 | G6: =IFERROR(__xludf.DUMMYFUNCTION("""COMPUTED_VALUE"""),"Yogesh Caterers") -> Yogesh Caterers | I6: =IFERROR(__xludf.DUMMYFUNCTION("""COMPUTED_VALUE"""),600.0) -> 600 | J6: =IFERROR(__xludf.DUMMYFUNCTION("""COMPUTED_VALUE"""),250.0) -> 250 | K6: =IFERROR(__xludf.DUMMYFUNCTION("""COMPUTED_VALUE"""),1.0) -> 1 | L6: =IFERROR(__xludf.DUMMYFUNCTION("""COMPUTED_VALUE"""),0.0) -> 0
A7: =IFERROR(__xludf.DUMMYFUNCTION("""COMPUTED_VALUE"""),46204.0) -> 46204 | B7: =IFERROR(__xludf.DUMMYFUNCTION("""COMPUTED_VALUE"""),"GD") -> GD | C7: =IFERROR(__xludf.DUMMYFUNCTION("""COMPUTED_VALUE"""),"Gadi ") -> Gadi | D7: =IFERROR(__xludf.DUMMYFUNCTION("""COMPUTED_VALUE"""),10.0) -> 10 | E7: =IFERROR(__xludf.DUMMYFUNCTION("""COMPUTED_VALUE"""),15.0) -> 15 | F7: =IFERROR(__xludf.DUMMYFUNCTION("""COMPUTED_VALUE"""),150.0) -> 150 | G7: =IFERROR(__xludf.DUMMYFUNCTION("""COMPUTED_VALUE"""),"Samarth Sound") -> Samarth Sound | I7: =IFERROR(__xludf.DUMMYFUNCTION("""COMPUTED_VALUE"""),150.0) -> 150 | K7: =IFERROR(__xludf.DUMMYFUNCTION("""COMPUTED_VALUE"""),10.0) -> 10 | L7: =IFERROR(__xludf.DUMMYFUNCTION("""COMPUTED_VALUE"""),0.0) -> 0
A8: =IFERROR(__xludf.DUMMYFUNCTION("""COMPUTED_VALUE"""),46204.0) -> 46204 | B8: =IFERROR(__xludf.DUMMYFUNCTION("""COMPUTED_VALUE"""),"AAH") -> AAH | C8: =IFERROR(__xludf.DUMMYFUNCTION("""COMPUTED_VALUE"""),"Amp Ahuja ") -> Amp Ahuja | D8: =IFERROR(__xludf.DUMMYFUNCTION("""COMPUTED_VALUE"""),1.0) -> 1 | E8: =IFERROR(__xludf.DUMMYFUNCTION("""COMPUTED_VALUE"""),800.0) -> 800 | F8: =IFERROR(__xludf.DUMMYFUNCTION("""COMPUTED_VALUE"""),800.0) -> 800 | G8: =IFERROR(__xludf.DUMMYFUNCTION("""COMPUTED_VALUE"""),"Samarth Sound") -> Samarth Sound | I8: =IFERROR(__xludf.DUMMYFUNCTION("""COMPUTED_VALUE"""),800.0) -> 800 | K8: =IFERROR(__xludf.DUMMYFUNCTION("""COMPUTED_VALUE"""),1.0) -> 1 | L8: =IFERROR(__xludf.DUMMYFUNCTION("""COMPUTED_VALUE"""),0.0) -> 0
A9: =IFERROR(__xludf.DUMMYFUNCTION("""COMPUTED_VALUE"""),46204.0) -> 46204 | B9: =IFERROR(__xludf.DUMMYFUNCTION("""COMPUTED_VALUE"""),"CH") -> CH | C9: =IFERROR(__xludf.DUMMYFUNCTION("""COMPUTED_VALUE"""),"Chair ") -> Chair | D9: =IFERROR(__xludf.DUMMYFUNCTION("""COMPUTED_VALUE"""),20.0) -> 20 | E9: =IFERROR(__xludf.DUMMYFUNCTION("""COMPUTED_VALUE"""),4.0) -> 4 | F9: =IFERROR(__xludf.DUMMYFUNCTION("""COMPUTED_VALUE"""),80.0) -> 80 | G9: =IFERROR(__xludf.DUMMYFUNCTION("""COMPUTED_VALUE"""),"Tulja Bhavani Mandap") -> Tulja Bhavani Mandap | J9: =IFERROR(__xludf.DUMMYFUNCTION("""COMPUTED_VALUE"""),80.0) -> 80 | K9: =IFERROR(__xludf.DUMMYFUNCTION("""COMPUTED_VALUE"""),20.0) -> 20 | L9: =IFERROR(__xludf.DUMMYFUNCTION("""COMPUTED_VALUE"""),0.0) -> 0
A10: =IFERROR(__xludf.DUMMYFUNCTION("""COMPUTED_VALUE"""),46204.0) -> 46204 | B10: =IFERROR(__xludf.DUMMYFUNCTION("""COMPUTED_VALUE"""),"CH") -> CH | C10: =IFERROR(__xludf.DUMMYFUNCTION("""COMPUTED_VALUE"""),"Chair ") -> Chair | D10: =IFERROR(__xludf.DUMMYFUNCTION("""COMPUTED_VALUE"""),70.0) -> 70 | E10: =IFERROR(__xludf.DUMMYFUNCTION("""COMPUTED_VALUE"""),4.0) -> 4 | F10: =IFERROR(__xludf.DUMMYFUNCTION("""COMPUTED_VALUE"""),280.0) -> 280 | G10: =IFERROR(__xludf.DUMMYFUNCTION("""COMPUTED_VALUE"""),"Tulja Bhavani Mandap") -> Tulja Bhavani Mandap | J10: =IFERROR(__xludf.DUMMYFUNCTION("""COMPUTED_VALUE"""),280.0) -> 280 | K10: =IFERROR(__xludf.DUMMYFUNCTION("""COMPUTED_VALUE"""),70.0) -> 70 | L10: =IFERROR(__xludf.DUMMYFUNCTION("""COMPUTED_VALUE"""),0.0) -> 0
A11: =IFERROR(__xludf.DUMMYFUNCTION("""COMPUTED_VALUE"""),46204.0) -> 46204 | B11: =IFERROR(__xludf.DUMMYFUNCTION("""COMPUTED_VALUE"""),"TBL") -> TBL | C11: =IFERROR(__xludf.DUMMYFUNCTION("""COMPUTED_VALUE"""),"Table") -> Table | D11: =IFERROR(__xludf.DUMMYFUNCTION("""COMPUTED_VALUE"""),39.0) -> 39 | E11: =IFERROR(__xludf.DUMMYFUNCTION("""COMPUTED_VALUE"""),20.0) -> 20 | F11: =IFERROR(__xludf.DUMMYFUNCTION("""COMPUTED_VALUE"""),1000.0) -> 1000 | G11: =IFERROR(__xludf.DUMMYFUNCTION("""COMPUTED_VALUE"""),"CASH") -> CASH | I11: =IFERROR(__xludf.DUMMYFUNCTION("""COMPUTED_VALUE"""),1000.0) -> 1000 | K11: =IFERROR(__xludf.DUMMYFUNCTION("""COMPUTED_VALUE"""),39.0) -> 39 | L11: =IFERROR(__xludf.DUMMYFUNCTION("""COMPUTED_VALUE"""),0.0) -> 0 | M11: =IFERROR(__xludf.DUMMYFUNCTION("""COMPUTED_VALUE"""),"Avinash gaikwad") -> Avinash gaikwad
A12: =IFERROR(__xludf.DUMMYFUNCTION("""COMPUTED_VALUE"""),46204.0) -> 46204 | B12: =IFERROR(__xludf.DUMMYFUNCTION("""COMPUTED_VALUE"""),"DSH") -> DSH | C12: =IFERROR(__xludf.DUMMYFUNCTION("""COMPUTED_VALUE"""),"Dish") -> Dish | D12: =IFERROR(__xludf.DUMMYFUNCTION("""COMPUTED_VALUE"""),200.0) -> 200 | E12: =IFERROR(__xludf.DUMMYFUNCTION("""COMPUTED_VALUE"""),2.0) -> 2 | F12: =IFERROR(__xludf.DUMMYFUNCTION("""COMPUTED_VALUE"""),540.0) -> 540 | G12: =IFERROR(__xludf.DUMMYFUNCTION("""COMPUTED_VALUE"""),"CASH") -> CASH | I12: =IFERROR(__xludf.DUMMYFUNCTION("""COMPUTED_VALUE"""),540.0) -> 540 | K12: =IFERROR(__xludf.DUMMYFUNCTION("""COMPUTED_VALUE"""),200.0) -> 200 | L12: =IFERROR(__xludf.DUMMYFUNCTION("""COMPUTED_VALUE"""),0.0) -> 0 | M12: =IFERROR(__xludf.DUMMYFUNCTION("""COMPUTED_VALUE"""),"Avinash gaikwad") -> Avinash gaikwad
A13: =IFERROR(__xludf.DUMMYFUNCTION("""COMPUTED_VALUE"""),46206.0) -> 46206 | B13: =IFERROR(__xludf.DUMMYFUNCTION("""COMPUTED_VALUE"""),"CTRNG") -> CTRNG | C13: =IFERROR(__xludf.DUMMYFUNCTION("""COMPUTED_VALUE"""),"CTRNG") -> CTRNG | D13: =IFERROR(__xludf.DUMMYFUNCTION("""COMPUTED_VALUE"""),1.0) -> 1 | E13: =IFERROR(__xludf.DUMMYFUNCTION("""COMPUTED_VALUE"""),50.0) -> 50 | F13: =IFERROR(__xludf.DUMMYFUNCTION("""COMPUTED_VALUE"""),50.0) -> 50 | G13: =IFERROR(__xludf.DUMMYFUNCTION("""COMPUTED_VALUE"""),"CASH") -> CASH | J13: =IFERROR(__xludf.DUMMYFUNCTION("""COMPUTED_VALUE"""),50.0) -> 50 | K13: =IFERROR(__xludf.DUMMYFUNCTION("""COMPUTED_VALUE"""),1.0) -> 1 | L13: =IFERROR(__xludf.DUMMYFUNCTION("""COMPUTED_VALUE"""),0.0) -> 0 | M13: =IFERROR(__xludf.DUMMYFUNCTION("""COMPUTED_VALUE"""),"Vijay jadhav") -> Vijay jadhav
A14: =IFERROR(__xludf.DUMMYFUNCTION("""COMPUTED_VALUE"""),46206.0) -> 46206 | B14: =IFERROR(__xludf.DUMMYFUNCTION("""COMPUTED_VALUE"""),"HLC") -> HLC | C14: =IFERROR(__xludf.DUMMYFUNCTION("""COMPUTED_VALUE"""),"Halad Chair") -> Halad Chair | D14: =IFERROR(__xludf.DUMMYFUNCTION("""COMPUTED_VALUE"""),1.0) -> 1 | E14: =IFERROR(__xludf.DUMMYFUNCTION("""COMPUTED_VALUE"""),300.0) -> 300 | F14: =IFERROR(__xludf.DUMMYFUNCTION("""COMPUTED_VALUE"""),300.0) -> 300 | G14: =IFERROR(__xludf.DUMMYFUNCTION("""COMPUTED_VALUE"""),"Sunil Garandwal") -> Sunil Garandwal | I14: =IFERROR(__xludf.DUMMYFUNCTION("""COMPUTED_VALUE"""),300.0) -> 300 | K14: =IFERROR(__xludf.DUMMYFUNCTION("""COMPUTED_VALUE"""),1.0) -> 1 | L14: =IFERROR(__xludf.DUMMYFUNCTION("""COMPUTED_VALUE"""),0.0) -> 0
A15: =IFERROR(__xludf.DUMMYFUNCTION("""COMPUTED_VALUE"""),46207.0) -> 46207 | B15: =IFERROR(__xludf.DUMMYFUNCTION("""COMPUTED_VALUE"""),"CTRNG") -> CTRNG | C15: =IFERROR(__xludf.DUMMYFUNCTION("""COMPUTED_VALUE"""),"CTRNG") -> CTRNG | D15: =IFERROR(__xludf.DUMMYFUNCTION("""COMPUTED_VALUE"""),1.0) -> 1 | E15: =IFERROR(__xludf.DUMMYFUNCTION("""COMPUTED_VALUE"""),330.0) -> 330 | F15: =IFERROR(__xludf.DUMMYFUNCTION("""COMPUTED_VALUE"""),330.0) -> 330 | G15: =IFERROR(__xludf.DUMMYFUNCTION("""COMPUTED_VALUE"""),"Abhiman Kharat") -> Abhiman Kharat | I15: =IFERROR(__xludf.DUMMYFUNCTION("""COMPUTED_VALUE"""),100.0) -> 100 | J15: =IFERROR(__xludf.DUMMYFUNCTION("""COMPUTED_VALUE"""),230.0) -> 230 | K15: =IFERROR(__xludf.DUMMYFUNCTION("""COMPUTED_VALUE"""),1.0) -> 1 | L15: =IFERROR(__xludf.DUMMYFUNCTION("""COMPUTED_VALUE"""),0.0) -> 0
A16: =IFERROR(__xludf.DUMMYFUNCTION("""COMPUTED_VALUE"""),46206.0) -> 46206 | B16: =IFERROR(__xludf.DUMMYFUNCTION("""COMPUTED_VALUE"""),"CTRNG") -> CTRNG | C16: =IFERROR(__xludf.DUMMYFUNCTION("""COMPUTED_VALUE"""),"CTRNG") -> CTRNG | D16: =IFERROR(__xludf.DUMMYFUNCTION("""COMPUTED_VALUE"""),1.0) -> 1 | E16: =IFERROR(__xludf.DUMMYFUNCTION("""COMPUTED_VALUE"""),450.0) -> 450 | F16: =IFERROR(__xludf.DUMMYFUNCTION("""COMPUTED_VALUE"""),450.0) -> 450 | G16: =IFERROR(__xludf.DUMMYFUNCTION("""COMPUTED_VALUE"""),"Ganesh Mandap T") -> Ganesh Mandap T | J16: =IFERROR(__xludf.DUMMYFUNCTION("""COMPUTED_VALUE"""),450.0) -> 450 | K16: =IFERROR(__xludf.DUMMYFUNCTION("""COMPUTED_VALUE"""),1.0) -> 1 | L16: =IFERROR(__xludf.DUMMYFUNCTION("""COMPUTED_VALUE"""),0.0) -> 0
A17: =IFERROR(__xludf.DUMMYFUNCTION("""COMPUTED_VALUE"""),46206.0) -> 46206 | B17: =IFERROR(__xludf.DUMMYFUNCTION("""COMPUTED_VALUE"""),"HLC") -> HLC | C17: =IFERROR(__xludf.DUMMYFUNCTION("""COMPUTED_VALUE"""),"Halad Chair") -> Halad Chair | D17: =IFERROR(__xludf.DUMMYFUNCTION("""COMPUTED_VALUE"""),1.0) -> 1 | E17: =IFERROR(__xludf.DUMMYFUNCTION("""COMPUTED_VALUE"""),300.0) -> 300 | F17: =IFERROR(__xludf.DUMMYFUNCTION("""COMPUTED_VALUE"""),300.0) -> 300 | G17: =IFERROR(__xludf.DUMMYFUNCTION("""COMPUTED_VALUE"""),"Ganesh Mandap T") -> Ganesh Mandap T | J17: =IFERROR(__xludf.DUMMYFUNCTION("""COMPUTED_VALUE"""),300.0) -> 300 | K17: =IFERROR(__xludf.DUMMYFUNCTION("""COMPUTED_VALUE"""),1.0) -> 1 | L17: =IFERROR(__xludf.DUMMYFUNCTION("""COMPUTED_VALUE"""),0.0) -> 0
A18: =IFERROR(__xludf.DUMMYFUNCTION("""COMPUTED_VALUE"""),46206.0) -> 46206 | E18: =IFERROR(__xludf.DUMMYFUNCTION("""COMPUTED_VALUE"""),0.0) -> 0 | F18: =IFERROR(__xludf.DUMMYFUNCTION("""COMPUTED_VALUE"""),0.0) -> 0 | G18: =IFERROR(__xludf.DUMMYFUNCTION("""COMPUTED_VALUE"""),"Atul Salve") -> Atul Salve | I18: =IFERROR(__xludf.DUMMYFUNCTION("""COMPUTED_VALUE"""),1000.0) -> 1000 | J18: =IFERROR(__xludf.DUMMYFUNCTION("""COMPUTED_VALUE"""),-1000.0) -> -1000 | L18: =IFERROR(__xludf.DUMMYFUNCTION("""COMPUTED_VALUE"""),0.0) -> 0
A19: =IFERROR(__xludf.DUMMYFUNCTION("""COMPUTED_VALUE"""),46207.0) -> 46207 | B19: =IFERROR(__xludf.DUMMYFUNCTION("""COMPUTED_VALUE"""),"SMI") -> SMI | C19: =IFERROR(__xludf.DUMMYFUNCTION("""COMPUTED_VALUE"""),"Samai") -> Samai | D19: =IFERROR(__xludf.DUMMYFUNCTION("""COMPUTED_VALUE"""),1.0) -> 1 | E19: =IFERROR(__xludf.DUMMYFUNCTION("""COMPUTED_VALUE"""),300.0) -> 300 | F19: =IFERROR(__xludf.DUMMYFUNCTION("""COMPUTED_VALUE"""),300.0) -> 300 | G19: =IFERROR(__xludf.DUMMYFUNCTION("""COMPUTED_VALUE"""),"Vishva Mandap") -> Vishva Mandap | I19: =IFERROR(__xludf.DUMMYFUNCTION("""COMPUTED_VALUE"""),300.0) -> 300 | K19: =IFERROR(__xludf.DUMMYFUNCTION("""COMPUTED_VALUE"""),1.0) -> 1 | L19: =IFERROR(__xludf.DUMMYFUNCTION("""COMPUTED_VALUE"""),0.0) -> 0
A20: =IFERROR(__xludf.DUMMYFUNCTION("""COMPUTED_VALUE"""),46208.0) -> 46208 | B20: =IFERROR(__xludf.DUMMYFUNCTION("""COMPUTED_VALUE"""),"PLN") -> PLN | C20: =IFERROR(__xludf.DUMMYFUNCTION("""COMPUTED_VALUE"""),"Palna") -> Palna | D20: =IFERROR(__xludf.DUMMYFUNCTION("""COMPUTED_VALUE"""),1.0) -> 1 | E20: =IFERROR(__xludf.DUMMYFUNCTION("""COMPUTED_VALUE"""),500.0) -> 500 | F20: =IFERROR(__xludf.DUMMYFUNCTION("""COMPUTED_VALUE"""),500.0) -> 500 | G20: =IFERROR(__xludf.DUMMYFUNCTION("""COMPUTED_VALUE"""),"Ayush Mandap") -> Ayush Mandap | I20: =IFERROR(__xludf.DUMMYFUNCTION("""COMPUTED_VALUE"""),0.0) -> 0 | J20: =IFERROR(__xludf.DUMMYFUNCTION("""COMPUTED_VALUE"""),500.0) -> 500 | K20: =IFERROR(__xludf.DUMMYFUNCTION("""COMPUTED_VALUE"""),1.0) -> 1 | L20: =IFERROR(__xludf.DUMMYFUNCTION("""COMPUTED_VALUE"""),0.0) -> 0
A21: =IFERROR(__xludf.DUMMYFUNCTION("""COMPUTED_VALUE"""),46208.0) -> 46208 | B21: =IFERROR(__xludf.DUMMYFUNCTION("""COMPUTED_VALUE"""),"MSF") -> MSF | C21: =IFERROR(__xludf.DUMMYFUNCTION("""COMPUTED_VALUE"""),"Maharaja Sofa ") -> Maharaja Sofa | D21: =IFERROR(__xludf.DUMMYFUNCTION("""COMPUTED_VALUE"""),1.0) -> 1 | E21: =IFERROR(__xludf.DUMMYFUNCTION("""COMPUTED_VALUE"""),700.0) -> 700 | F21: =IFERROR(__xludf.DUMMYFUNCTION("""COMPUTED_VALUE"""),700.0) -> 700 | G21: =IFERROR(__xludf.DUMMYFUNCTION("""COMPUTED_VALUE"""),"Ayush Mandap") -> Ayush Mandap | I21: =IFERROR(__xludf.DUMMYFUNCTION("""COMPUTED_VALUE"""),700.0) -> 700 | K21: =IFERROR(__xludf.DUMMYFUNCTION("""COMPUTED_VALUE"""),1.0) -> 1 | L21: =IFERROR(__xludf.DUMMYFUNCTION("""COMPUTED_VALUE"""),0.0) -> 0
A22: =IFERROR(__xludf.DUMMYFUNCTION("""COMPUTED_VALUE"""),46208.0) -> 46208 | B22: =IFERROR(__xludf.DUMMYFUNCTION("""COMPUTED_VALUE"""),"PLN") -> PLN | C22: =IFERROR(__xludf.DUMMYFUNCTION("""COMPUTED_VALUE"""),"Palna") -> Palna | D22: =IFERROR(__xludf.DUMMYFUNCTION("""COMPUTED_VALUE"""),1.0) -> 1 | E22: =IFERROR(__xludf.DUMMYFUNCTION("""COMPUTED_VALUE"""),500.0) -> 500 | F22: =IFERROR(__xludf.DUMMYFUNCTION("""COMPUTED_VALUE"""),500.0) -> 500 | G22: =IFERROR(__xludf.DUMMYFUNCTION("""COMPUTED_VALUE"""),"Ayush Mandap") -> Ayush Mandap | I22: =IFERROR(__xludf.DUMMYFUNCTION("""COMPUTED_VALUE"""),500.0) -> 500 | K22: =IFERROR(__xludf.DUMMYFUNCTION("""COMPUTED_VALUE"""),1.0) -> 1 | L22: =IFERROR(__xludf.DUMMYFUNCTION("""COMPUTED_VALUE"""),0.0) -> 0
A23: =IFERROR(__xludf.DUMMYFUNCTION("""COMPUTED_VALUE"""),46208.0) -> 46208 | B23: =IFERROR(__xludf.DUMMYFUNCTION("""COMPUTED_VALUE"""),"CTRNG") -> CTRNG | C23: =IFERROR(__xludf.DUMMYFUNCTION("""COMPUTED_VALUE"""),"CTRNG") -> CTRNG | D23: =IFERROR(__xludf.DUMMYFUNCTION("""COMPUTED_VALUE"""),1.0) -> 1 | E23: =IFERROR(__xludf.DUMMYFUNCTION("""COMPUTED_VALUE"""),900.0) -> 900 | F23: =IFERROR(__xludf.DUMMYFUNCTION("""COMPUTED_VALUE"""),900.0) -> 900 | G23: =IFERROR(__xludf.DUMMYFUNCTION("""COMPUTED_VALUE"""),"Yogesh Caterers") -> Yogesh Caterers | J23: =IFERROR(__xludf.DUMMYFUNCTION("""COMPUTED_VALUE"""),900.0) -> 900 | K23: =IFERROR(__xludf.DUMMYFUNCTION("""COMPUTED_VALUE"""),1.0) -> 1 | L23: =IFERROR(__xludf.DUMMYFUNCTION("""COMPUTED_VALUE"""),0.0) -> 0
A24: =IFERROR(__xludf.DUMMYFUNCTION("""COMPUTED_VALUE"""),46204.0) -> 46204 | B24: =IFERROR(__xludf.DUMMYFUNCTION("""COMPUTED_VALUE"""),"GD SET") -> GD SET | C24: =IFERROR(__xludf.DUMMYFUNCTION("""COMPUTED_VALUE"""),"Gadi Set") -> Gadi Set | D24: =IFERROR(__xludf.DUMMYFUNCTION("""COMPUTED_VALUE"""),10.0) -> 10 | E24: =IFERROR(__xludf.DUMMYFUNCTION("""COMPUTED_VALUE"""),100.0) -> 100 | F24: =IFERROR(__xludf.DUMMYFUNCTION("""COMPUTED_VALUE"""),1000.0) -> 1000 | G24: =IFERROR(__xludf.DUMMYFUNCTION("""COMPUTED_VALUE"""),"CASH") -> CASH | I24: =IFERROR(__xludf.DUMMYFUNCTION("""COMPUTED_VALUE"""),1000.0) -> 1000 | K24: =IFERROR(__xludf.DUMMYFUNCTION("""COMPUTED_VALUE"""),10.0) -> 10 | L24: =IFERROR(__xludf.DUMMYFUNCTION("""COMPUTED_VALUE"""),0.0) -> 0
A25: =IFERROR(__xludf.DUMMYFUNCTION("""COMPUTED_VALUE"""),46204.0) -> 46204 | B25: =IFERROR(__xludf.DUMMYFUNCTION("""COMPUTED_VALUE"""),"RTBL") -> RTBL | C25: =IFERROR(__xludf.DUMMYFUNCTION("""COMPUTED_VALUE"""),"Round Table ") -> Round Table | D25: =IFERROR(__xludf.DUMMYFUNCTION("""COMPUTED_VALUE"""),1.0) -> 1 | E25: =IFERROR(__xludf.DUMMYFUNCTION("""COMPUTED_VALUE"""),200.0) -> 200 | F25: =IFERROR(__xludf.DUMMYFUNCTION("""COMPUTED_VALUE"""),200.0) -> 200 | G25: =IFERROR(__xludf.DUMMYFUNCTION("""COMPUTED_VALUE"""),"CASH") -> CASH | I25: =IFERROR(__xludf.DUMMYFUNCTION("""COMPUTED_VALUE"""),200.0) -> 200 | K25: =IFERROR(__xludf.DUMMYFUNCTION("""COMPUTED_VALUE"""),1.0) -> 1 | L25: =IFERROR(__xludf.DUMMYFUNCTION("""COMPUTED_VALUE"""),0.0) -> 0
A26: =IFERROR(__xludf.DUMMYFUNCTION("""COMPUTED_VALUE"""),46204.0) -> 46204 | B26: =IFERROR(__xludf.DUMMYFUNCTION("""COMPUTED_VALUE"""),"PRD") -> PRD | C26: =IFERROR(__xludf.DUMMYFUNCTION("""COMPUTED_VALUE"""),"Parda") -> Parda | D26: =IFERROR(__xludf.DUMMYFUNCTION("""COMPUTED_VALUE"""),1.0) -> 1 | E26: =IFERROR(__xludf.DUMMYFUNCTION("""COMPUTED_VALUE"""),100.0) -> 100 | F26: =IFERROR(__xludf.DUMMYFUNCTION("""COMPUTED_VALUE"""),100.0) -> 100 | G26: =IFERROR(__xludf.DUMMYFUNCTION("""COMPUTED_VALUE"""),"CASH") -> CASH | I26: =IFERROR(__xludf.DUMMYFUNCTION("""COMPUTED_VALUE"""),100.0) -> 100 | K26: =IFERROR(__xludf.DUMMYFUNCTION("""COMPUTED_VALUE"""),1.0) -> 1 | L26: =IFERROR(__xludf.DUMMYFUNCTION("""COMPUTED_VALUE"""),0.0) -> 0
A27: =IFERROR(__xludf.DUMMYFUNCTION("""COMPUTED_VALUE"""),46209.0) -> 46209 | B27: =IFERROR(__xludf.DUMMYFUNCTION("""COMPUTED_VALUE"""),"CTRNG") -> CTRNG | C27: =IFERROR(__xludf.DUMMYFUNCTION("""COMPUTED_VALUE"""),"CTRNG") -> CTRNG | D27: =IFERROR(__xludf.DUMMYFUNCTION("""COMPUTED_VALUE"""),1.0) -> 1 | E27: =IFERROR(__xludf.DUMMYFUNCTION("""COMPUTED_VALUE"""),100.0) -> 100 | F27: =IFERROR(__xludf.DUMMYFUNCTION("""COMPUTED_VALUE"""),100.0) -> 100 | G27: =IFERROR(__xludf.DUMMYFUNCTION("""COMPUTED_VALUE"""),"CASH") -> CASH | I27: =IFERROR(__xludf.DUMMYFUNCTION("""COMPUTED_VALUE"""),100.0) -> 100 | K27: =IFERROR(__xludf.DUMMYFUNCTION("""COMPUTED_VALUE"""),1.0) -> 1 | L27: =IFERROR(__xludf.DUMMYFUNCTION("""COMPUTED_VALUE"""),0.0) -> 0
A28: =IFERROR(__xludf.DUMMYFUNCTION("""COMPUTED_VALUE"""),46210.0) -> 46210 | B28: =IFERROR(__xludf.DUMMYFUNCTION("""COMPUTED_VALUE"""),"THRMS") -> THRMS | C28: =IFERROR(__xludf.DUMMYFUNCTION("""COMPUTED_VALUE"""),"Thermos") -> Thermos | D28: =IFERROR(__xludf.DUMMYFUNCTION("""COMPUTED_VALUE"""),1.0) -> 1 | E28: =IFERROR(__xludf.DUMMYFUNCTION("""COMPUTED_VALUE"""),50.0) -> 50 | F28: =IFERROR(__xludf.DUMMYFUNCTION("""COMPUTED_VALUE"""),50.0) -> 50 | G28: =IFERROR(__xludf.DUMMYFUNCTION("""COMPUTED_VALUE"""),"CASH") -> CASH | J28: =IFERROR(__xludf.DUMMYFUNCTION("""COMPUTED_VALUE"""),50.0) -> 50 | K28: =IFERROR(__xludf.DUMMYFUNCTION("""COMPUTED_VALUE"""),1.0) -> 1 | L28: =IFERROR(__xludf.DUMMYFUNCTION("""COMPUTED_VALUE"""),0.0) -> 0 | M28: =IFERROR(__xludf.DUMMYFUNCTION("""COMPUTED_VALUE"""),"Bhagwat Pawar") -> Bhagwat Pawar
A29: =IFERROR(__xludf.DUMMYFUNCTION("""COMPUTED_VALUE"""),46211.0) -> 46211 | B29: =IFERROR(__xludf.DUMMYFUNCTION("""COMPUTED_VALUE"""),"CH") -> CH | C29: =IFERROR(__xludf.DUMMYFUNCTION("""COMPUTED_VALUE"""),"Chair ") -> Chair | D29: =IFERROR(__xludf.DUMMYFUNCTION("""COMPUTED_VALUE"""),37.0) -> 37 | E29: =IFERROR(__xludf.DUMMYFUNCTION("""COMPUTED_VALUE"""),10.0) -> 10 | F29: =IFERROR(__xludf.DUMMYFUNCTION("""COMPUTED_VALUE"""),370.0) -> 370 | G29: =IFERROR(__xludf.DUMMYFUNCTION("""COMPUTED_VALUE"""),"CASH") -> CASH | I29: =IFERROR(__xludf.DUMMYFUNCTION("""COMPUTED_VALUE"""),370.0) -> 370 | K29: =IFERROR(__xludf.DUMMYFUNCTION("""COMPUTED_VALUE"""),37.0) -> 37 | L29: =IFERROR(__xludf.DUMMYFUNCTION("""COMPUTED_VALUE"""),0.0) -> 0
A30: =IFERROR(__xludf.DUMMYFUNCTION("""COMPUTED_VALUE"""),46211.0) -> 46211 | B30: =IFERROR(__xludf.DUMMYFUNCTION("""COMPUTED_VALUE"""),"TBL") -> TBL | C30: =IFERROR(__xludf.DUMMYFUNCTION("""COMPUTED_VALUE"""),"Table") -> Table | D30: =IFERROR(__xludf.DUMMYFUNCTION("""COMPUTED_VALUE"""),9.0) -> 9 | E30: =IFERROR(__xludf.DUMMYFUNCTION("""COMPUTED_VALUE"""),20.0) -> 20 | F30: =IFERROR(__xludf.DUMMYFUNCTION("""COMPUTED_VALUE"""),180.0) -> 180 | G30: =IFERROR(__xludf.DUMMYFUNCTION("""COMPUTED_VALUE"""),"CASH") -> CASH | I30: =IFERROR(__xludf.DUMMYFUNCTION("""COMPUTED_VALUE"""),180.0) -> 180 | K30: =IFERROR(__xludf.DUMMYFUNCTION("""COMPUTED_VALUE"""),9.0) -> 9 | L30: =IFERROR(__xludf.DUMMYFUNCTION("""COMPUTED_VALUE"""),0.0) -> 0
A31: =IFERROR(__xludf.DUMMYFUNCTION("""COMPUTED_VALUE"""),46211.0) -> 46211 | B31: =IFERROR(__xludf.DUMMYFUNCTION("""COMPUTED_VALUE"""),"FRL") -> FRL | C31: =IFERROR(__xludf.DUMMYFUNCTION("""COMPUTED_VALUE"""),"Freel") -> Freel | D31: =IFERROR(__xludf.DUMMYFUNCTION("""COMPUTED_VALUE"""),5.0) -> 5 | E31: =IFERROR(__xludf.DUMMYFUNCTION("""COMPUTED_VALUE"""),30.0) -> 30 | F31: =IFERROR(__xludf.DUMMYFUNCTION("""COMPUTED_VALUE"""),150.0) -> 150 | G31: =IFERROR(__xludf.DUMMYFUNCTION("""COMPUTED_VALUE"""),"CASH") -> CASH | I31: =IFERROR(__xludf.DUMMYFUNCTION("""COMPUTED_VALUE"""),150.0) -> 150 | K31: =IFERROR(__xludf.DUMMYFUNCTION("""COMPUTED_VALUE"""),5.0) -> 5 | L31: =IFERROR(__xludf.DUMMYFUNCTION("""COMPUTED_VALUE"""),0.0) -> 0
A32: =IFERROR(__xludf.DUMMYFUNCTION("""COMPUTED_VALUE"""),46212.0) -> 46212 | B32: =IFERROR(__xludf.DUMMYFUNCTION("""COMPUTED_VALUE"""),"CTRNG") -> CTRNG | C32: =IFERROR(__xludf.DUMMYFUNCTION("""COMPUTED_VALUE"""),"CTRNG") -> CTRNG | D32: =IFERROR(__xludf.DUMMYFUNCTION("""COMPUTED_VALUE"""),1.0) -> 1 | E32: =IFERROR(__xludf.DUMMYFUNCTION("""COMPUTED_VALUE"""),275.0) -> 275 | F32: =IFERROR(__xludf.DUMMYFUNCTION("""COMPUTED_VALUE"""),275.0) -> 275 | G32: =IFERROR(__xludf.DUMMYFUNCTION("""COMPUTED_VALUE"""),"CASH") -> CASH | I32: =IFERROR(__xludf.DUMMYFUNCTION("""COMPUTED_VALUE"""),275.0) -> 275 | K32: =IFERROR(__xludf.DUMMYFUNCTION("""COMPUTED_VALUE"""),1.0) -> 1 | L32: =IFERROR(__xludf.DUMMYFUNCTION("""COMPUTED_VALUE"""),0.0) -> 0
A33: =IFERROR(__xludf.DUMMYFUNCTION("""COMPUTED_VALUE"""),46212.0) -> 46212 | B33: =IFERROR(__xludf.DUMMYFUNCTION("""COMPUTED_VALUE"""),"CH") -> CH | C33: =IFERROR(__xludf.DUMMYFUNCTION("""COMPUTED_VALUE"""),"Chair ") -> Chair | D33: =IFERROR(__xludf.DUMMYFUNCTION("""COMPUTED_VALUE"""),4.0) -> 4 | E33: =IFERROR(__xludf.DUMMYFUNCTION("""COMPUTED_VALUE"""),10.0) -> 10 | F33: =IFERROR(__xludf.DUMMYFUNCTION("""COMPUTED_VALUE"""),40.0) -> 40 | G33: =IFERROR(__xludf.DUMMYFUNCTION("""COMPUTED_VALUE"""),"CASH") -> CASH | I33: =IFERROR(__xludf.DUMMYFUNCTION("""COMPUTED_VALUE"""),40.0) -> 40 | K33: =IFERROR(__xludf.DUMMYFUNCTION("""COMPUTED_VALUE"""),4.0) -> 4 | L33: =IFERROR(__xludf.DUMMYFUNCTION("""COMPUTED_VALUE"""),0.0) -> 0
A34: =IFERROR(__xludf.DUMMYFUNCTION("""COMPUTED_VALUE"""),46212.0) -> 46212 | B34: =IFERROR(__xludf.DUMMYFUNCTION("""COMPUTED_VALUE"""),"ASN") -> ASN | C34: =IFERROR(__xludf.DUMMYFUNCTION("""COMPUTED_VALUE"""),"Asanpatti") -> Asanpatti | D34: =IFERROR(__xludf.DUMMYFUNCTION("""COMPUTED_VALUE"""),8.0) -> 8 | E34: =IFERROR(__xludf.DUMMYFUNCTION("""COMPUTED_VALUE"""),10.0) -> 10 | F34: =IFERROR(__xludf.DUMMYFUNCTION("""COMPUTED_VALUE"""),80.0) -> 80 | G34: =IFERROR(__xludf.DUMMYFUNCTION("""COMPUTED_VALUE"""),"CASH") -> CASH | I34: =IFERROR(__xludf.DUMMYFUNCTION("""COMPUTED_VALUE"""),80.0) -> 80 | K34: =IFERROR(__xludf.DUMMYFUNCTION("""COMPUTED_VALUE"""),8.0) -> 8 | L34: =IFERROR(__xludf.DUMMYFUNCTION("""COMPUTED_VALUE"""),0.0) -> 0
A35: =IFERROR(__xludf.DUMMYFUNCTION("""COMPUTED_VALUE"""),46213.0) -> 46213 | B35: =IFERROR(__xludf.DUMMYFUNCTION("""COMPUTED_VALUE"""),"AB") -> AB | C35: =IFERROR(__xludf.DUMMYFUNCTION("""COMPUTED_VALUE"""),"Ahuja Speaker") -> Ahuja Speaker | D35: =IFERROR(__xludf.DUMMYFUNCTION("""COMPUTED_VALUE"""),1.0) -> 1 | E35: =IFERROR(__xludf.DUMMYFUNCTION("""COMPUTED_VALUE"""),500.0) -> 500 | F35: =IFERROR(__xludf.DUMMYFUNCTION("""COMPUTED_VALUE"""),500.0) -> 500 | G35: =IFERROR(__xludf.DUMMYFUNCTION("""COMPUTED_VALUE"""),"CASH") -> CASH | J35: =IFERROR(__xludf.DUMMYFUNCTION("""COMPUTED_VALUE"""),500.0) -> 500 | K35: =IFERROR(__xludf.DUMMYFUNCTION("""COMPUTED_VALUE"""),1.0) -> 1 | L35: =IFERROR(__xludf.DUMMYFUNCTION("""COMPUTED_VALUE"""),0.0) -> 0
A36: =IFERROR(__xludf.DUMMYFUNCTION("""COMPUTED_VALUE"""),46209.0) -> 46209 | B36: =IFERROR(__xludf.DUMMYFUNCTION("""COMPUTED_VALUE"""),"CTRNG") -> CTRNG | C36: =IFERROR(__xludf.DUMMYFUNCTION("""COMPUTED_VALUE"""),"CTRNG") -> CTRNG | D36: =IFERROR(__xludf.DUMMYFUNCTION("""COMPUTED_VALUE"""),1.0) -> 1 | E36: =IFERROR(__xludf.DUMMYFUNCTION("""COMPUTED_VALUE"""),50.0) -> 50 | F36: =IFERROR(__xludf.DUMMYFUNCTION("""COMPUTED_VALUE"""),50.0) -> 50 | G36: =IFERROR(__xludf.DUMMYFUNCTION("""COMPUTED_VALUE"""),"Nagve Patil Caterers") -> Nagve Patil Caterers | I36: =IFERROR(__xludf.DUMMYFUNCTION("""COMPUTED_VALUE"""),50.0) -> 50 | K36: =IFERROR(__xludf.DUMMYFUNCTION("""COMPUTED_VALUE"""),1.0) -> 1 | L36: =IFERROR(__xludf.DUMMYFUNCTION("""COMPUTED_VALUE"""),0.0) -> 0
A37: =IFERROR(__xludf.DUMMYFUNCTION("""COMPUTED_VALUE"""),46210.0) -> 46210 | B37: =IFERROR(__xludf.DUMMYFUNCTION("""COMPUTED_VALUE"""),"SF") -> SF | C37: =IFERROR(__xludf.DUMMYFUNCTION("""COMPUTED_VALUE"""),"Sofa ") -> Sofa | D37: =IFERROR(__xludf.DUMMYFUNCTION("""COMPUTED_VALUE"""),1.0) -> 1 | E37: =IFERROR(__xludf.DUMMYFUNCTION("""COMPUTED_VALUE"""),150.0) -> 150 | F37: =IFERROR(__xludf.DUMMYFUNCTION("""COMPUTED_VALUE"""),150.0) -> 150 | G37: =IFERROR(__xludf.DUMMYFUNCTION("""COMPUTED_VALUE"""),"Dip Mandap") -> Dip Mandap | I37: =IFERROR(__xludf.DUMMYFUNCTION("""COMPUTED_VALUE"""),150.0) -> 150 | K37: =IFERROR(__xludf.DUMMYFUNCTION("""COMPUTED_VALUE"""),1.0) -> 1 | L37: =IFERROR(__xludf.DUMMYFUNCTION("""COMPUTED_VALUE"""),0.0) -> 0
A38: =IFERROR(__xludf.DUMMYFUNCTION("""COMPUTED_VALUE"""),46210.0) -> 46210 | B38: =IFERROR(__xludf.DUMMYFUNCTION("""COMPUTED_VALUE"""),"THRMS") -> THRMS | C38: =IFERROR(__xludf.DUMMYFUNCTION("""COMPUTED_VALUE"""),"Thermos") -> Thermos | D38: =IFERROR(__xludf.DUMMYFUNCTION("""COMPUTED_VALUE"""),1.0) -> 1 | E38: =IFERROR(__xludf.DUMMYFUNCTION("""COMPUTED_VALUE"""),50.0) -> 50 | F38: =IFERROR(__xludf.DUMMYFUNCTION("""COMPUTED_VALUE"""),50.0) -> 50 | G38: =IFERROR(__xludf.DUMMYFUNCTION("""COMPUTED_VALUE"""),"Dip Mandap") -> Dip Mandap | I38: =IFERROR(__xludf.DUMMYFUNCTION("""COMPUTED_VALUE"""),50.0) -> 50 | K38: =IFERROR(__xludf.DUMMYFUNCTION("""COMPUTED_VALUE"""),1.0) -> 1 | L38: =IFERROR(__xludf.DUMMYFUNCTION("""COMPUTED_VALUE"""),0.0) -> 0
A39: =IFERROR(__xludf.DUMMYFUNCTION("""COMPUTED_VALUE"""),46210.0) -> 46210 | B39: =IFERROR(__xludf.DUMMYFUNCTION("""COMPUTED_VALUE"""),"TBL") -> TBL | C39: =IFERROR(__xludf.DUMMYFUNCTION("""COMPUTED_VALUE"""),"Table") -> Table | D39: =IFERROR(__xludf.DUMMYFUNCTION("""COMPUTED_VALUE"""),1.0) -> 1 | E39: =IFERROR(__xludf.DUMMYFUNCTION("""COMPUTED_VALUE"""),20.0) -> 20 | F39: =IFERROR(__xludf.DUMMYFUNCTION("""COMPUTED_VALUE"""),20.0) -> 20 | G39: =IFERROR(__xludf.DUMMYFUNCTION("""COMPUTED_VALUE"""),"Mahalakshmi Mandap") -> Mahalakshmi Mandap | I39: =IFERROR(__xludf.DUMMYFUNCTION("""COMPUTED_VALUE"""),20.0) -> 20 | K39: =IFERROR(__xludf.DUMMYFUNCTION("""COMPUTED_VALUE"""),1.0) -> 1 | L39: =IFERROR(__xludf.DUMMYFUNCTION("""COMPUTED_VALUE"""),0.0) -> 0
A40: =IFERROR(__xludf.DUMMYFUNCTION("""COMPUTED_VALUE"""),46211.0) -> 46211 | B40: =IFERROR(__xludf.DUMMYFUNCTION("""COMPUTED_VALUE"""),"CTRNG") -> CTRNG | C40: =IFERROR(__xludf.DUMMYFUNCTION("""COMPUTED_VALUE"""),"CTRNG") -> CTRNG | D40: =IFERROR(__xludf.DUMMYFUNCTION("""COMPUTED_VALUE"""),1.0) -> 1 | E40: =IFERROR(__xludf.DUMMYFUNCTION("""COMPUTED_VALUE"""),600.0) -> 600 | F40: =IFERROR(__xludf.DUMMYFUNCTION("""COMPUTED_VALUE"""),600.0) -> 600 | G40: =IFERROR(__xludf.DUMMYFUNCTION("""COMPUTED_VALUE"""),"Pruthviraj Mandap") -> Pruthviraj Mandap | I40: =IFERROR(__xludf.DUMMYFUNCTION("""COMPUTED_VALUE"""),600.0) -> 600 | K40: =IFERROR(__xludf.DUMMYFUNCTION("""COMPUTED_VALUE"""),1.0) -> 1 | L40: =IFERROR(__xludf.DUMMYFUNCTION("""COMPUTED_VALUE"""),0.0) -> 0
A41: =IFERROR(__xludf.DUMMYFUNCTION("""COMPUTED_VALUE"""),46210.0) -> 46210 | E41: =IFERROR(__xludf.DUMMYFUNCTION("""COMPUTED_VALUE"""),0.0) -> 0 | F41: =IFERROR(__xludf.DUMMYFUNCTION("""COMPUTED_VALUE"""),0.0) -> 0 | L41: =IFERROR(__xludf.DUMMYFUNCTION("""COMPUTED_VALUE"""),0.0) -> 0
A42: =IFERROR(__xludf.DUMMYFUNCTION("""COMPUTED_VALUE"""),46210.0) -> 46210 | E42: =IFERROR(__xludf.DUMMYFUNCTION("""COMPUTED_VALUE"""),0.0) -> 0 | F42: =IFERROR(__xludf.DUMMYFUNCTION("""COMPUTED_VALUE"""),0.0) -> 0 | L42: =IFERROR(__xludf.DUMMYFUNCTION("""COMPUTED_VALUE"""),0.0) -> 0
A43: =IFERROR(__xludf.DUMMYFUNCTION("""COMPUTED_VALUE"""),46210.0) -> 46210 | E43: =IFERROR(__xludf.DUMMYFUNCTION("""COMPUTED_VALUE"""),0.0) -> 0 | F43: =IFERROR(__xludf.DUMMYFUNCTION("""COMPUTED_VALUE"""),0.0) -> 0 | L43: =IFERROR(__xludf.DUMMYFUNCTION("""COMPUTED_VALUE"""),0.0) -> 0

Sheet Pay BAL
G2: PAYMENT BALANCE
A5: =IFERROR(__xludf.DUMMYFUNCTION("QUERY(Sales!A:M,""SELECT * WHERE Col10 IS NOT NULL"",1)"),"DATE") -> DATE | B5: =IFERROR(__xludf.DUMMYFUNCTION("""COMPUTED_VALUE"""),"ITEM ID") -> ITEM ID | C5: =IFERROR(__xludf.DUMMYFUNCTION("""COMPUTED_VALUE"""),"ITEM NAME") -> ITEM NAME | D5: =IFERROR(__xludf.DUMMYFUNCTION("""COMPUTED_VALUE"""),"QUANTITY") -> QUANTITY | E5: =IFERROR(__xludf.DUMMYFUNCTION("""COMPUTED_VALUE"""),"PRICE") -> PRICE | F5: =IFERROR(__xludf.DUMMYFUNCTION("""COMPUTED_VALUE"""),"TOTAL") -> TOTAL | G5: =IFERROR(__xludf.DUMMYFUNCTION("""COMPUTED_VALUE"""),"CUSTOMER NAME") -> CUSTOMER NAME | H5: =IFERROR(__xludf.DUMMYFUNCTION("""COMPUTED_VALUE"""),"PAYMENT METHOD ") -> PAYMENT METHOD | I5: =IFERROR(__xludf.DUMMYFUNCTION("""COMPUTED_VALUE"""),"PAYMENT RECEIVED ") -> PAYMENT RECEIVED | J5: =IFERROR(__xludf.DUMMYFUNCTION("""COMPUTED_VALUE"""),"PAYMENT BALANCE ") -> PAYMENT BALANCE | K5: =IFERROR(__xludf.DUMMYFUNCTION("""COMPUTED_VALUE"""),"RETURN QUANTITY ") -> RETURN QUANTITY | L5: =IFERROR(__xludf.DUMMYFUNCTION("""COMPUTED_VALUE"""),"BALANCE QUANTITY") -> BALANCE QUANTITY | M5: =IFERROR(__xludf.DUMMYFUNCTION("""COMPUTED_VALUE"""),"Narration") -> Narration
A6: =IFERROR(__xludf.DUMMYFUNCTION("""COMPUTED_VALUE"""),46204.0) -> 46204 | B6: =IFERROR(__xludf.DUMMYFUNCTION("""COMPUTED_VALUE"""),"CTRNG") -> CTRNG | C6: =IFERROR(__xludf.DUMMYFUNCTION("""COMPUTED_VALUE"""),"CTRNG") -> CTRNG | D6: =IFERROR(__xludf.DUMMYFUNCTION("""COMPUTED_VALUE"""),1.0) -> 1 | E6: =IFERROR(__xludf.DUMMYFUNCTION("""COMPUTED_VALUE"""),850.0) -> 850 | F6: =IFERROR(__xludf.DUMMYFUNCTION("""COMPUTED_VALUE"""),850.0) -> 850 | G6: =IFERROR(__xludf.DUMMYFUNCTION("""COMPUTED_VALUE"""),"Yogesh Caterers") -> Yogesh Caterers | I6: =IFERROR(__xludf.DUMMYFUNCTION("""COMPUTED_VALUE"""),600.0) -> 600 | J6: =IFERROR(__xludf.DUMMYFUNCTION("""COMPUTED_VALUE"""),250.0) -> 250 | K6: =IFERROR(__xludf.DUMMYFUNCTION("""COMPUTED_VALUE"""),1.0) -> 1 | L6: =IFERROR(__xludf.DUMMYFUNCTION("""COMPUTED_VALUE"""),0.0) -> 0
A7: =IFERROR(__xludf.DUMMYFUNCTION("""COMPUTED_VALUE"""),46204.0) -> 46204 | B7: =IFERROR(__xludf.DUMMYFUNCTION("""COMPUTED_VALUE"""),"CH") -> CH | C7: =IFERROR(__xludf.DUMMYFUNCTION("""COMPUTED_VALUE"""),"Chair ") -> Chair | D7: =IFERROR(__xludf.DUMMYFUNCTION("""COMPUTED_VALUE"""),20.0) -> 20 | E7: =IFERROR(__xludf.DUMMYFUNCTION("""COMPUTED_VALUE"""),4.0) -> 4 | F7: =IFERROR(__xludf.DUMMYFUNCTION("""COMPUTED_VALUE"""),80.0) -> 80 | G7: =IFERROR(__xludf.DUMMYFUNCTION("""COMPUTED_VALUE"""),"Tulja Bhavani Mandap") -> Tulja Bhavani Mandap | J7: =IFERROR(__xludf.DUMMYFUNCTION("""COMPUTED_VALUE"""),80.0) -> 80 | K7: =IFERROR(__xludf.DUMMYFUNCTION("""COMPUTED_VALUE"""),20.0) -> 20 | L7: =IFERROR(__xludf.DUMMYFUNCTION("""COMPUTED_VALUE"""),0.0) -> 0
A8: =IFERROR(__xludf.DUMMYFUNCTION("""COMPUTED_VALUE"""),46204.0) -> 46204 | B8: =IFERROR(__xludf.DUMMYFUNCTION("""COMPUTED_VALUE"""),"CH") -> CH | C8: =IFERROR(__xludf.DUMMYFUNCTION("""COMPUTED_VALUE"""),"Chair ") -> Chair | D8: =IFERROR(__xludf.DUMMYFUNCTION("""COMPUTED_VALUE"""),70.0) -> 70 | E8: =IFERROR(__xludf.DUMMYFUNCTION("""COMPUTED_VALUE"""),4.0) -> 4 | F8: =IFERROR(__xludf.DUMMYFUNCTION("""COMPUTED_VALUE"""),280.0) -> 280 | G8: =IFERROR(__xludf.DUMMYFUNCTION("""COMPUTED_VALUE"""),"Tulja Bhavani Mandap") -> Tulja Bhavani Mandap | J8: =IFERROR(__xludf.DUMMYFUNCTION("""COMPUTED_VALUE"""),280.0) -> 280 | K8: =IFERROR(__xludf.DUMMYFUNCTION("""COMPUTED_VALUE"""),70.0) -> 70 | L8: =IFERROR(__xludf.DUMMYFUNCTION("""COMPUTED_VALUE"""),0.0) -> 0
A9: =IFERROR(__xludf.DUMMYFUNCTION("""COMPUTED_VALUE"""),46206.0) -> 46206 | B9: =IFERROR(__xludf.DUMMYFUNCTION("""COMPUTED_VALUE"""),"CTRNG") -> CTRNG | C9: =IFERROR(__xludf.DUMMYFUNCTION("""COMPUTED_VALUE"""),"CTRNG") -> CTRNG | D9: =IFERROR(__xludf.DUMMYFUNCTION("""COMPUTED_VALUE"""),1.0) -> 1 | E9: =IFERROR(__xludf.DUMMYFUNCTION("""COMPUTED_VALUE"""),50.0) -> 50 | F9: =IFERROR(__xludf.DUMMYFUNCTION("""COMPUTED_VALUE"""),50.0) -> 50 | G9: =IFERROR(__xludf.DUMMYFUNCTION("""COMPUTED_VALUE"""),"CASH") -> CASH | J9: =IFERROR(__xludf.DUMMYFUNCTION("""COMPUTED_VALUE"""),50.0) -> 50 | K9: =IFERROR(__xludf.DUMMYFUNCTION("""COMPUTED_VALUE"""),1.0) -> 1 | L9: =IFERROR(__xludf.DUMMYFUNCTION("""COMPUTED_VALUE"""),0.0) -> 0 | M9: =IFERROR(__xludf.DUMMYFUNCTION("""COMPUTED_VALUE"""),"Vijay jadhav") -> Vijay jadhav
A10: =IFERROR(__xludf.DUMMYFUNCTION("""COMPUTED_VALUE"""),46207.0) -> 46207 | B10: =IFERROR(__xludf.DUMMYFUNCTION("""COMPUTED_VALUE"""),"CTRNG") -> CTRNG | C10: =IFERROR(__xludf.DUMMYFUNCTION("""COMPUTED_VALUE"""),"CTRNG") -> CTRNG | D10: =IFERROR(__xludf.DUMMYFUNCTION("""COMPUTED_VALUE"""),1.0) -> 1 | E10: =IFERROR(__xludf.DUMMYFUNCTION("""COMPUTED_VALUE"""),330.0) -> 330 | F10: =IFERROR(__xludf.DUMMYFUNCTION("""COMPUTED_VALUE"""),330.0) -> 330 | G10: =IFERROR(__xludf.DUMMYFUNCTION("""COMPUTED_VALUE"""),"Abhiman Kharat") -> Abhiman Kharat | I10: =IFERROR(__xludf.DUMMYFUNCTION("""COMPUTED_VALUE"""),100.0) -> 100 | J10: =IFERROR(__xludf.DUMMYFUNCTION("""COMPUTED_VALUE"""),230.0) -> 230 | K10: =IFERROR(__xludf.DUMMYFUNCTION("""COMPUTED_VALUE"""),1.0) -> 1 | L10: =IFERROR(__xludf.DUMMYFUNCTION("""COMPUTED_VALUE"""),0.0) -> 0
A11: =IFERROR(__xludf.DUMMYFUNCTION("""COMPUTED_VALUE"""),46206.0) -> 46206 | B11: =IFERROR(__xludf.DUMMYFUNCTION("""COMPUTED_VALUE"""),"CTRNG") -> CTRNG | C11: =IFERROR(__xludf.DUMMYFUNCTION("""COMPUTED_VALUE"""),"CTRNG") -> CTRNG | D11: =IFERROR(__xludf.DUMMYFUNCTION("""COMPUTED_VALUE"""),1.0) -> 1 | E11: =IFERROR(__xludf.DUMMYFUNCTION("""COMPUTED_VALUE"""),450.0) -> 450 | F11: =IFERROR(__xludf.DUMMYFUNCTION("""COMPUTED_VALUE"""),450.0) -> 450 | G11: =IFERROR(__xludf.DUMMYFUNCTION("""COMPUTED_VALUE"""),"Ganesh Mandap T") -> Ganesh Mandap T | J11: =IFERROR(__xludf.DUMMYFUNCTION("""COMPUTED_VALUE"""),450.0) -> 450 | K11: =IFERROR(__xludf.DUMMYFUNCTION("""COMPUTED_VALUE"""),1.0) -> 1 | L11: =IFERROR(__xludf.DUMMYFUNCTION("""COMPUTED_VALUE"""),0.0) -> 0
A12: =IFERROR(__xludf.DUMMYFUNCTION("""COMPUTED_VALUE"""),46206.0) -> 46206 | B12: =IFERROR(__xludf.DUMMYFUNCTION("""COMPUTED_VALUE"""),"HLC") -> HLC | C12: =IFERROR(__xludf.DUMMYFUNCTION("""COMPUTED_VALUE"""),"Halad Chair") -> Halad Chair | D12: =IFERROR(__xludf.DUMMYFUNCTION("""COMPUTED_VALUE"""),1.0) -> 1 | E12: =IFERROR(__xludf.DUMMYFUNCTION("""COMPUTED_VALUE"""),300.0) -> 300 | F12: =IFERROR(__xludf.DUMMYFUNCTION("""COMPUTED_VALUE"""),300.0) -> 300 | G12: =IFERROR(__xludf.DUMMYFUNCTION("""COMPUTED_VALUE"""),"Ganesh Mandap T") -> Ganesh Mandap T | J12: =IFERROR(__xludf.DUMMYFUNCTION("""COMPUTED_VALUE"""),300.0) -> 300 | K12: =IFERROR(__xludf.DUMMYFUNCTION("""COMPUTED_VALUE"""),1.0) -> 1 | L12: =IFERROR(__xludf.DUMMYFUNCTION("""COMPUTED_VALUE"""),0.0) -> 0
A13: =IFERROR(__xludf.DUMMYFUNCTION("""COMPUTED_VALUE"""),46206.0) -> 46206 | E13: =IFERROR(__xludf.DUMMYFUNCTION("""COMPUTED_VALUE"""),0.0) -> 0 | F13: =IFERROR(__xludf.DUMMYFUNCTION("""COMPUTED_VALUE"""),0.0) -> 0 | G13: =IFERROR(__xludf.DUMMYFUNCTION("""COMPUTED_VALUE"""),"Atul Salve") -> Atul Salve | I13: =IFERROR(__xludf.DUMMYFUNCTION("""COMPUTED_VALUE"""),1000.0) -> 1000 | J13: =IFERROR(__xludf.DUMMYFUNCTION("""COMPUTED_VALUE"""),-1000.0) -> -1000 | L13: =IFERROR(__xludf.DUMMYFUNCTION("""COMPUTED_VALUE"""),0.0) -> 0
A14: =IFERROR(__xludf.DUMMYFUNCTION("""COMPUTED_VALUE"""),46208.0) -> 46208 | B14: =IFERROR(__xludf.DUMMYFUNCTION("""COMPUTED_VALUE"""),"PLN") -> PLN | C14: =IFERROR(__xludf.DUMMYFUNCTION("""COMPUTED_VALUE"""),"Palna") -> Palna | D14: =IFERROR(__xludf.DUMMYFUNCTION("""COMPUTED_VALUE"""),1.0) -> 1 | E14: =IFERROR(__xludf.DUMMYFUNCTION("""COMPUTED_VALUE"""),500.0) -> 500 | F14: =IFERROR(__xludf.DUMMYFUNCTION("""COMPUTED_VALUE"""),500.0) -> 500 | G14: =IFERROR(__xludf.DUMMYFUNCTION("""COMPUTED_VALUE"""),"Ayush Mandap") -> Ayush Mandap | I14: =IFERROR(__xludf.DUMMYFUNCTION("""COMPUTED_VALUE"""),0.0) -> 0 | J14: =IFERROR(__xludf.DUMMYFUNCTION("""COMPUTED_VALUE"""),500.0) -> 500 | K14: =IFERROR(__xludf.DUMMYFUNCTION("""COMPUTED_VALUE"""),1.0) -> 1 | L14: =IFERROR(__xludf.DUMMYFUNCTION("""COMPUTED_VALUE"""),0.0) -> 0
A15: =IFERROR(__xludf.DUMMYFUNCTION("""COMPUTED_VALUE"""),46208.0) -> 46208 | B15: =IFERROR(__xludf.DUMMYFUNCTION("""COMPUTED_VALUE"""),"CTRNG") -> CTRNG | C15: =IFERROR(__xludf.DUMMYFUNCTION("""COMPUTED_VALUE"""),"CTRNG") -> CTRNG | D15: =IFERROR(__xludf.DUMMYFUNCTION("""COMPUTED_VALUE"""),1.0) -> 1 | E15: =IFERROR(__xludf.DUMMYFUNCTION("""COMPUTED_VALUE"""),900.0) -> 900 | F15: =IFERROR(__xludf.DUMMYFUNCTION("""COMPUTED_VALUE"""),900.0) -> 900 | G15: =IFERROR(__xludf.DUMMYFUNCTION("""COMPUTED_VALUE"""),"Yogesh Caterers") -> Yogesh Caterers | J15: =IFERROR(__xludf.DUMMYFUNCTION("""COMPUTED_VALUE"""),900.0) -> 900 | K15: =IFERROR(__xludf.DUMMYFUNCTION("""COMPUTED_VALUE"""),1.0) -> 1 | L15: =IFERROR(__xludf.DUMMYFUNCTION("""COMPUTED_VALUE"""),0.0) -> 0
A16: =IFERROR(__xludf.DUMMYFUNCTION("""COMPUTED_VALUE"""),46210.0) -> 46210 | B16: =IFERROR(__xludf.DUMMYFUNCTION("""COMPUTED_VALUE"""),"THRMS") -> THRMS | C16: =IFERROR(__xludf.DUMMYFUNCTION("""COMPUTED_VALUE"""),"Thermos") -> Thermos | D16: =IFERROR(__xludf.DUMMYFUNCTION("""COMPUTED_VALUE"""),1.0) -> 1 | E16: =IFERROR(__xludf.DUMMYFUNCTION("""COMPUTED_VALUE"""),50.0) -> 50 | F16: =IFERROR(__xludf.DUMMYFUNCTION("""COMPUTED_VALUE"""),50.0) -> 50 | G16: =IFERROR(__xludf.DUMMYFUNCTION("""COMPUTED_VALUE"""),"CASH") -> CASH | J16: =IFERROR(__xludf.DUMMYFUNCTION("""COMPUTED_VALUE"""),50.0) -> 50 | K16: =IFERROR(__xludf.DUMMYFUNCTION("""COMPUTED_VALUE"""),1.0) -> 1 | L16: =IFERROR(__xludf.DUMMYFUNCTION("""COMPUTED_VALUE"""),0.0) -> 0 | M16: =IFERROR(__xludf.DUMMYFUNCTION("""COMPUTED_VALUE"""),"Bhagwat Pawar") -> Bhagwat Pawar
A17: =IFERROR(__xludf.DUMMYFUNCTION("""COMPUTED_VALUE"""),46213.0) -> 46213 | B17: =IFERROR(__xludf.DUMMYFUNCTION("""COMPUTED_VALUE"""),"AB") -> AB | C17: =IFERROR(__xludf.DUMMYFUNCTION("""COMPUTED_VALUE"""),"Ahuja Speaker") -> Ahuja Speaker | D17: =IFERROR(__xludf.DUMMYFUNCTION("""COMPUTED_VALUE"""),1.0) -> 1 | E17: =IFERROR(__xludf.DUMMYFUNCTION("""COMPUTED_VALUE"""),500.0) -> 500 | F17: =IFERROR(__xludf.DUMMYFUNCTION("""COMPUTED_VALUE"""),500.0) -> 500 | G17: =IFERROR(__xludf.DUMMYFUNCTION("""COMPUTED_VALUE"""),"CASH") -> CASH | J17: =IFERROR(__xludf.DUMMYFUNCTION("""COMPUTED_VALUE"""),500.0) -> 500 | K17: =IFERROR(__xludf.DUMMYFUNCTION("""COMPUTED_VALUE"""),1.0) -> 1 | L17: =IFERROR(__xludf.DUMMYFUNCTION("""COMPUTED_VALUE"""),0.0) -> 0
A18: =IFERROR(__xludf.DUMMYFUNCTION("""COMPUTED_VALUE"""),46213.0) -> 46213 | B18: =IFERROR(__xludf.DUMMYFUNCTION("""COMPUTED_VALUE"""),"CTRNG") -> CTRNG | C18: =IFERROR(__xludf.DUMMYFUNCTION("""COMPUTED_VALUE"""),"CTRNG") -> CTRNG | D18: =IFERROR(__xludf.DUMMYFUNCTION("""COMPUTED_VALUE"""),1.0) -> 1 | E18: =IFERROR(__xludf.DUMMYFUNCTION("""COMPUTED_VALUE"""),100.0) -> 100 | F18: =IFERROR(__xludf.DUMMYFUNCTION("""COMPUTED_VALUE"""),100.0) -> 100 | G18: =IFERROR(__xludf.DUMMYFUNCTION("""COMPUTED_VALUE"""),"CASH") -> CASH | J18: =IFERROR(__xludf.DUMMYFUNCTION("""COMPUTED_VALUE"""),100.0) -> 100 | M18: =IFERROR(__xludf.DUMMYFUNCTION("""COMPUTED_VALUE"""),"Prem Jangale") -> Prem Jangale
A19: =IFERROR(__xludf.DUMMYFUNCTION("""COMPUTED_VALUE"""),46213.0) -> 46213 | B19: =IFERROR(__xludf.DUMMYFUNCTION("""COMPUTED_VALUE"""),"CTRNG") -> CTRNG | C19: =IFERROR(__xludf.DUMMYFUNCTION("""COMPUTED_VALUE"""),"CTRNG") -> CTRNG | D19: =IFERROR(__xludf.DUMMYFUNCTION("""COMPUTED_VALUE"""),1.0) -> 1 | E19: =IFERROR(__xludf.DUMMYFUNCTION("""COMPUTED_VALUE"""),100.0) -> 100 | F19: =IFERROR(__xludf.DUMMYFUNCTION("""COMPUTED_VALUE"""),100.0) -> 100 | G19: =IFERROR(__xludf.DUMMYFUNCTION("""COMPUTED_VALUE"""),"CASH") -> CASH | J19: =IFERROR(__xludf.DUMMYFUNCTION("""COMPUTED_VALUE"""),100.0) -> 100
A20: =IFERROR(__xludf.DUMMYFUNCTION("""COMPUTED_VALUE"""),46213.0) -> 46213 | B20: =IFERROR(__xludf.DUMMYFUNCTION("""COMPUTED_VALUE"""),"SMI") -> SMI | C20: =IFERROR(__xludf.DUMMYFUNCTION("""COMPUTED_VALUE"""),"Samai") -> Samai | D20: =IFERROR(__xludf.DUMMYFUNCTION("""COMPUTED_VALUE"""),1.0) -> 1 | E20: =IFERROR(__xludf.DUMMYFUNCTION("""COMPUTED_VALUE"""),300.0) -> 300 | F20: =IFERROR(__xludf.DUMMYFUNCTION("""COMPUTED_VALUE"""),300.0) -> 300 | G20: =IFERROR(__xludf.DUMMYFUNCTION("""COMPUTED_VALUE"""),"CASH") -> CASH | J20: =IFERROR(__xludf.DUMMYFUNCTION("""COMPUTED_VALUE"""),300.0) -> 300 | M20: =IFERROR(__xludf.DUMMYFUNCTION("""COMPUTED_VALUE"""),"Indriya Jewellers") -> Indriya Jewellers
A21: =IFERROR(__xludf.DUMMYFUNCTION("""COMPUTED_VALUE"""),46210.0) -> 46210 | B21: =IFERROR(__xludf.DUMMYFUNCTION("""COMPUTED_VALUE"""),"GD SET") -> GD SET | C21: =IFERROR(__xludf.DUMMYFUNCTION("""COMPUTED_VALUE"""),"Gadi Set") -> Gadi Set | D21: =IFERROR(__xludf.DUMMYFUNCTION("""COMPUTED_VALUE"""),1.0) -> 1 | E21: =IFERROR(__xludf.DUMMYFUNCTION("""COMPUTED_VALUE"""),6000.0) -> 6000 | F21: =IFERROR(__xludf.DUMMYFUNCTION("""COMPUTED_VALUE"""),6000.0) -> 6000 | G21: =IFERROR(__xludf.DUMMYFUNCTION("""COMPUTED_VALUE"""),"Rajdhani Mandap") -> Rajdhani Mandap | I21: =IFERROR(__xludf.DUMMYFUNCTION("""COMPUTED_VALUE"""),4000.0) -> 4000 | J21: =IFERROR(__xludf.DUMMYFUNCTION("""COMPUTED_VALUE"""),2000.0) -> 2000

Sheet Inventory
A1: ITEM ID | B1: ITEM NAME | C1: STOCK AVAILABLE | D1: RENT | E1: STOCK IN | F1: STOCK OUT | G1: CURRENT STOCK | H1: MINIMUM STOCK LIMIT | I1: TOTAL REVENUE
A2: OP BAL | B2: Opening Balance | D2: 0 | E2: =SUMIF(Sales!B:B, A2, Sales!K:K) -> 0 | F2: =SUMIF(Sales!B:B, A2, Sales!D:D) -> 0 | G2: =E2-F2 -> 0 | I2: =SUMIF(Sales!C:C,B2,Sales!I:I) -> 0
A3: CTRNG | B3: CTRNG | D3: 0 | E3: =SUMIF(Sales!B:B, A3, Sales!K:K) -> 10 | F3: =SUMIF(Sales!B:B, A3, Sales!D:D) -> 14 | G3: =E3-F3 -> -4 | I3: =SUMIF(Sales!C:C,B3,Sales!I:I) -> 1875
A4: JC | B4: Jumbo Cooler | D4: 500 | E4: =SUMIF(Sales!B:B, A4, Sales!K:K) -> 0 | F4: =SUMIF(Sales!B:B, A4, Sales!D:D) -> 0 | G4: =E4-F4 -> 0 | I4: =SUMIF(Sales!C:C,B4,Sales!I:I) -> 0
A5: CH | B5: Chair | C5: 600 | D5: 4 | E5: =SUMIF(Sales!B:B, A5, Sales!K:K) -> 134 | F5: =SUMIF(Sales!B:B, A5, Sales!D:D) -> 186 | G5: =E5-F5 -> -52 | H5: 100 | I5: =SUMIF(Sales!C:C,B5,Sales!I:I) -> 660
A6: RTBL | B6: Round Table | D6: 125 | E6: =SUMIF(Sales!B:B, A6, Sales!K:K) -> 1 | F6: =SUMIF(Sales!B:B, A6, Sales!D:D) -> 1 | G6: =E6-F6 -> 0 | I6: =SUMIF(Sales!C:C,B6,Sales!I:I) -> 200
A7: FN | B7: Fan | D7: 100 | E7: =SUMIF(Sales!B:B, A7, Sales!K:K) -> 0 | F7: =SUMIF(Sales!B:B, A7, Sales!D:D) -> 4 | G7: =E7-F7 -> -4 | I7: =SUMIF(Sales!C:C,B7,Sales!I:I) -> 600
A8: GD | B8: Gadi | D8: 15 | E8: =SUMIF(Sales!B:B, A8, Sales!K:K) -> 11 | F8: =SUMIF(Sales!B:B, A8, Sales!D:D) -> 30 | G8: =E8-F8 -> -19 | I8: =SUMIF(Sales!C:C,B8,Sales!I:I) -> 450
A9: DRM | B9: Drum | D9: 20 | E9: =SUMIF(Sales!B:B, A9, Sales!K:K) -> 0 | F9: =SUMIF(Sales!B:B, A9, Sales!D:D) -> 1 | G9: =E9-F9 -> -1 | I9: =SUMIF(Sales!C:C,B9,Sales!I:I) -> 120
A10: TBL | B10: Table | D10: 20 | E10: =SUMIF(Sales!B:B, A10, Sales!K:K) -> 50 | F10: =SUMIF(Sales!B:B, A10, Sales!D:D) -> 64 | G10: =E10-F10 -> -14 | I10: =SUMIF(Sales!C:C,B10,Sales!I:I) -> 1500
A11: AB | B11: Ahuja Speaker | D11: 500 | E11: =SUMIF(Sales!B:B, A11, Sales!K:K) -> 1 | F11: =SUMIF(Sales!B:B, A11, Sales!D:D) -> 1 | G11: =E11-F11 -> 0 | I11: =SUMIF(Sales!C:C,B11,Sales!I:I) -> 0
A12: SMI | B12: Samai | D12: 300 | E12: =SUMIF(Sales!B:B, A12, Sales!K:K) -> 1 | F12: =SUMIF(Sales!B:B, A12, Sales!D:D) -> 2 | G12: =E12-F12 -> -1 | I12: =SUMIF(Sales!C:C,B12,Sales!I:I) -> 300
A13: WBS | B13: Wash Basin | D13: 200 | E13: =SUMIF(Sales!B:B, A13, Sales!K:K) -> 0 | F13: =SUMIF(Sales!B:B, A13, Sales!D:D) -> 0 | G13: =E13-F13 -> 0 | I13: =SUMIF(Sales!C:C,B13,Sales!I:I) -> 0
A14: BS | B14: Bedsheet | D14: 5 | E14: =SUMIF(Sales!B:B, A14, Sales!K:K) -> 0 | F14: =SUMIF(Sales!B:B, A14, Sales!D:D) -> 0 | G14: =E14-F14 -> 0 | I14: =SUMIF(Sales!C:C,B14,Sales!I:I) -> 0
A15: PLN | B15: Palna | D15: 500 | E15: =SUMIF(Sales!B:B, A15, Sales!K:K) -> 2 | F15: =SUMIF(Sales!B:B, A15, Sales!D:D) -> 2 | G15: =E15-F15 -> 0 | I15: =SUMIF(Sales!C:C,B15,Sales!I:I) -> 500
A16: Sm Culr | B16: Small Cooler | D16: 200 | E16: =SUMIF(Sales!B:B, A16, Sales!K:K) -> 0 | F16: =SUMIF(Sales!B:B, A16, Sales!D:D) -> 0 | G16: =E16-F16 -> 0 | I16: =SUMIF(Sales!C:C,B16,Sales!I:I) -> 0
A17: FRL | B17: Freel | D17: 30 | E17: =SUMIF(Sales!B:B, A17, Sales!K:K) -> 5 | F17: =SUMIF(Sales!B:B, A17, Sales!D:D) -> 5 | G17: =E17-F17 -> 0 | I17: =SUMIF(Sales!C:C,B17,Sales!I:I) -> 150
... A56: DIAS | B56: Podium | D56: 300 | E56: =SUMIF(Sales!B:B, A56, Sales!K:K) -> 0 | F56: =SUMIF(Sales!B:B, A56, Sales!D:D) -> 0 | G56: =E56-F56 -> 0 | I56: =SUMIF(Sales!C:C,B56,Sales!I:I) -> 0

Sheet Customers
A1: Shop Name | B1: Name | C1: Category | D1: Contact Number | E1: Alternate Number | F1: Address | G1: Reference | H1: O/P balance | I1: Column 1
A2: Ayush Mandap | B2: Ajay Kulkarni | C2: Mandap | H2: =SUMIF(Sales!G:G,A2,Sales!J:J)-SUMIF(Sales!G:G,A2,Sales!I:I) -> -1250
A3: Ganesh Mandap T | B3: Shyam Thakur | C3: Mandap | H3: =SUMIF(Sales!G:G,A3,Sales!J:J)-SUMIF(Sales!G:G,A3,Sales!I:I) -> 750 | I3: विष्णु ठाकूर
A4: Yogesh Caterers | B4: Anand Bansode | C4: Caterers | H4: =SUMIF(Sales!G:G,A4,Sales!J:J)-SUMIF(Sales!G:G,A4,Sales!I:I) -> 550
A5: Tulja Bhavani Mandap | B5: Sanju Khoje | C5: Mandap | H5: =SUMIF(Sales!G:G,A5,Sales!J:J)-SUMIF(Sales!G:G,A5,Sales!I:I) -> 360 | I5: तुळजा भवानी मंडप
A6: Abhiman Kharat | B6: Abhiman Kharat | C6: Caterers | H6: =SUMIF(Sales!G:G,A6,Sales!J:J)-SUMIF(Sales!G:G,A6,Sales!I:I) -> 130
A7: G S Event | B7: Guddu Shinde | C7: Mandap | H7: =SUMIF(Sales!G:G,A7,Sales!J:J)-SUMIF(Sales!G:G,A7,Sales!I:I) -> 0 | I7: गुड्डू शिंदे
A8: Jay Hari Mandap | B8: Krushna Panchal | C8: Mandap | H8: =SUMIF(Sales!G:G,A8,Sales!J:J)-SUMIF(Sales!G:G,A8,Sales!I:I) -> 0 | I8: पांचाळ महाराज
A9: Maitri Mandap | B9: Sanket Yeole | C9: Mandap | H9: =SUMIF(Sales!G:G,A9,Sales!J:J)-SUMIF(Sales!G:G,A9,Sales!I:I) -> 0 | I9: संकेत येवले
A10: Pruthviraj Mandap | B10: Kishor Bhalerao | C10: Mandap | H10: =SUMIF(Sales!G:G,A10,Sales!J:J)-SUMIF(Sales!G:G,A10,Sales!I:I) -> -600 | I10: पृथ्वीराज मंडप
A11: Ankit bajaj | B11: Ankit bajaj | C11: Mandap | H11: =SUMIF(Sales!G:G,A11,Sales!J:J)-SUMIF(Sales!G:G,A11,Sales!I:I) -> 0
A12: Saileela Caterers | B12: Sandeep Sontakke | C12: Caterers | H12: =SUMIF(Sales!G:G,A12,Sales!J:J)-SUMIF(Sales!G:G,A12,Sales!I:I) -> 0 | I12: संदीप सोनटक्के
A13: Sant Shiromani Mandap | B13: Babasaheb Dabhade | C13: Mandap | H13: =SUMIF(Sales!G:G,A13,Sales!J:J)-SUMIF(Sales!G:G,A13,Sales!I:I) -> 0 | I13: संत शिरोमणी मंडप
A14: Ajay Mandap | B14: Ajay Kharat | C14: Mandap | H14: =SUMIF(Sales!G:G,A14,Sales!J:J)-SUMIF(Sales!G:G,A14,Sales!I:I) -> 0 | I14: अजय खरात
A15: Sai Pooja Caterers | B15: Sunil Nayar | C15: Caterers | H15: =SUMIF(Sales!G:G,A15,Sales!J:J)-SUMIF(Sales!G:G,A15,Sales!I:I) -> 0 | I15: सुनील नायर
A16: Pathare Mandap | B16: Sachin Pathare | C16: Mandap | H16: =SUMIF(Sales!G:G,A16,Sales!J:J)-SUMIF(Sales!G:G,A16,Sales!I:I) -> 0 | I16: पठारे मंडप
A17: Golden Mandap | B17: Altaf Patel | C17: Mandap | H17: =SUMIF(Sales!G:G,A17,Sales!J:J)-SUMIF(Sales!G:G,A17,Sales!I:I) -> 0 | I17: गोल्डन मंडप
A18: Hotel Ecotel | B18: Kshirsagar | C18: Mandap | H18: =SUMIF(Sales!G:G,A18,Sales!J:J)-SUMIF(Sales!G:G,A18,Sales!I:I) -> 0
A19: Nilesh Chaudahary | B19: Nilesh Chaudahary | C19: Mandap | H19: =SUMIF(Sales!G:G,A19,Sales!J:J)-SUMIF(Sales!G:G,A19,Sales!I:I) -> 0
A20: Renuka Mandap | B20: Rohidas Igve | C20: Mandap | H20: =SUMIF(Sales!G:G,A20,Sales!J:J)-SUMIF(Sales!G:G,A20,Sales!I:I) -> 0
A21: Gautam Kirtikar | B21: Gautam Kirtikar | C21: Mandap | H21: =SUMIF(Sales!G:G,A21,Sales!J:J)-SUMIF(Sales!G:G,A21,Sales!I:I) -> 0
A22: Pawan Dhakne | B22: Pawan Dhakne | C22: Caterers | H22: =SUMIF(Sales!G:G,A22,Sales!J:J)-SUMIF(Sales!G:G,A22,Sales!I:I) -> 0
A23: Sai Shraddha Caterers | B23: Kishor Shinde | C23: Caterers | H23: =SUMIF(Sales!G:G,A23,Sales!J:J)-SUMIF(Sales!G:G,A23,Sales!I:I) -> 0 | I23: किशोर शिंदे
A24: B R Mandap | B24: PArvez Shaikh | C24: Mandap | H24: =SUMIF(Sales!G:G,A24,Sales!J:J)-SUMIF(Sales!G:G,A24,Sales!I:I) -> 0 | I24: बि आर मंडप
A25: Abdul Rikshaw | B25: Abdul Rikshaw | C25: Mandap | H25: =SUMIF(Sales!G:G,A25,Sales!J:J)-SUMIF(Sales!G:G,A25,Sales!I:I) -> 0
A26: Matoshree lawns | B26: Sachin Wagh | C26: Mandap | H26: =SUMIF(Sales!G:G,A26,Sales!J:J)-SUMIF(Sales!G:G,A26,Sales!I:I) -> 0
A27: Dipak Nikam | B27: Dipak Nikam | C27: Mandap | H27: =SUMIF(Sales!G:G,A27,Sales!J:J)-SUMIF(Sales!G:G,A27,Sales!I:I) -> 0
A28: Balaji Mandap G | B28: Giriraj Uplenchwar | C28: Mandap | H28: =SUMIF(Sales!G:G,A28,Sales!J:J)-SUMIF(Sales!G:G,A28,Sales!I:I) -> 0 | I28: बालाजी मंडप
A29: Kishor Mandap | B29: Kishor Chaudhari | C29: Mandap | H29: =SUMIF(Sales!G:G,A29,Sales!J:J)-SUMIF(Sales!G:G,A29,Sales!I:I) -> 0
A30: Mahadev Umrikar | B30: Mahadev Umrikar | C30: Caterers | H30: =SUMIF(Sales!G:G,A30,Sales!J:J)-SUMIF(Sales!G:G,A30,Sales!I:I) -> 0
A31: Balaji Mandap K | B31: Khandre Mama | C31: Mandap | H31: =SUMIF(Sales!G:G,A31,Sales!J:J)-SUMIF(Sales!G:G,A31,Sales!I:I) -> 0
A32: Dashrath Caterers | B32: Babasaheb Borade | C32: Caterers | H32: =SUMIF(Sales!G:G,A32,Sales!J:J)-SUMIF(Sales!G:G,A32,Sales!I:I) -> 0
A33: Dip Mandap | B33: Bhagwat Pawar | C33: Mandap | H33: =SUMIF(Sales!G:G,A33,Sales!J:J)-SUMIF(Sales!G:G,A33,Sales!I:I) -> -350
A34: Dipak Nawale | B34: Dipak Nawale | C34: Mandap | H34: =SUMIF(Sales!G:G,A34,Sales!J:J)-SUMIF(Sales!G:G,A34,Sales!I:I) -> 0
A35: Ganesh Mandap K | B35: Ganesh Kale | C35: Mandap | H35: =SUMIF(Sales!G:G,A35,Sales!J:J)-SUMIF(Sales!G:G,A35,Sales!I:I) -> 0
A36: Kshirsagar Mandap R | B36: Raju Kshirsagar | C36: Mandap | H36: =SUMIF(Sales!G:G,A36,Sales!J:J)-SUMIF(Sales!G:G,A36,Sales!I:I) -> 0
A37: Kshirsagar Mandap S | B37: Shyam Kshirsagar | C37: Mandap | H37: =SUMIF(Sales!G:G,A37,Sales!J:J)-SUMIF(Sales!G:G,A37,Sales!I:I) -> 0
A38: Mahalakshmi Mandap | B38: Abasaheb Tawar | C38: Mandap | H38: =SUMIF(Sales!G:G,A38,Sales!J:J)-SUMIF(Sales!G:G,A38,Sales!I:I) -> -140
A39: Mauli Mandap | B39: Shravan Vaidya | C39: Mandap | H39: =SUMIF(Sales!G:G,A39,Sales!J:J)-SUMIF(Sales!G:G,A39,Sales!I:I) -> 0
A40: Sachin Mandap | B40: Jaydave Gande | C40: Mandap | H40: =SUMIF(Sales!G:G,A40,Sales!J:J)-SUMIF(Sales!G:G,A40,Sales!I:I) -> 0
... A77: Samarth Sound | B77: Ganesh Karangale | C77: Mandap | H77: =SUMIF(Sales!G:G,A77,Sales!J:J)-SUMIF(Sales!G:G,A77,Sales!I:I) -> -950
A78: Atul Salve | B78: Atul Salve | C78: Mandap | H78: =SUMIF(Sales!G:G,A78,Sales!J:J)-SUMIF(Sales!G:G,A78,Sales!I:I) -> -2000 | I78: अतुल साळवे
A79: CASH | B79: Cash Customer | C79: Mandap | H79: =SUMIF(Sales!G:G,A79,Sales!J:J)-SUMIF(Sales!G:G,A79,Sales!I:I) -> -4215
A80: Shri Decorators | B80: Pramod Pawar | C80: Mandap | H80: =SUMIF(Sales!G:G,A80,Sales!J:J)-SUMIF(Sales!G:G,A80,Sales!I:I) -> -300
A81: Rajdhani Mandap | B81: Dipak Bagul | C81: Mandap | H81: =SUMIF(Sales!G:G,A81,Sales!J:J)-SUMIF(Sales!G:G,A81,Sales!I:I) -> -2000

Sheet Purchases
A1: DATE | B1: ITEM ID | C1: ITEM NAME | D1: QUANTITY | E1: COST | F1: TOTAL
C2: {=_xlfn.XLOOKUP(B2, Inventory!A:A, Inventory!B:B, "Not Found")} -> Not Found | E2: {=_xlfn.XLOOKUP(B2, Inventory!A:A, Inventory!C:C, 0)} -> 0 | F2: =D2*E2 -> 0
C3: {=_xlfn.XLOOKUP(B3, Inventory!A:A, Inventory!B:B, "Not Found")} -> Not Found | E3: {=_xlfn.XLOOKUP(B3, Inventory!A:A, Inventory!C:C, 0)} -> 0 | F3: =D3*E3 -> 0
C4: {=_xlfn.XLOOKUP(B4, Inventory!A:A, Inventory!B:B, "Not Found")} -> Not Found | E4: {=_xlfn.XLOOKUP(B4, Inventory!A:A, Inventory!C:C, 0)} -> 0 | F4: =D4*E4 -> 0
C5: {=_xlfn.XLOOKUP(B5, Inventory!A:A, Inventory!B:B, "Not Found")} -> Not Found | E5: {=_xlfn.XLOOKUP(B5, Inventory!A:A, Inventory!C:C, 0)} -> 0 | F5: =D5*E5 -> 0
C6: {=_xlfn.XLOOKUP(B6, Inventory!A:A, Inventory!B:B, "Not Found")} -> Not Found | E6: {=_xlfn.XLOOKUP(B6, Inventory!A:A, Inventory!C:C, 0)} -> 0 | F6: =D6*E6 -> 0
C7: {=_xlfn.XLOOKUP(B7, Inventory!A:A, Inventory!B:B, "Not Found")} -> Not Found | E7: {=_xlfn.XLOOKUP(B7, Inventory!A:A, Inventory!C:C, 0)} -> 0 | F7: =D7*E7 -> 0
C8: {=_xlfn.XLOOKUP(B8, Inventory!A:A, Inventory!B:B, "Not Found")} -> Not Found | E8: {=_xlfn.XLOOKUP(B8, Inventory!A:A, Inventory!C:C, 0)} -> 0 | F8: =D8*E8 -> 0
C9: {=_xlfn.XLOOKUP(B9, Inventory!A:A, Inventory!B:B, "Not Found")} -> Not Found | E9: {=_xlfn.XLOOKUP(B9, Inventory!A:A, Inventory!C:C, 0)} -> 0 | F9: =D9*E9 -> 0
C10: {=_xlfn.XLOOKUP(B10, Inventory!A:A, Inventory!B:B, "Not Found")} -> Not Found | E10: {=_xlfn.XLOOKUP(B10, Inventory!A:A, Inventory!C:C, 0)} -> 0 | F10: =D10*E10 -> 0
C11: {=_xlfn.XLOOKUP(B11, Inventory!A:A, Inventory!B:B, "Not Found")} -> Not Found | E11: {=_xlfn.XLOOKUP(B11, Inventory!A:A, Inventory!C:C, 0)} -> 0 | F11: =D11*E11 -> 0
C12: {=_xlfn.XLOOKUP(B12, Inventory!A:A, Inventory!B:B, "Not Found")} -> Not Found | E12: {=_xlfn.XLOOKUP(B12, Inventory!A:A, Inventory!C:C, 0)} -> 0 | F12: =D12*E12 -> 0
C13: {=_xlfn.XLOOKUP(B13, Inventory!A:A, Inventory!B:B, "Not Found")} -> Not Found | E13: {=_xlfn.XLOOKUP(B13, Inventory!A:A, Inventory!C:C, 0)} -> 0 | F13: =D13*E13 -> 0
... C34: {=_xlfn.XLOOKUP(B34, Inventory!A:A, Inventory!B:B, "Not Found")} -> Not Found | E34: {=_xlfn.XLOOKUP(B34, Inventory!A:A, Inventory!C:C, 0)} -> 0 | F34: =D34*E34 -> 0
